Workbook
Name Всебайки1: #REF!
Name проданныебайки: 'список мото'!$F$3:$F$100
Name Всемото: 'список мото'!$A:$A

Sheet клиенты
B1: AUTO CNCL | C1: Название мото | D1: Имя | E1: Дата начала | F1: Дата завершения | G1: Срок | H1: Платеж в день | I1: Долг | J1: К оплате на данный момент | K1: Оплачено | L1: Платеж в месяц (для скрипта) | M1: Платеж в день (для скрипта) | N1: Пробег на момент сдачи | O1: Последняя замена масла | P1: После последней замены масла | Q1: Текущий пробег с датой | R1: Дата отметки текущего пробега | S1: Залог | T1: Шлем | U1: Контакты | V1: Примечание | W1: Для скрипта и проверки | X1: Тип для скрипта
A2: Завершена | B2: OFF | C2: PCX 150CC GREY PHUKET 778 | D2: Рената | E2: 44812 | F2: 44819 | G2: =IF((E2="")+(F2=""), "", IF(DATEDIF(E2, F2, "d") > 30, DATEDIF(E2, F2, "m") & " М", DATEDIF(E2, F2, "d") & " Д")) -> 7 Д | H2: =1500/7 -> 214.28571 | I2: =IF(OR(A2="в аренде", A2="в аренде 1", A2="в аренде 2"), J2-K2, "") | J2: =IF(OR(A2="в аренде", A2="в аренде 1", A2="в аренде 2"), DATEDIF(E2, TODAY(), "D")*H2, "") | K2: 1500 | N2: 15970 | O2: =IFERROR(__xludf.DUMMYFUNCTION("IFERROR( VLOOKUP(C2, FILTER( IMPORTRANGE(""https://docs.google.com/spreadsheets/d/1ZBCmVvzoFu7X0td7O5T5xSJplK8m8h9wvdESBc0a1EE/edit#gid=1841437934"", ""Лист1!$C:$I""), IMPORTRANGE(""https://docs.google.com/spreadsheets/d/1ZBCmVvzoFu7X0t"&"d7O5T5xSJplK8m8h9wvdESBc0a1EE/edit#gid=1841437934"", ""Лист1!$C:$C"") = C2 ), 7, FALSE ), """" ) "),"") | P2: =IFERROR(__xludf.DUMMYFUNCTION("IF(OR(ISBLANK(Q2), ISBLANK(O2), VALUE(SUBSTITUTE(INDEX(SPLIT(IF(ISBLANK(R2), Q2, R2), "" km""), 0, 1), "" "", """")) - O2 = 0), """", IF(ISBLANK(R2), VALUE(SUBSTITUTE(INDEX(SPLIT(Q2, "" km""), 0, 1), "" "", """")) - O2, VALUE(SUBSTITUTE(INDEX(SPLIT(R2, """&" km""), 0, 1), "" "", """")) - O2))"),"#VALUE!") -> #VALUE! | Q2: =IF(AND(ISBLANK(N2), ISBLANK(E2), ISBLANK(R2)), "", IF(ISBLANK(R2), TEXT(N2, "#,##0") & " Km, " & TEXT(E2, "dd.mm.yyyy"), R2)) -> коцки низа | R2: коцки низа | S2: 500 вычел | T2: 1 | U2: @Arreeonelove +918767219725 | V2: пьяненькая неуверненная | W2: =IF(F2 = "", "", IF(NOW() > (DATEVALUE(LEFT(F2, SEARCH(",", F2) - 2)) + TIMEVALUE(MID(F2, SEARCH(",", F2) + 2, 5))), "Завершена", "В аренде")) -> Завершена | X2: =IFERROR(__xludf.DUMMYFUNCTION("IF(C2 = """", """", IF(REGEXMATCH(C2, ""PCX|NMAX|ADV|CLICK""), ""скутер"", ""мото""))"),"скутер") -> скутер
A3: Завершена | B3: OFF | C3: XMAX 300CC GREY PHUKET 4246 | D3: Сергей | E3: 44817 | F3: 44908 | G3: =IF((E3="")+(F3=""), "", IF(DATEDIF(E3, F3, "d") > 30, DATEDIF(E3, F3, "m") & " М", DATEDIF(E3, F3, "d") & " Д")) -> 3 М | H3: 333.33 | I3: =IF(OR(A3="в аренде", A3="в аренде 1", A3="в аренде 2"), J3-K3, "") | J3: =IF(OR(A3="в аренде", A3="в аренде 1", A3="в аренде 2"), DATEDIF(E3, TODAY(), "D")*H3, "") | K3: 20000 | N3: 11080 | O3: =IFERROR(__xludf.DUMMYFUNCTION("IFERROR( VLOOKUP(C3, FILTER( IMPORTRANGE(""https://docs.google.com/spreadsheets/d/1ZBCmVvzoFu7X0td7O5T5xSJplK8m8h9wvdESBc0a1EE/edit#gid=1841437934"", ""Лист1!$C:$I""), IMPORTRANGE(""https://docs.google.com/spreadsheets/d/1ZBCmVvzoFu7X0t"&"d7O5T5xSJplK8m8h9wvdESBc0a1EE/edit#gid=1841437934"", ""Лист1!$C:$C"") = C3 ), 7, FALSE ), """" ) "),38640.0) -> 38640 | P3: =IFERROR(__xludf.DUMMYFUNCTION("IF(OR(ISBLANK(Q3), ISBLANK(O3), VALUE(SUBSTITUTE(INDEX(SPLIT(IF(ISBLANK(R3), Q3, R3), "" km""), 0, 1), "" "", """")) - O3 = 0), """", IF(ISBLANK(R3), VALUE(SUBSTITUTE(INDEX(SPLIT(Q3, "" km""), 0, 1), "" "", """")) - O3, VALUE(SUBSTITUTE(INDEX(SPLIT(R3, """&" km""), 0, 1), "" "", """")) - O3))"),-27560.0) -> -27560 | Q3: =IF(AND(ISBLANK(N3), ISBLANK(E3), ISBLANK(R3)), "", IF(ISBLANK(R3), TEXT(N3, "#,##0") & " Km, " & TEXT(E3, "dd.mm.yyyy"), R3)) -> 11 080 Km, 13.09.2022 | S3: 5000 | T3: - | U3: @penytwice +66617412035 | V3: вроде опытный живет в тае | W3: =IF(F3 = "", "", IF(NOW() > (DATEVALUE(LEFT(F3, SEARCH(",", F3) - 2)) + TIMEVALUE(MID(F3, SEARCH(",", F3) + 2, 5))), "Завершена", "В аренде")) -> Завершена | X3: =IFERROR(__xludf.DUMMYFUNCTION("IF(C3 = """", """", IF(REGEXMATCH(C3, ""PCX|NMAX|ADV|CLICK""), ""скутер"", ""мото""))"),"мото") -> мото
A4: Завершена | B4: OFF | C4: FORZA 300CC GREY PHUKET 4234 | D4: Андрей | E4: 44835 | F4: 44866 | G4: =IF((E4="")+(F4=""), "", IF(DATEDIF(E4, F4, "d") > 30, DATEDIF(E4, F4, "m") & " М", DATEDIF(E4, F4, "d") & " Д")) -> 1 М | H4: =11000/30 -> 366.66667 | I4: =IF(OR(A4="в аренде", A4="в аренде 1", A4="в аренде 2"), J4-K4, "") | J4: =IF(OR(A4="в аренде", A4="в аренде 1", A4="в аренде 2"), DATEDIF(E4, TODAY(), "D")*H4, "") | K4: 11000 | N4: 17273 | O4: =IFERROR(__xludf.DUMMYFUNCTION("IFERROR( VLOOKUP(C4, FILTER( IMPORTRANGE(""https://docs.google.com/spreadsheets/d/1ZBCmVvzoFu7X0td7O5T5xSJplK8m8h9wvdESBc0a1EE/edit#gid=1841437934"", ""Лист1!$C:$I""), IMPORTRANGE(""https://docs.google.com/spreadsheets/d/1ZBCmVvzoFu7X0t"&"d7O5T5xSJplK8m8h9wvdESBc0a1EE/edit#gid=1841437934"", ""Лист1!$C:$C"") = C4 ), 7, FALSE ), """" ) "),"") | P4: =IFERROR(__xludf.DUMMYFUNCTION("IF(OR(ISBLANK(Q4), ISBLANK(O4), VALUE(SUBSTITUTE(INDEX(SPLIT(IF(ISBLANK(R4), Q4, R4), "" km""), 0, 1), "" "", """")) - O4 = 0), """", IF(ISBLANK(R4), VALUE(SUBSTITUTE(INDEX(SPLIT(Q4, "" km""), 0, 1), "" "", """")) - O4, VALUE(SUBSTITUTE(INDEX(SPLIT(R4, """&" km""), 0, 1), "" "", """")) - O4))"),17273.0) -> 17273 | Q4: =IF(AND(ISBLANK(N4), ISBLANK(E4), ISBLANK(R4)), "", IF(ISBLANK(R4), TEXT(N4, "#,##0") & " Km, " & TEXT(E4, "dd.mm.yyyy"), R4)) -> 17 273 Km, 01.10.2022 | S4: 5000 | T4: 2 | U4: @marbok 943375719 | V4: гуд мотоджимхана | W4: =IF(F4 = "", "", IF(NOW() > (DATEVALUE(LEFT(F4, SEARCH(",", F4) - 2)) + TIMEVALUE(MID(F4, SEARCH(",", F4) + 2, 5))), "Завершена", "В аренде")) -> Завершена | X4: =IFERROR(__xludf.DUMMYFUNCTION("IF(C4 = """", """", IF(REGEXMATCH(C4, ""PCX|NMAX|ADV|CLICK""), ""скутер"", ""мото""))"),"мото") -> мото
A5: Завершена | B5: OFF | C5: PCX 150CC GREY PHUKET 778 | D5: Никита Моисеев | E5: 44837 | F5: 44844 | G5: =IF((E5="")+(F5=""), "", IF(DATEDIF(E5, F5, "d") > 30, DATEDIF(E5, F5, "m") & " М", DATEDIF(E5, F5, "d") & " Д")) -> 7 Д | H5: 250 | I5: =IF(OR(A5="в аренде", A5="в аренде 1", A5="в аренде 2"), J5-K5, "") | J5: =IF(OR(A5="в аренде", A5="в аренде 1", A5="в аренде 2"), DATEDIF(E5, TODAY(), "D")*H5, "") | K5: 1500 | N5: 16200 | O5: =IFERROR(__xludf.DUMMYFUNCTION("IFERROR( VLOOKUP(C5, FILTER( IMPORTRANGE(""https://docs.google.com/spreadsheets/d/1ZBCmVvzoFu7X0td7O5T5xSJplK8m8h9wvdESBc0a1EE/edit#gid=1841437934"", ""Лист1!$C:$I""), IMPORTRANGE(""https://docs.google.com/spreadsheets/d/1ZBCmVvzoFu7X0t"&"d7O5T5xSJplK8m8h9wvdESBc0a1EE/edit#gid=1841437934"", ""Лист1!$C:$C"") = C5 ), 7, FALSE ), """" ) "),"") | P5: =IFERROR(__xludf.DUMMYFUNCTION("IF(OR(ISBLANK(Q5), ISBLANK(O5), VALUE(SUBSTITUTE(INDEX(SPLIT(IF(ISBLANK(R5), Q5, R5), "" km""), 0, 1), "" "", """")) - O5 = 0), """", IF(ISBLANK(R5), VALUE(SUBSTITUTE(INDEX(SPLIT(Q5, "" km""), 0, 1), "" "", """")) - O5, VALUE(SUBSTITUTE(INDEX(SPLIT(R5, """&" km""), 0, 1), "" "", """")) - O5))"),16200.0) -> 16200 | Q5: =IF(AND(ISBLANK(N5), ISBLANK(E5), ISBLANK(R5)), "", IF(ISBLANK(R5), TEXT(N5, "#,##0") & " Km, " & TEXT(E5, "dd.mm.yyyy"), R5)) -> 16 200 Km, 03.10.2022 | S5: 3000 | T5: 2 | U5: @spacegilly +79958803610 | V5: Мутный Арбитражник возможно скамер | W5: =IF(F5 = "", "", IF(NOW() > (DATEVALUE(LEFT(F5, SEARCH(",", F5) - 2)) + TIMEVALUE(MID(F5, SEARCH(",", F5) + 2, 5))), "Завершена", "В аренде")) -> Завершена | X5: =IFERROR(__xludf.DUMMYFUNCTION("IF(C5 = """", """", IF(REGEXMATCH(C5, ""PCX|NMAX|ADV|CLICK""), ""скутер"", ""мото""))"),"скутер") -> скутер
A6: Завершена | B6: OFF | C6: NMAX 155CC GREEN-B PHUKET 4957 | D6: Andrei друг | E6: 44852 | F6: 44975 | G6: =IF((E6="")+(F6=""), "", IF(DATEDIF(E6, F6, "d") > 30, DATEDIF(E6, F6, "m") & " М", DATEDIF(E6, F6, "d") & " Д")) -> 4 М | H6: =5800/30 -> 193.33333 | I6: =IF(OR(A6="в аренде", A6="в аренде 1", A6="в аренде 2"), J6-K6, "") | J6: =IF(OR(A6="в аренде", A6="в аренде 1", A6="в аренде 2"), DATEDIF(E6, TODAY(), "D")*H6, "") | K6: =5800+5800+5800+1500 -> 18900 | N6: 12800 | O6: =IFERROR(__xludf.DUMMYFUNCTION("IFERROR( VLOOKUP(C6, FILTER( IMPORTRANGE(""https://docs.google.com/spreadsheets/d/1ZBCmVvzoFu7X0td7O5T5xSJplK8m8h9wvdESBc0a1EE/edit#gid=1841437934"", ""Лист1!$C:$I""), IMPORTRANGE(""https://docs.google.com/spreadsheets/d/1ZBCmVvzoFu7X0t"&"d7O5T5xSJplK8m8h9wvdESBc0a1EE/edit#gid=1841437934"", ""Лист1!$C:$C"") = C6 ), 7, FALSE ), """" ) "),30800.0) -> 30800 | P6: =IFERROR(__xludf.DUMMYFUNCTION("IF(OR(ISBLANK(Q6), ISBLANK(O6), VALUE(SUBSTITUTE(INDEX(SPLIT(IF(ISBLANK(R6), Q6, R6), "" km""), 0, 1), "" "", """")) - O6 = 0), """", IF(ISBLANK(R6), VALUE(SUBSTITUTE(INDEX(SPLIT(Q6, "" km""), 0, 1), "" "", """")) - O6, VALUE(SUBSTITUTE(INDEX(SPLIT(R6, """&" km""), 0, 1), "" "", """")) - O6))"),-18000.0) -> -18000 | Q6: =IF(AND(ISBLANK(N6), ISBLANK(E6), ISBLANK(R6)), "", IF(ISBLANK(R6), TEXT(N6, "#,##0") & " Km, " & TEXT(E6, "dd.mm.yyyy"), R6)) -> 12 800 Km, 18.10.2022 | S6: 3000 | T6: 1 | U6: @Maskellanear +6695291890 | V6: молодой но вроде опыт есть | W6: =IF(F6 = "", "", IF(NOW() > (DATEVALUE(LEFT(F6, SEARCH(",", F6) - 2)) + TIMEVALUE(MID(F6, SEARCH(",", F6) + 2, 5))), "Завершена", "В аренде")) -> Завершена | X6: =IFERROR(__xludf.DUMMYFUNCTION("IF(C6 = """", """", IF(REGEXMATCH(C6, ""PCX|NMAX|ADV|CLICK""), ""скутер"", ""мото""))"),"скутер") -> скутер
A7: Завершена | B7: OFF | C7: NMAX 155CC BLACK GREEN PHUKET 4253 | D7: Дарья | E7: 44854 | F7: 45005 | G7: =IF((E7="")+(F7=""), "", IF(DATEDIF(E7, F7, "d") > 30, DATEDIF(E7, F7, "m") & " М", DATEDIF(E7, F7, "d") & " Д")) -> 5 М | H7: =6000/30 -> 200 | I7: =IF(OR(A7="в аренде", A7="в аренде 1", A7="в аренде 2"), J7-K7, "") | J7: =IF(OR(A7="в аренде", A7="в аренде 1", A7="в аренде 2"), DATEDIF(E7, TODAY(), "D")*H7, "") | K7: =6000+6000+6000+6000 -> 24000 | N7: 17300 | O7: =IFERROR(__xludf.DUMMYFUNCTION("IFERROR( VLOOKUP(C7, FILTER( IMPORTRANGE(""https://docs.google.com/spreadsheets/d/1ZBCmVvzoFu7X0td7O5T5xSJplK8m8h9wvdESBc0a1EE/edit#gid=1841437934"", ""Лист1!$C:$I""), IMPORTRANGE(""https://docs.google.com/spreadsheets/d/1ZBCmVvzoFu7X0t"&"d7O5T5xSJplK8m8h9wvdESBc0a1EE/edit#gid=1841437934"", ""Лист1!$C:$C"") = C7 ), 7, FALSE ), """" ) "),35800.0) -> 35800 | P7: =IFERROR(__xludf.DUMMYFUNCTION("IF(OR(ISBLANK(Q7), ISBLANK(O7), VALUE(SUBSTITUTE(INDEX(SPLIT(IF(ISBLANK(R7), Q7, R7), "" km""), 0, 1), "" "", """")) - O7 = 0), """", IF(ISBLANK(R7), VALUE(SUBSTITUTE(INDEX(SPLIT(Q7, "" km""), 0, 1), "" "", """")) - O7, VALUE(SUBSTITUTE(INDEX(SPLIT(R7, """&" km""), 0, 1), "" "", """")) - O7))"),-18500.0) -> -18500 | Q7: =IF(AND(ISBLANK(N7), ISBLANK(E7), ISBLANK(R7)), "", IF(ISBLANK(R7), TEXT(N7, "#,##0") & " Km, " & TEXT(E7, "dd.mm.yyyy"), R7)) -> 17 300 Km, 20.10.2022 | S7: 3000 | T7: - | U7: @daria2dare | V7: на вид ок | W7: =IF(F7 = "", "", IF(NOW() > (DATEVALUE(LEFT(F7, SEARCH(",", F7) - 2)) + TIMEVALUE(MID(F7, SEARCH(",", F7) + 2, 5))), "Завершена", "В аренде")) -> Завершена | X7: =IFERROR(__xludf.DUMMYFUNCTION("IF(C7 = """", """", IF(REGEXMATCH(C7, ""PCX|NMAX|ADV|CLICK""), ""скутер"", ""мото""))"),"скутер") -> скутер
A8: Завершена | B8: OFF | C8: CLICK 125CC PHUKET 5580 | D8: Дима | E8: 44855 | F8: 44886 | G8: =IF((E8="")+(F8=""), "", IF(DATEDIF(E8, F8, "d") > 30, DATEDIF(E8, F8, "m") & " М", DATEDIF(E8, F8, "d") & " Д")) -> 1 М | H8: =4000/30 -> 133.33333 | I8: =IF(OR(A8="в аренде", A8="в аренде 1", A8="в аренде 2"), J8-K8, "") | J8: =IF(OR(A8="в аренде", A8="в аренде 1", A8="в аренде 2"), DATEDIF(E8, TODAY(), "D")*H8, "") | K8: 4000 | N8: 26720 | O8: =IFERROR(__xludf.DUMMYFUNCTION("IFERROR( VLOOKUP(C8, FILTER( IMPORTRANGE(""https://docs.google.com/spreadsheets/d/1ZBCmVvzoFu7X0td7O5T5xSJplK8m8h9wvdESBc0a1EE/edit#gid=1841437934"", ""Лист1!$C:$I""), IMPORTRANGE(""https://docs.google.com/spreadsheets/d/1ZBCmVvzoFu7X0t"&"d7O5T5xSJplK8m8h9wvdESBc0a1EE/edit#gid=1841437934"", ""Лист1!$C:$C"") = C8 ), 7, FALSE ), """" ) "),33515.0) -> 33515 | P8: =IFERROR(__xludf.DUMMYFUNCTION("IF(OR(ISBLANK(Q8), ISBLANK(O8), VALUE(SUBSTITUTE(INDEX(SPLIT(IF(ISBLANK(R8), Q8, R8), "" km""), 0, 1), "" "", """")) - O8 = 0), """", IF(ISBLANK(R8), VALUE(SUBSTITUTE(INDEX(SPLIT(Q8, "" km""), 0, 1), "" "", """")) - O8, VALUE(SUBSTITUTE(INDEX(SPLIT(R8, """&" km""), 0, 1), "" "", """")) - O8))"),-6795.0) -> -6795 | Q8: =IF(AND(ISBLANK(N8), ISBLANK(E8), ISBLANK(R8)), "", IF(ISBLANK(R8), TEXT(N8, "#,##0") & " Km, " & TEXT(E8, "dd.mm.yyyy"), R8)) -> 26 720 Km, 21.10.2022 | S8: 3000 | T8: 1 | U8: @dimanetesov | V8: опыта нет вроде норм чел с другом @egorovcrz | W8: =IF(F8 = "", "", IF(NOW() > (DATEVALUE(LEFT(F8, SEARCH(",", F8) - 2)) + TIMEVALUE(MID(F8, SEARCH(",", F8) + 2, 5))), "Завершена", "В аренде")) -> Завершена | X8: =IFERROR(__xludf.DUMMYFUNCTION("IF(C8 = """", """", IF(REGEXMATCH(C8, ""PCX|NMAX|ADV|CLICK""), ""скутер"", ""мото""))"),"скутер") -> скутер
A9: Завершена | B9: OFF | C9: NMAX 155CC BLACK GOLD-2 PHUKET 4685 | D9: Тарас | E9: 44855 | F9: 44894 | G9: =IF((E9="")+(F9=""), "", IF(DATEDIF(E9, F9, "d") > 30, DATEDIF(E9, F9, "m") & " М", DATEDIF(E9, F9, "d") & " Д")) -> 1 М | H9: =6500/30 -> 216.66667 | I9: =IF(OR(A9="в аренде", A9="в аренде 1", A9="в аренде 2"), J9-K9, "") | J9: =IF(OR(A9="в аренде", A9="в аренде 1", A9="в аренде 2"), DATEDIF(E9, TODAY(), "D")*H9, "") | K9: =7000+1500 -> 8500 | N9: 19300 | O9: =IFERROR(__xludf.DUMMYFUNCTION("IFERROR( VLOOKUP(C9, FILTER( IMPORTRANGE(""https://docs.google.com/spreadsheets/d/1ZBCmVvzoFu7X0td7O5T5xSJplK8m8h9wvdESBc0a1EE/edit#gid=1841437934"", ""Лист1!$C:$I""), IMPORTRANGE(""https://docs.google.com/spreadsheets/d/1ZBCmVvzoFu7X0t"&"d7O5T5xSJplK8m8h9wvdESBc0a1EE/edit#gid=1841437934"", ""Лист1!$C:$C"") = C9 ), 7, FALSE ), """" ) "),36400.0) -> 36400 | P9: =IFERROR(__xludf.DUMMYFUNCTION("IF(OR(ISBLANK(Q9), ISBLANK(O9), VALUE(SUBSTITUTE(INDEX(SPLIT(IF(ISBLANK(R9), Q9, R9), "" km""), 0, 1), "" "", """")) - O9 = 0), """", IF(ISBLANK(R9), VALUE(SUBSTITUTE(INDEX(SPLIT(Q9, "" km""), 0, 1), "" "", """")) - O9, VALUE(SUBSTITUTE(INDEX(SPLIT(R9, """&" km""), 0, 1), "" "", """")) - O9))"),-17100.0) -> -17100 | Q9: =IF(AND(ISBLANK(N9), ISBLANK(E9), ISBLANK(R9)), "", IF(ISBLANK(R9), TEXT(N9, "#,##0") & " Km, " & TEXT(E9, "dd.mm.yyyy"), R9)) -> 19 300 Km, 21.10.2022 | S9: 3000 | T9: 2 | U9: @Danin_12 | V9: укр гуд ребята опытные | W9: =IF(F9 = "", "", IF(NOW() > (DATEVALUE(LEFT(F9, SEARCH(",", F9) - 2)) + TIMEVALUE(MID(F9, SEARCH(",", F9) + 2, 5))), "Завершена", "В аренде")) -> Завершена | X9: =IFERROR(__xludf.DUMMYFUNCTION("IF(C9 = """", """", IF(REGEXMATCH(C9, ""PCX|NMAX|ADV|CLICK""), ""скутер"", ""мото""))"),"скутер") -> скутер
A10: Завершена | B10: OFF | C10: FORZA 300CC RED PHUKET 4244 | D10: Алексей | E10: 44855 | F10: 44947 | G10: =IF((E10="")+(F10=""), "", IF(DATEDIF(E10, F10, "d") > 30, DATEDIF(E10, F10, "m") & " М", DATEDIF(E10, F10, "d") & " Д")) -> 3 М | H10: =5500/30 -> 183.33333 | I10: =IF(OR(A10="в аренде", A10="в аренде 1", A10="в аренде 2"), J10-K10, "") | J10: =IF(OR(A10="в аренде", A10="в аренде 1", A10="в аренде 2"), DATEDIF(E10, TODAY(), "D")*H10, "") | K10: 5500 | N10: 24000 | O10: =IFERROR(__xludf.DUMMYFUNCTION("IFERROR( VLOOKUP(C10, FILTER( IMPORTRANGE(""https://docs.google.com/spreadsheets/d/1ZBCmVvzoFu7X0td7O5T5xSJplK8m8h9wvdESBc0a1EE/edit#gid=1841437934"", ""Лист1!$C:$I""), IMPORTRANGE(""https://docs.google.com/spreadsheets/d/1ZBCmVvzoFu7X0"&"td7O5T5xSJplK8m8h9wvdESBc0a1EE/edit#gid=1841437934"", ""Лист1!$C:$C"") = C10 ), 7, FALSE ), """" ) "),"") | P10: =IFERROR(__xludf.DUMMYFUNCTION("IF(OR(ISBLANK(Q10), ISBLANK(O10), VALUE(SUBSTITUTE(INDEX(SPLIT(IF(ISBLANK(R10), Q10, R10), "" km""), 0, 1), "" "", """")) - O10 = 0), """", IF(ISBLANK(R10), VALUE(SUBSTITUTE(INDEX(SPLIT(Q10, "" km""), 0, 1), "" "", """")) - O10, VALUE(SUBSTITUTE(INDEX(SPL"&"IT(R10, "" km""), 0, 1), "" "", """")) - O10))"),24000.0) -> 24000 | Q10: =IF(AND(ISBLANK(N10), ISBLANK(E10), ISBLANK(R10)), "", IF(ISBLANK(R10), TEXT(N10, "#,##0") & " Km, " & TEXT(E10, "dd.mm.yyyy"), R10)) -> 24 000 Km, 21.10.2022 | S10: 3000 | T10: 1 | U10: @egorovcrz | V10: опыт есть вроде норм чел с другом @dimanesterov | W10: =IF(F10 = "", "", IF(NOW() > (DATEVALUE(LEFT(F10, SEARCH(",", F10) - 2)) + TIMEVALUE(MID(F10, SEARCH(",", F10) + 2, 5))), "Завершена", "В аренде")) -> Завершена | X10: =IFERROR(__xludf.DUMMYFUNCTION("IF(C10 = """", """", IF(REGEXMATCH(C10, ""PCX|NMAX|ADV|CLICK""), ""скутер"", ""мото""))"),"мото") -> мото
A11: Завершена | B11: OFF | C11: XMAX 300CC GREEN PHUKET 4248 | D11: Анатолий | E11: 44856 | F11: 44948 | G11: =IF((E11="")+(F11=""), "", IF(DATEDIF(E11, F11, "d") > 30, DATEDIF(E11, F11, "m") & " М", DATEDIF(E11, F11, "d") & " Д")) -> 3 М | H11: =13000/30 -> 433.33333 | I11: =IF(OR(A11="в аренде", A11="в аренде 1", A11="в аренде 2"), J11-K11, "") | J11: =IF(OR(A11="в аренде", A11="в аренде 1", A11="в аренде 2"), DATEDIF(E11, TODAY(), "D")*H11, "") | K11: =13000+13000+13000 -> 39000 | N11: 9900 | O11: =IFERROR(__xludf.DUMMYFUNCTION("IFERROR( VLOOKUP(C11, FILTER( IMPORTRANGE(""https://docs.google.com/spreadsheets/d/1ZBCmVvzoFu7X0td7O5T5xSJplK8m8h9wvdESBc0a1EE/edit#gid=1841437934"", ""Лист1!$C:$I""), IMPORTRANGE(""https://docs.google.com/spreadsheets/d/1ZBCmVvzoFu7X0"&"td7O5T5xSJplK8m8h9wvdESBc0a1EE/edit#gid=1841437934"", ""Лист1!$C:$C"") = C11 ), 7, FALSE ), """" ) "),32600.0) -> 32600 | P11: =IFERROR(__xludf.DUMMYFUNCTION("IF(OR(ISBLANK(Q11), ISBLANK(O11), VALUE(SUBSTITUTE(INDEX(SPLIT(IF(ISBLANK(R11), Q11, R11), "" km""), 0, 1), "" "", """")) - O11 = 0), """", IF(ISBLANK(R11), VALUE(SUBSTITUTE(INDEX(SPLIT(Q11, "" km""), 0, 1), "" "", """")) - O11, VALUE(SUBSTITUTE(INDEX(SPL"&"IT(R11, "" km""), 0, 1), "" "", """")) - O11))"),-22700.0) -> -22700 | Q11: =IF(AND(ISBLANK(N11), ISBLANK(E11), ISBLANK(R11)), "", IF(ISBLANK(R11), TEXT(N11, "#,##0") & " Km, " & TEXT(E11, "dd.mm.yyyy"), R11)) -> 9 900 Km, 22.10.2022 | S11: 5000 | T11: 1 | U11: @proxwian | V11: прогер не очень опытный но норм | W11: =IF(F11 = "", "", IF(NOW() > (DATEVALUE(LEFT(F11, SEARCH(",", F11) - 2)) + TIMEVALUE(MID(F11, SEARCH(",", F11) + 2, 5))), "Завершена", "В аренде")) -> Завершена | X11: =IFERROR(__xludf.DUMMYFUNCTION("IF(C11 = """", """", IF(REGEXMATCH(C11, ""PCX|NMAX|ADV|CLICK""), ""скутер"", ""мото""))"),"мото") -> мото
A12: Завершена | B12: OFF | C12: NMAX 155CC BLACK GOLD PHUKET 4255 | D12: Павел | E12: 44856 | F12: 44948 | G12: =IF((E12="")+(F12=""), "", IF(DATEDIF(E12, F12, "d") > 30, DATEDIF(E12, F12, "m") & " М", DATEDIF(E12, F12, "d") & " Д")) -> 3 М | H12: =7000/30 -> 233.33333 | I12: =IF(OR(A12="в аренде", A12="в аренде 1", A12="в аренде 2"), J12-K12, "") | J12: =IF(OR(A12="в аренде", A12="в аренде 1", A12="в аренде 2"), DATEDIF(E12, TODAY(), "D")*H12, "") | K12: =7000+7000 -> 14000 | N12: 29275 | O12: =IFERROR(__xludf.DUMMYFUNCTION("IFERROR( VLOOKUP(C12, FILTER( IMPORTRANGE(""https://docs.google.com/spreadsheets/d/1ZBCmVvzoFu7X0td7O5T5xSJplK8m8h9wvdESBc0a1EE/edit#gid=1841437934"", ""Лист1!$C:$I""), IMPORTRANGE(""https://docs.google.com/spreadsheets/d/1ZBCmVvzoFu7X0"&"td7O5T5xSJplK8m8h9wvdESBc0a1EE/edit#gid=1841437934"", ""Лист1!$C:$C"") = C12 ), 7, FALSE ), """" ) "),24094.0) -> 24094 | P12: =IFERROR(__xludf.DUMMYFUNCTION("IF(OR(ISBLANK(Q12), ISBLANK(O12), VALUE(SUBSTITUTE(INDEX(SPLIT(IF(ISBLANK(R12), Q12, R12), "" km""), 0, 1), "" "", """")) - O12 = 0), """", IF(ISBLANK(R12), VALUE(SUBSTITUTE(INDEX(SPLIT(Q12, "" km""), 0, 1), "" "", """")) - O12, VALUE(SUBSTITUTE(INDEX(SPL"&"IT(R12, "" km""), 0, 1), "" "", """")) - O12))"),5181.0) -> 5181 | Q12: =IF(AND(ISBLANK(N12), ISBLANK(E12), ISBLANK(R12)), "", IF(ISBLANK(R12), TEXT(N12, "#,##0") & " Km, " & TEXT(E12, "dd.mm.yyyy"), R12)) -> 29 275 Km, 22.10.2022 | S12: =3000 -> 3000 | T12: 1 | U12: @TarasovPS | V12: странный неопытный | W12: =IF(F12 = "", "", IF(NOW() > (DATEVALUE(LEFT(F12, SEARCH(",", F12) - 2)) + TIMEVALUE(MID(F12, SEARCH(",", F12) + 2, 5))), "Завершена", "В аренде")) -> Завершена | X12: =IFERROR(__xludf.DUMMYFUNCTION("IF(C12 = """", """", IF(REGEXMATCH(C12, ""PCX|NMAX|ADV|CLICK""), ""скутер"", ""мото""))"),"скутер") -> скутер
A13: Завершена | B13: OFF | C13: PCX 150CC GREY PHUKET 778 | D13: Никита Моисеев | E13: 44858 | F13: 45005 | G13: =IF((E13="")+(F13=""), "", IF(DATEDIF(E13, F13, "d") > 30, DATEDIF(E13, F13, "m") & " М", DATEDIF(E13, F13, "d") & " Д")) -> 4 М | H13: 250 | I13: =IF(OR(A13="в аренде", A13="в аренде 1", A13="в аренде 2"), J13-K13, "") | J13: =IF(OR(A13="в аренде", A13="в аренде 1", A13="в аренде 2"), DATEDIF(E13, TODAY(), "D")*H13, "") | K13: =1500+1750+1750+1750+1750+1750+200+1550+1750+3500+1750+750+1000+1750+1750+1750+1750+1750+660+1090+500 -> 31750 | N13: 16800 | O13: =IFERROR(__xludf.DUMMYFUNCTION("IFERROR( VLOOKUP(C13, FILTER( IMPORTRANGE(""https://docs.google.com/spreadsheets/d/1ZBCmVvzoFu7X0td7O5T5xSJplK8m8h9wvdESBc0a1EE/edit#gid=1841437934"", ""Лист1!$C:$I""), IMPORTRANGE(""https://docs.google.com/spreadsheets/d/1ZBCmVvzoFu7X0"&"td7O5T5xSJplK8m8h9wvdESBc0a1EE/edit#gid=1841437934"", ""Лист1!$C:$C"") = C13 ), 7, FALSE ), """" ) "),"") | P13: =IFERROR(__xludf.DUMMYFUNCTION("IF(OR(ISBLANK(Q13), ISBLANK(O13), VALUE(SUBSTITUTE(INDEX(SPLIT(IF(ISBLANK(R13), Q13, R13), "" km""), 0, 1), "" "", """")) - O13 = 0), """", IF(ISBLANK(R13), VALUE(SUBSTITUTE(INDEX(SPLIT(Q13, "" km""), 0, 1), "" "", """")) - O13, VALUE(SUBSTITUTE(INDEX(SPL"&"IT(R13, "" km""), 0, 1), "" "", """")) - O13))"),16800.0) -> 16800 | Q13: =IF(AND(ISBLANK(N13), ISBLANK(E13), ISBLANK(R13)), "", IF(ISBLANK(R13), TEXT(N13, "#,##0") & " Km, " & TEXT(E13, "dd.mm.yyyy"), R13)) -> 16 800 Km, 24.10.2022 | S13: 3000 | T13: 1 | U13: @spacegilly +79958803611 | V13: Мутный Арбитражник возможно скамер | W13: =IF(F13 = "", "", IF(NOW() > (DATEVALUE(LEFT(F13, SEARCH(",", F13) - 2)) + TIMEVALUE(MID(F13, SEARCH(",", F13) + 2, 5))), "Завершена", "В аренде")) -> Завершена | X13: =IFERROR(__xludf.DUMMYFUNCTION("IF(C13 = """", """", IF(REGEXMATCH(C13, ""PCX|NMAX|ADV|CLICK""), ""скутер"", ""мото""))"),"скутер") -> скутер
A14: Завершена | B14: OFF | C14: NMAX 155CC BLACK GOLD-3 PHUKET 7530 | D14: Максим | E14: 44865 | F14: 44985 | G14: =IF((E14="")+(F14=""), "", IF(DATEDIF(E14, F14, "d") > 30, DATEDIF(E14, F14, "m") & " М", DATEDIF(E14, F14, "d") & " Д")) -> 3 М | H14: =7000/30 -> 233.33333 | I14: =IF(OR(A14="в аренде", A14="в аренде 1", A14="в аренде 2"), J14-K14, "") | J14: =IF(OR(A14="в аренде", A14="в аренде 1", A14="в аренде 2"), DATEDIF(E14, TODAY(), "D")*H14, "") | K14: 24000 | N14: 33000 | O14: =IFERROR(__xludf.DUMMYFUNCTION("IFERROR( VLOOKUP(C14, FILTER( IMPORTRANGE(""https://docs.google.com/spreadsheets/d/1ZBCmVvzoFu7X0td7O5T5xSJplK8m8h9wvdESBc0a1EE/edit#gid=1841437934"", ""Лист1!$C:$I""), IMPORTRANGE(""https://docs.google.com/spreadsheets/d/1ZBCmVvzoFu7X0"&"td7O5T5xSJplK8m8h9wvdESBc0a1EE/edit#gid=1841437934"", ""Лист1!$C:$C"") = C14 ), 7, FALSE ), """" ) "),31000.0) -> 31000 | P14: =IFERROR(__xludf.DUMMYFUNCTION("IF(OR(ISBLANK(Q14), ISBLANK(O14), VALUE(SUBSTITUTE(INDEX(SPLIT(IF(ISBLANK(R14), Q14, R14), "" km""), 0, 1), "" "", """")) - O14 = 0), """", IF(ISBLANK(R14), VALUE(SUBSTITUTE(INDEX(SPLIT(Q14, "" km""), 0, 1), "" "", """")) - O14, VALUE(SUBSTITUTE(INDEX(SPL"&"IT(R14, "" km""), 0, 1), "" "", """")) - O14))"),2000.0) -> 2000 | Q14: =IF(AND(ISBLANK(N14), ISBLANK(E14), ISBLANK(R14)), "", IF(ISBLANK(R14), TEXT(N14, "#,##0") & " Km, " & TEXT(E14, "dd.mm.yyyy"), R14)) -> 33 000 Km, 31.10.2022 | S14: 3300 | U14: @Maxmironov | V14: приличный небольшой опыт есть | W14: =IF(F14 = "", "", IF(NOW() > (DATEVALUE(LEFT(F14, SEARCH(",", F14) - 2)) + TIMEVALUE(MID(F14, SEARCH(",", F14) + 2, 5))), "Завершена", "В аренде")) -> Завершена | X14: =IFERROR(__xludf.DUMMYFUNCTION("IF(C14 = """", """", IF(REGEXMATCH(C14, ""PCX|NMAX|ADV|CLICK""), ""скутер"", ""мото""))"),"скутер") -> скутер
A15: Завершена | B15: OFF | C15: NMAX 155CC GREY PHUKET 5960 | D15: Дмитрий Чуканов | E15: 44866 | F15: 44933 | G15: =IF((E15="")+(F15=""), "", IF(DATEDIF(E15, F15, "d") > 30, DATEDIF(E15, F15, "m") & " М", DATEDIF(E15, F15, "d") & " Д")) -> 2 М | H15: 350 | I15: =IF(OR(A15="в аренде", A15="в аренде 1", A15="в аренде 2"), J15-K15, "") | J15: =IF(OR(A15="в аренде", A15="в аренде 1", A15="в аренде 2"), DATEDIF(E15, TODAY(), "D")*H15, "") | K15: 2800 | N15: 15600 | O15: =IFERROR(__xludf.DUMMYFUNCTION("IFERROR( VLOOKUP(C15, FILTER( IMPORTRANGE(""https://docs.google.com/spreadsheets/d/1ZBCmVvzoFu7X0td7O5T5xSJplK8m8h9wvdESBc0a1EE/edit#gid=1841437934"", ""Лист1!$C:$I""), IMPORTRANGE(""https://docs.google.com/spreadsheets/d/1ZBCmVvzoFu7X0"&"td7O5T5xSJplK8m8h9wvdESBc0a1EE/edit#gid=1841437934"", ""Лист1!$C:$C"") = C15 ), 7, FALSE ), """" ) "),37300.0) -> 37300 | P15: =IFERROR(__xludf.DUMMYFUNCTION("IF(OR(ISBLANK(Q15), ISBLANK(O15), VALUE(SUBSTITUTE(INDEX(SPLIT(IF(ISBLANK(R15), Q15, R15), "" km""), 0, 1), "" "", """")) - O15 = 0), """", IF(ISBLANK(R15), VALUE(SUBSTITUTE(INDEX(SPLIT(Q15, "" km""), 0, 1), "" "", """")) - O15, VALUE(SUBSTITUTE(INDEX(SPL"&"IT(R15, "" km""), 0, 1), "" "", """")) - O15))"),-21700.0) -> -21700 | Q15: =IF(AND(ISBLANK(N15), ISBLANK(E15), ISBLANK(R15)), "", IF(ISBLANK(R15), TEXT(N15, "#,##0") & " Km, " & TEXT(E15, "dd.mm.yyyy"), R15)) -> 15 600 Km, 01.11.2022 | S15: 3000 | T15: 1 | U15: @Dmitry_Tch | V15: старнный какойто | W15: =IF(F15 = "", "", IF(NOW() > (DATEVALUE(LEFT(F15, SEARCH(",", F15) - 2)) + TIMEVALUE(MID(F15, SEARCH(",", F15) + 2, 5))), "Завершена", "В аренде")) -> Завершена | X15: =IFERROR(__xludf.DUMMYFUNCTION("IF(C15 = """", """", IF(REGEXMATCH(C15, ""PCX|NMAX|ADV|CLICK""), ""скутер"", ""мото""))"),"скутер") -> скутер
A16: Завершена | B16: OFF | C16: NMAX 155CC YCONNECT BKK | D16: Евгений | E16: 44867 | F16: 45048 | G16: =IF((E16="")+(F16=""), "", IF(DATEDIF(E16, F16, "d") > 30, DATEDIF(E16, F16, "m") & " М", DATEDIF(E16, F16, "d") & " Д")) -> 6 М | H16: =7000/30 -> 233.33333 | I16: =IF(OR(A16="в аренде", A16="в аренде 1", A16="в аренде 2"), J16-K16, "") | J16: =IF(OR(A16="в аренде", A16="в аренде 1", A16="в аренде 2"), DATEDIF(E16, TODAY(), "D")*H16, "") | K16: =7000+7000+7000+7000+7000+7000 -> 42000 | N16: 9916 | O16: =IFERROR(__xludf.DUMMYFUNCTION("IFERROR( VLOOKUP(C16, FILTER( IMPORTRANGE(""https://docs.google.com/spreadsheets/d/1ZBCmVvzoFu7X0td7O5T5xSJplK8m8h9wvdESBc0a1EE/edit#gid=1841437934"", ""Лист1!$C:$I""), IMPORTRANGE(""https://docs.google.com/spreadsheets/d/1ZBCmVvzoFu7X0"&"td7O5T5xSJplK8m8h9wvdESBc0a1EE/edit#gid=1841437934"", ""Лист1!$C:$C"") = C16 ), 7, FALSE ), """" ) "),"") | P16: =IFERROR(__xludf.DUMMYFUNCTION("IF(OR(ISBLANK(Q16), ISBLANK(O16), VALUE(SUBSTITUTE(INDEX(SPLIT(IF(ISBLANK(R16), Q16, R16), "" km""), 0, 1), "" "", """")) - O16 = 0), """", IF(ISBLANK(R16), VALUE(SUBSTITUTE(INDEX(SPLIT(Q16, "" km""), 0, 1), "" "", """")) - O16, VALUE(SUBSTITUTE(INDEX(SPL"&"IT(R16, "" km""), 0, 1), "" "", """")) - O16))"),9916.0) -> 9916 | Q16: =IF(AND(ISBLANK(N16), ISBLANK(E16), ISBLANK(R16)), "", IF(ISBLANK(R16), TEXT(N16, "#,##0") & " Km, " & TEXT(E16, "dd.mm.yyyy"), R16)) -> 9 916 Km, 02.11.2022 | S16: 3000 | T16: 1 | U16: @adler_love | V16: норм чел привел много | W16: =IF(F16 = "", "", IF(NOW() > (DATEVALUE(LEFT(F16, SEARCH(",", F16) - 2)) + TIMEVALUE(MID(F16, SEARCH(",", F16) + 2, 5))), "Завершена", "В аренде")) -> Завершена | X16: =IFERROR(__xludf.DUMMYFUNCTION("IF(C16 = """", """", IF(REGEXMATCH(C16, ""PCX|NMAX|ADV|CLICK""), ""скутер"", ""мото""))"),"скутер") -> скутер
A17: Завершена | B17: OFF | C17: FORZA 300CC RED PHUKET 4244 | D17: Ramil | E17: 44868 | F17: 44938 | G17: =IF((E17="")+(F17=""), "", IF(DATEDIF(E17, F17, "d") > 30, DATEDIF(E17, F17, "m") & " М", DATEDIF(E17, F17, "d") & " Д")) -> 2 М | H17: =12000/30 -> 400 | I17: =IF(OR(A17="в аренде", A17="в аренде 1", A17="в аренде 2"), J17-K17, "") | J17: =IF(OR(A17="в аренде", A17="в аренде 1", A17="в аренде 2"), DATEDIF(E17, TODAY(), "D")*H17, "") | K17: =12000+12000+4000 -> 28000 | N17: 18000 | O17: =IFERROR(__xludf.DUMMYFUNCTION("IFERROR( VLOOKUP(C17, FILTER( IMPORTRANGE(""https://docs.google.com/spreadsheets/d/1ZBCmVvzoFu7X0td7O5T5xSJplK8m8h9wvdESBc0a1EE/edit#gid=1841437934"", ""Лист1!$C:$I""), IMPORTRANGE(""https://docs.google.com/spreadsheets/d/1ZBCmVvzoFu7X0"&"td7O5T5xSJplK8m8h9wvdESBc0a1EE/edit#gid=1841437934"", ""Лист1!$C:$C"") = C17 ), 7, FALSE ), """" ) "),"") | P17: =IFERROR(__xludf.DUMMYFUNCTION("IF(OR(ISBLANK(Q17), ISBLANK(O17), VALUE(SUBSTITUTE(INDEX(SPLIT(IF(ISBLANK(R17), Q17, R17), "" km""), 0, 1), "" "", """")) - O17 = 0), """", IF(ISBLANK(R17), VALUE(SUBSTITUTE(INDEX(SPLIT(Q17, "" km""), 0, 1), "" "", """")) - O17, VALUE(SUBSTITUTE(INDEX(SPL"&"IT(R17, "" km""), 0, 1), "" "", """")) - O17))"),18000.0) -> 18000 | Q17: =IF(AND(ISBLANK(N17), ISBLANK(E17), ISBLANK(R17)), "", IF(ISBLANK(R17), TEXT(N17, "#,##0") & " Km, " & TEXT(E17, "dd.mm.yyyy"), R17)) -> 18 000 Km, 03.11.2022 | S17: 5000 | T17: 1 | U17: @Ra_boss111 | V17: Взрослый ровный чел | W17: =IF(F17 = "", "", IF(NOW() > (DATEVALUE(LEFT(F17, SEARCH(",", F17) - 2)) + TIMEVALUE(MID(F17, SEARCH(",", F17) + 2, 5))), "Завершена", "В аренде")) -> Завершена | X17: =IFERROR(__xludf.DUMMYFUNCTION("IF(C17 = """", """", IF(REGEXMATCH(C17, ""PCX|NMAX|ADV|CLICK""), ""скутер"", ""мото""))"),"мото") -> мото
A18: Завершена | B18: OFF | C18: NMAX 155CC GREY MATT PHUKET 7527 | D18: Александр Ильин | E18: 44870 | F18: 44893 | G18: =IF((E18="")+(F18=""), "", IF(DATEDIF(E18, F18, "d") > 30, DATEDIF(E18, F18, "m") & " М", DATEDIF(E18, F18, "d") & " Д")) -> 23 Д | H18: =7000/30 -> 233.33333 | I18: =IF(OR(A18="в аренде", A18="в аренде 1", A18="в аренде 2"), J18-K18, "") | J18: =IF(OR(A18="в аренде", A18="в аренде 1", A18="в аренде 2"), DATEDIF(E18, TODAY(), "D")*H18, "") | K18: 5367 | N18: 12400 | O18: =IFERROR(__xludf.DUMMYFUNCTION("IFERROR( VLOOKUP(C18, FILTER( IMPORTRANGE(""https://docs.google.com/spreadsheets/d/1ZBCmVvzoFu7X0td7O5T5xSJplK8m8h9wvdESBc0a1EE/edit#gid=1841437934"", ""Лист1!$C:$I""), IMPORTRANGE(""https://docs.google.com/spreadsheets/d/1ZBCmVvzoFu7X0"&"td7O5T5xSJplK8m8h9wvdESBc0a1EE/edit#gid=1841437934"", ""Лист1!$C:$C"") = C18 ), 7, FALSE ), """" ) "),"") | P18: =IFERROR(__xludf.DUMMYFUNCTION("IF(OR(ISBLANK(Q18), ISBLANK(O18), VALUE(SUBSTITUTE(INDEX(SPLIT(IF(ISBLANK(R18), Q18, R18), "" km""), 0, 1), "" "", """")) - O18 = 0), """", IF(ISBLANK(R18), VALUE(SUBSTITUTE(INDEX(SPLIT(Q18, "" km""), 0, 1), "" "", """")) - O18, VALUE(SUBSTITUTE(INDEX(SPL"&"IT(R18, "" km""), 0, 1), "" "", """")) - O18))"),12400.0) -> 12400 | Q18: =IF(AND(ISBLANK(N18), ISBLANK(E18), ISBLANK(R18)), "", IF(ISBLANK(R18), TEXT(N18, "#,##0") & " Km, " & TEXT(E18, "dd.mm.yyyy"), R18)) -> 12 400 Km, 05.11.2022 | S18: 3000 | T18: 1 | U18: @Alex_hetzer | V18: немного странный но ок опыт не большой | W18: =IF(F18 = "", "", IF(NOW() > (DATEVALUE(LEFT(F18, SEARCH(",", F18) - 2)) + TIMEVALUE(MID(F18, SEARCH(",", F18) + 2, 5))), "Завершена", "В аренде")) -> Завершена | X18: =IFERROR(__xludf.DUMMYFUNCTION("IF(C18 = """", """", IF(REGEXMATCH(C18, ""PCX|NMAX|ADV|CLICK""), ""скутер"", ""мото""))"),"скутер") -> скутер
A19: Завершена | B19: OFF | C19: XMAX 300CC BLUE PHUKET 5773 | D19: Евгений | E19: 44872 | F19: 44893 | G19: =IF((E19="")+(F19=""), "", IF(DATEDIF(E19, F19, "d") > 30, DATEDIF(E19, F19, "m") & " М", DATEDIF(E19, F19, "d") & " Д")) -> 21 Д | H19: 480 | I19: =IF(OR(A19="в аренде", A19="в аренде 1", A19="в аренде 2"), J19-K19, "") | J19: =IF(OR(A19="в аренде", A19="в аренде 1", A19="в аренде 2"), DATEDIF(E19, TODAY(), "D")*H19, "") | K19: =1830+8250 -> 10080 | N19: 28600 | O19: =IFERROR(__xludf.DUMMYFUNCTION("IFERROR( VLOOKUP(C19, FILTER( IMPORTRANGE(""https://docs.google.com/spreadsheets/d/1ZBCmVvzoFu7X0td7O5T5xSJplK8m8h9wvdESBc0a1EE/edit#gid=1841437934"", ""Лист1!$C:$I""), IMPORTRANGE(""https://docs.google.com/spreadsheets/d/1ZBCmVvzoFu7X0"&"td7O5T5xSJplK8m8h9wvdESBc0a1EE/edit#gid=1841437934"", ""Лист1!$C:$C"") = C19 ), 7, FALSE ), """" ) "),23500.0) -> 23500 | P19: =IFERROR(__xludf.DUMMYFUNCTION("IF(OR(ISBLANK(Q19), ISBLANK(O19), VALUE(SUBSTITUTE(INDEX(SPLIT(IF(ISBLANK(R19), Q19, R19), "" km""), 0, 1), "" "", """")) - O19 = 0), """", IF(ISBLANK(R19), VALUE(SUBSTITUTE(INDEX(SPLIT(Q19, "" km""), 0, 1), "" "", """")) - O19, VALUE(SUBSTITUTE(INDEX(SPL"&"IT(R19, "" km""), 0, 1), "" "", """")) - O19))"),5100.0) -> 5100 | Q19: =IF(AND(ISBLANK(N19), ISBLANK(E19), ISBLANK(R19)), "", IF(ISBLANK(R19), TEXT(N19, "#,##0") & " Km, " & TEXT(E19, "dd.mm.yyyy"), R19)) -> 28 600 Km, 07.11.2022 | S19: 5000 | T19: 1 | U19: @eallend | V19: приятный с большим опытом | W19: =IF(F19 = "", "", IF(NOW() > (DATEVALUE(LEFT(F19, SEARCH(",", F19) - 2)) + TIMEVALUE(MID(F19, SEARCH(",", F19) + 2, 5))), "Завершена", "В аренде")) -> Завершена | X19: =IFERROR(__xludf.DUMMYFUNCTION("IF(C19 = """", """", IF(REGEXMATCH(C19, ""PCX|NMAX|ADV|CLICK""), ""скутер"", ""мото""))"),"мото") -> мото
A20: Завершена | B20: OFF | C20: NMAX 155CC GREY PHUKET 5960 | D20: Николай | E20: 44874 | F20: 44881 | G20: =IF((E20="")+(F20=""), "", IF(DATEDIF(E20, F20, "d") > 30, DATEDIF(E20, F20, "m") & " М", DATEDIF(E20, F20, "d") & " Д")) -> 7 Д | H20: 300 | I20: =IF(OR(A20="в аренде", A20="в аренде 1", A20="в аренде 2"), J20-K20, "") | J20: =IF(OR(A20="в аренде", A20="в аренде 1", A20="в аренде 2"), DATEDIF(E20, TODAY(), "D")*H20, "") | K20: 2100 | N20: 15880 | O20: =IFERROR(__xludf.DUMMYFUNCTION("IFERROR( VLOOKUP(C20, FILTER( IMPORTRANGE(""https://docs.google.com/spreadsheets/d/1ZBCmVvzoFu7X0td7O5T5xSJplK8m8h9wvdESBc0a1EE/edit#gid=1841437934"", ""Лист1!$C:$I""), IMPORTRANGE(""https://docs.google.com/spreadsheets/d/1ZBCmVvzoFu7X0"&"td7O5T5xSJplK8m8h9wvdESBc0a1EE/edit#gid=1841437934"", ""Лист1!$C:$C"") = C20 ), 7, FALSE ), """" ) "),37300.0) -> 37300 | P20: =IFERROR(__xludf.DUMMYFUNCTION("IF(OR(ISBLANK(Q20), ISBLANK(O20), VALUE(SUBSTITUTE(INDEX(SPLIT(IF(ISBLANK(R20), Q20, R20), "" km""), 0, 1), "" "", """")) - O20 = 0), """", IF(ISBLANK(R20), VALUE(SUBSTITUTE(INDEX(SPLIT(Q20, "" km""), 0, 1), "" "", """")) - O20, VALUE(SUBSTITUTE(INDEX(SPL"&"IT(R20, "" km""), 0, 1), "" "", """")) - O20))"),-21420.0) -> -21420 | Q20: =IF(AND(ISBLANK(N20), ISBLANK(E20), ISBLANK(R20)), "", IF(ISBLANK(R20), TEXT(N20, "#,##0") & " Km, " & TEXT(E20, "dd.mm.yyyy"), R20)) -> 15 880 Km, 09.11.2022 | S20: 3000 | T20: 2 | U20: @npekshuev | V20: Ник др Артем | W20: =IF(F20 = "", "", IF(NOW() > (DATEVALUE(LEFT(F20, SEARCH(",", F20) - 2)) + TIMEVALUE(MID(F20, SEARCH(",", F20) + 2, 5))), "Завершена", "В аренде")) -> Завершена | X20: =IFERROR(__xludf.DUMMYFUNCTION("IF(C20 = """", """", IF(REGEXMATCH(C20, ""PCX|NMAX|ADV|CLICK""), ""скутер"", ""мото""))"),"скутер") -> скутер
A21: Завершена | B21: OFF | C21: NMAX 155CC GREY GOLD PHUKET 6908 | D21: Roman | E21: 44875 | F21: 44905 | G21: =IF((E21="")+(F21=""), "", IF(DATEDIF(E21, F21, "d") > 30, DATEDIF(E21, F21, "m") & " М", DATEDIF(E21, F21, "d") & " Д")) -> 30 Д | H21: =7500/30 -> 250 | I21: =IF(OR(A21="в аренде", A21="в аренде 1", A21="в аренде 2"), J21-K21, "") | J21: =IF(OR(A21="в аренде", A21="в аренде 1", A21="в аренде 2"), DATEDIF(E21, TODAY(), "D")*H21, "") | K21: 7500 | N21: 23400 | O21: =IFERROR(__xludf.DUMMYFUNCTION("IFERROR( VLOOKUP(C21, FILTER( IMPORTRANGE(""https://docs.google.com/spreadsheets/d/1ZBCmVvzoFu7X0td7O5T5xSJplK8m8h9wvdESBc0a1EE/edit#gid=1841437934"", ""Лист1!$C:$I""), IMPORTRANGE(""https://docs.google.com/spreadsheets/d/1ZBCmVvzoFu7X0"&"td7O5T5xSJplK8m8h9wvdESBc0a1EE/edit#gid=1841437934"", ""Лист1!$C:$C"") = C21 ), 7, FALSE ), """" ) "),32200.0) -> 32200 | P21: =IFERROR(__xludf.DUMMYFUNCTION("IF(OR(ISBLANK(Q21), ISBLANK(O21), VALUE(SUBSTITUTE(INDEX(SPLIT(IF(ISBLANK(R21), Q21, R21), "" km""), 0, 1), "" "", """")) - O21 = 0), """", IF(ISBLANK(R21), VALUE(SUBSTITUTE(INDEX(SPLIT(Q21, "" km""), 0, 1), "" "", """")) - O21, VALUE(SUBSTITUTE(INDEX(SPL"&"IT(R21, "" km""), 0, 1), "" "", """")) - O21))"),-8800.0) -> -8800 | Q21: =IF(AND(ISBLANK(N21), ISBLANK(E21), ISBLANK(R21)), "", IF(ISBLANK(R21), TEXT(N21, "#,##0") & " Km, " & TEXT(E21, "dd.mm.yyyy"), R21)) -> 23 400 Km, 10.11.2022 | S21: 3000 | T21: 1 | U21: @futuroman | V21: украинец резкий но норм | W21: =IF(F21 = "", "", IF(NOW() > (DATEVALUE(LEFT(F21, SEARCH(",", F21) - 2)) + TIMEVALUE(MID(F21, SEARCH(",", F21) + 2, 5))), "Завершена", "В аренде")) -> Завершена | X21: =IFERROR(__xludf.DUMMYFUNCTION("IF(C21 = """", """", IF(REGEXMATCH(C21, ""PCX|NMAX|ADV|CLICK""), ""скутер"", ""мото""))"),"скутер") -> скутер
A22: Завершена | B22: OFF | C22: CBR 650R PHUKET 4505 | D22: Артем Тимофеев | E22: 44876 | F22: 44879 | G22: =IF((E22="")+(F22=""), "", IF(DATEDIF(E22, F22, "d") > 30, DATEDIF(E22, F22, "m") & " М", DATEDIF(E22, F22, "d") & " Д")) -> 3 Д | H22: =2500 -> 2500 | I22: =IF(OR(A22="в аренде", A22="в аренде 1", A22="в аренде 2"), J22-K22, "") | J22: =IF(OR(A22="в аренде", A22="в аренде 1", A22="в аренде 2"), DATEDIF(E22, TODAY(), "D")*H22, "") | K22: 8500 | N22: 26600 | O22: =IFERROR(__xludf.DUMMYFUNCTION("IFERROR( VLOOKUP(C22, FILTER( IMPORTRANGE(""https://docs.google.com/spreadsheets/d/1ZBCmVvzoFu7X0td7O5T5xSJplK8m8h9wvdESBc0a1EE/edit#gid=1841437934"", ""Лист1!$C:$I""), IMPORTRANGE(""https://docs.google.com/spreadsheets/d/1ZBCmVvzoFu7X0"&"td7O5T5xSJplK8m8h9wvdESBc0a1EE/edit#gid=1841437934"", ""Лист1!$C:$C"") = C22 ), 7, FALSE ), """" ) "),63700.0) -> 63700 | P22: =IFERROR(__xludf.DUMMYFUNCTION("IF(OR(ISBLANK(Q22), ISBLANK(O22), VALUE(SUBSTITUTE(INDEX(SPLIT(IF(ISBLANK(R22), Q22, R22), "" km""), 0, 1), "" "", """")) - O22 = 0), """", IF(ISBLANK(R22), VALUE(SUBSTITUTE(INDEX(SPLIT(Q22, "" km""), 0, 1), "" "", """")) - O22, VALUE(SUBSTITUTE(INDEX(SPL"&"IT(R22, "" km""), 0, 1), "" "", """")) - O22))"),-37100.0) -> -37100 | Q22: =IF(AND(ISBLANK(N22), ISBLANK(E22), ISBLANK(R22)), "", IF(ISBLANK(R22), TEXT(N22, "#,##0") & " Km, " & TEXT(E22, "dd.mm.yyyy"), R22)) -> 26 600 Km, 11.11.2022 | S22: 300 | T22: 1 | U22: +79138112101 | V22: вроде опытный здоровяк | W22: =IF(F22 = "", "", IF(NOW() > (DATEVALUE(LEFT(F22, SEARCH(",", F22) - 2)) + TIMEVALUE(MID(F22, SEARCH(",", F22) + 2, 5))), "Завершена", "В аренде")) -> Завершена | X22: =IFERROR(__xludf.DUMMYFUNCTION("IF(C22 = """", """", IF(REGEXMATCH(C22, ""PCX|NMAX|ADV|CLICK""), ""скутер"", ""мото""))"),"мото") -> мото
A23: Завершена | B23: OFF | C23: NMAX 155CC RACE PHUKET 7532 | D23: Антон | E23: 44877 | F23: 45028 | G23: =IF((E23="")+(F23=""), "", IF(DATEDIF(E23, F23, "d") > 30, DATEDIF(E23, F23, "m") & " М", DATEDIF(E23, F23, "d") & " Д")) -> 5 М | H23: =7000/30 -> 233.33333 | I23: =IF(OR(A23="в аренде", A23="в аренде 1", A23="в аренде 2"), J23-K23, "") | J23: =IF(OR(A23="в аренде", A23="в аренде 1", A23="в аренде 2"), DATEDIF(E23, TODAY(), "D")*H23, "") | K23: =14000+14000+7000 -> 35000 | N23: 13300 | O23: =IFERROR(__xludf.DUMMYFUNCTION("IFERROR( VLOOKUP(C23, FILTER( IMPORTRANGE(""https://docs.google.com/spreadsheets/d/1ZBCmVvzoFu7X0td7O5T5xSJplK8m8h9wvdESBc0a1EE/edit#gid=1841437934"", ""Лист1!$C:$I""), IMPORTRANGE(""https://docs.google.com/spreadsheets/d/1ZBCmVvzoFu7X0"&"td7O5T5xSJplK8m8h9wvdESBc0a1EE/edit#gid=1841437934"", ""Лист1!$C:$C"") = C23 ), 7, FALSE ), """" ) "),26000.0) -> 26000 | P23: =IFERROR(__xludf.DUMMYFUNCTION("IF(OR(ISBLANK(Q23), ISBLANK(O23), VALUE(SUBSTITUTE(INDEX(SPLIT(IF(ISBLANK(R23), Q23, R23), "" km""), 0, 1), "" "", """")) - O23 = 0), """", IF(ISBLANK(R23), VALUE(SUBSTITUTE(INDEX(SPLIT(Q23, "" km""), 0, 1), "" "", """")) - O23, VALUE(SUBSTITUTE(INDEX(SPL"&"IT(R23, "" km""), 0, 1), "" "", """")) - O23))"),"#VALUE!") -> #VALUE! | Q23: =IF(AND(ISBLANK(N23), ISBLANK(E23), ISBLANK(R23)), "", IF(ISBLANK(R23), TEXT(N23, "#,##0") & " Km, " & TEXT(E23, "dd.mm.yyyy"), R23)) -> хочет на год | R23: хочет на год | S23: 0 | T23: 2 | U23: @rebmalad | V23: добрый казах | W23: =IF(F23 = "", "", IF(NOW() > (DATEVALUE(LEFT(F23, SEARCH(",", F23) - 2)) + TIMEVALUE(MID(F23, SEARCH(",", F23) + 2, 5))), "Завершена", "В аренде")) -> Завершена | X23: =IFERROR(__xludf.DUMMYFUNCTION("IF(C23 = """", """", IF(REGEXMATCH(C23, ""PCX|NMAX|ADV|CLICK""), ""скутер"", ""мото""))"),"скутер") -> скутер
A24: Завершена | B24: OFF | C24: XMAX 300CC GREY PHUKET 4246 | D24: Сергей | E24: 44878 | F24: 44970 | G24: =IF((E24="")+(F24=""), "", IF(DATEDIF(E24, F24, "d") > 30, DATEDIF(E24, F24, "m") & " М", DATEDIF(E24, F24, "d") & " Д")) -> 3 М | H24: =12000/30 -> 400 | I24: =IF(OR(A24="в аренде", A24="в аренде 1", A24="в аренде 2"), J24-K24, "") | J24: =IF(OR(A24="в аренде", A24="в аренде 1", A24="в аренде 2"), DATEDIF(E24, TODAY(), "D")*H24, "") | K24: =12000+12000+12000+2100 -> 38100 | N24: 13900 | O24: =IFERROR(__xludf.DUMMYFUNCTION("IFERROR( VLOOKUP(C24, FILTER( IMPORTRANGE(""https://docs.google.com/spreadsheets/d/1ZBCmVvzoFu7X0td7O5T5xSJplK8m8h9wvdESBc0a1EE/edit#gid=1841437934"", ""Лист1!$C:$I""), IMPORTRANGE(""https://docs.google.com/spreadsheets/d/1ZBCmVvzoFu7X0"&"td7O5T5xSJplK8m8h9wvdESBc0a1EE/edit#gid=1841437934"", ""Лист1!$C:$C"") = C24 ), 7, FALSE ), """" ) "),38640.0) -> 38640 | P24: =IFERROR(__xludf.DUMMYFUNCTION("IF(OR(ISBLANK(Q24), ISBLANK(O24), VALUE(SUBSTITUTE(INDEX(SPLIT(IF(ISBLANK(R24), Q24, R24), "" km""), 0, 1), "" "", """")) - O24 = 0), """", IF(ISBLANK(R24), VALUE(SUBSTITUTE(INDEX(SPLIT(Q24, "" km""), 0, 1), "" "", """")) - O24, VALUE(SUBSTITUTE(INDEX(SPL"&"IT(R24, "" km""), 0, 1), "" "", """")) - O24))"),-24740.0) -> -24740 | Q24: =IF(AND(ISBLANK(N24), ISBLANK(E24), ISBLANK(R24)), "", IF(ISBLANK(R24), TEXT(N24, "#,##0") & " Km, " & TEXT(E24, "dd.mm.yyyy"), R24)) -> 13 900 Km, 13.11.2022 | S24: 5000 | T24: 2 | U24: @d_kryzhko | V24: опытный пара адекватных:))))))) | W24: =IF(F24 = "", "", IF(NOW() > (DATEVALUE(LEFT(F24, SEARCH(",", F24) - 2)) + TIMEVALUE(MID(F24, SEARCH(",", F24) + 2, 5))), "Завершена", "В аренде")) -> Завершена | X24: =IFERROR(__xludf.DUMMYFUNCTION("IF(C24 = """", """", IF(REGEXMATCH(C24, ""PCX|NMAX|ADV|CLICK""), ""скутер"", ""мото""))"),"мото") -> мото
A25: Завершена | B25: OFF | C25: XMAX 300CC 2020 BLACKGOLD PHUKET 3163 | D25: Николай | E25: 44883 | F25: 45006 | G25: =IF((E25="")+(F25=""), "", IF(DATEDIF(E25, F25, "d") > 30, DATEDIF(E25, F25, "m") & " М", DATEDIF(E25, F25, "d") & " Д")) -> 4 М | H25: =13000/30 -> 433.33333 | I25: =IF(OR(A25="в аренде", A25="в аренде 1", A25="в аренде 2"), J25-K25, "") | J25: =IF(OR(A25="в аренде", A25="в аренде 1", A25="в аренде 2"), DATEDIF(E25, TODAY(), "D")*H25, "") | K25: =13000+13000+13000+13000 -> 52000 | N25: 15880 | O25: =IFERROR(__xludf.DUMMYFUNCTION("IFERROR( VLOOKUP(C25, FILTER( IMPORTRANGE(""https://docs.google.com/spreadsheets/d/1ZBCmVvzoFu7X0td7O5T5xSJplK8m8h9wvdESBc0a1EE/edit#gid=1841437934"", ""Лист1!$C:$I""), IMPORTRANGE(""https://docs.google.com/spreadsheets/d/1ZBCmVvzoFu7X0"&"td7O5T5xSJplK8m8h9wvdESBc0a1EE/edit#gid=1841437934"", ""Лист1!$C:$C"") = C25 ), 7, FALSE ), """" ) "),"") | P25: =IFERROR(__xludf.DUMMYFUNCTION("IF(OR(ISBLANK(Q25), ISBLANK(O25), VALUE(SUBSTITUTE(INDEX(SPLIT(IF(ISBLANK(R25), Q25, R25), "" km""), 0, 1), "" "", """")) - O25 = 0), """", IF(ISBLANK(R25), VALUE(SUBSTITUTE(INDEX(SPLIT(Q25, "" km""), 0, 1), "" "", """")) - O25, VALUE(SUBSTITUTE(INDEX(SPL"&"IT(R25, "" km""), 0, 1), "" "", """")) - O25))"),15880.0) -> 15880 | Q25: =IF(AND(ISBLANK(N25), ISBLANK(E25), ISBLANK(R25)), "", IF(ISBLANK(R25), TEXT(N25, "#,##0") & " Km, " & TEXT(E25, "dd.mm.yyyy"), R25)) -> 15 880 Km, 18.11.2022 | S25: 5000 | T25: 2 | U25: @npekshuev | V25: Ник др Артем | W25: =IF(F25 = "", "", IF(NOW() > (DATEVALUE(LEFT(F25, SEARCH(",", F25) - 2)) + TIMEVALUE(MID(F25, SEARCH(",", F25) + 2, 5))), "Завершена", "В аренде")) -> Завершена | X25: =IFERROR(__xludf.DUMMYFUNCTION("IF(C25 = """", """", IF(REGEXMATCH(C25, ""PCX|NMAX|ADV|CLICK""), ""скутер"", ""мото""))"),"мото") -> мото
A26: Завершена | B26: OFF | C26: NMAX 155CC RED WHITE PHUKET 9548 | D26: Сева и Аня | E26: 44885 | F26: 45009 | G26: =IF((E26="")+(F26=""), "", IF(DATEDIF(E26, F26, "d") > 30, DATEDIF(E26, F26, "m") & " М", DATEDIF(E26, F26, "d") & " Д")) -> 4 М | H26: =8000/30 -> 266.66667 | I26: =IF(OR(A26="в аренде", A26="в аренде 1", A26="в аренде 2"), J26-K26, "") | J26: =IF(OR(A26="в аренде", A26="в аренде 1", A26="в аренде 2"), DATEDIF(E26, TODAY(), "D")*H26, "") | K26: =8000+8000+8000+8000+1070 -> 33070 | N26: 13800 | O26: =IFERROR(__xludf.DUMMYFUNCTION("IFERROR( VLOOKUP(C26, FILTER( IMPORTRANGE(""https://docs.google.com/spreadsheets/d/1ZBCmVvzoFu7X0td7O5T5xSJplK8m8h9wvdESBc0a1EE/edit#gid=1841437934"", ""Лист1!$C:$I""), IMPORTRANGE(""https://docs.google.com/spreadsheets/d/1ZBCmVvzoFu7X0"&"td7O5T5xSJplK8m8h9wvdESBc0a1EE/edit#gid=1841437934"", ""Лист1!$C:$C"") = C26 ), 7, FALSE ), """" ) "),31800.0) -> 31800 | P26: =IFERROR(__xludf.DUMMYFUNCTION("IF(OR(ISBLANK(Q26), ISBLANK(O26), VALUE(SUBSTITUTE(INDEX(SPLIT(IF(ISBLANK(R26), Q26, R26), "" km""), 0, 1), "" "", """")) - O26 = 0), """", IF(ISBLANK(R26), VALUE(SUBSTITUTE(INDEX(SPLIT(Q26, "" km""), 0, 1), "" "", """")) - O26, VALUE(SUBSTITUTE(INDEX(SPL"&"IT(R26, "" km""), 0, 1), "" "", """")) - O26))"),-18000.0) -> -18000 | Q26: =IF(AND(ISBLANK(N26), ISBLANK(E26), ISBLANK(R26)), "", IF(ISBLANK(R26), TEXT(N26, "#,##0") & " Km, " & TEXT(E26, "dd.mm.yyyy"), R26)) -> 13 800 Km, 20.11.2022 | S26: 3000 | T26: 2 | U26: @vnjutv | V26: 1 ый раз катаются | W26: =IF(F26 = "", "", IF(NOW() > (DATEVALUE(LEFT(F26, SEARCH(",", F26) - 2)) + TIMEVALUE(MID(F26, SEARCH(",", F26) + 2, 5))), "Завершена", "В аренде")) -> Завершена | X26: =IFERROR(__xludf.DUMMYFUNCTION("IF(C26 = """", """", IF(REGEXMATCH(C26, ""PCX|NMAX|ADV|CLICK""), ""скутер"", ""мото""))"),"скутер") -> скутер
A27: Завершена | B27: OFF | C27: NMAX 155CC GREY PHUKET 5960 | D27: Svetlana | E27: 44885 | F27: 45010 | G27: =IF((E27="")+(F27=""), "", IF(DATEDIF(E27, F27, "d") > 30, DATEDIF(E27, F27, "m") & " М", DATEDIF(E27, F27, "d") & " Д")) -> 4 М | H27: =7500/30 -> 250 | I27: =IF(OR(A27="в аренде", A27="в аренде 1", A27="в аренде 2"), J27-K27, "") | J27: =IF(OR(A27="в аренде", A27="в аренде 1", A27="в аренде 2"), DATEDIF(E27, TODAY(), "D")*H27, "") | K27: =8000+8000+8000+7500 -> 31500 | N27: 16100 | O27: =IFERROR(__xludf.DUMMYFUNCTION("IFERROR( VLOOKUP(C27, FILTER( IMPORTRANGE(""https://docs.google.com/spreadsheets/d/1ZBCmVvzoFu7X0td7O5T5xSJplK8m8h9wvdESBc0a1EE/edit#gid=1841437934"", ""Лист1!$C:$I""), IMPORTRANGE(""https://docs.google.com/spreadsheets/d/1ZBCmVvzoFu7X0"&"td7O5T5xSJplK8m8h9wvdESBc0a1EE/edit#gid=1841437934"", ""Лист1!$C:$C"") = C27 ), 7, FALSE ), """" ) "),37300.0) -> 37300 | P27: =IFERROR(__xludf.DUMMYFUNCTION("IF(OR(ISBLANK(Q27), ISBLANK(O27), VALUE(SUBSTITUTE(INDEX(SPLIT(IF(ISBLANK(R27), Q27, R27), "" km""), 0, 1), "" "", """")) - O27 = 0), """", IF(ISBLANK(R27), VALUE(SUBSTITUTE(INDEX(SPLIT(Q27, "" km""), 0, 1), "" "", """")) - O27, VALUE(SUBSTITUTE(INDEX(SPL"&"IT(R27, "" km""), 0, 1), "" "", """")) - O27))"),-21200.0) -> -21200 | Q27: =IF(AND(ISBLANK(N27), ISBLANK(E27), ISBLANK(R27)), "", IF(ISBLANK(R27), TEXT(N27, "#,##0") & " Km, " & TEXT(E27, "dd.mm.yyyy"), R27)) -> 16 100 Km, 20.11.2022 | S27: 3000 | T27: 2 | U27: @schvetko | V27: норм ребята пара | W27: =IF(F27 = "", "", IF(NOW() > (DATEVALUE(LEFT(F27, SEARCH(",", F27) - 2)) + TIMEVALUE(MID(F27, SEARCH(",", F27) + 2, 5))), "Завершена", "В аренде")) -> Завершена | X27: =IFERROR(__xludf.DUMMYFUNCTION("IF(C27 = """", """", IF(REGEXMATCH(C27, ""PCX|NMAX|ADV|CLICK""), ""скутер"", ""мото""))"),"скутер") -> скутер
A28: Завершена | B28: OFF | C28: NMAX 155CC GREEN MATT PHUKET 6901 | D28: Альберт | E28: 44885 | F28: 45016 | G28: =IF((E28="")+(F28=""), "", IF(DATEDIF(E28, F28, "d") > 30, DATEDIF(E28, F28, "m") & " М", DATEDIF(E28, F28, "d") & " Д")) -> 4 М | H28: =8000/30 -> 266.66667 | I28: =IF(OR(A28="в аренде", A28="в аренде 1", A28="в аренде 2"), J28-K28, "") | J28: =IF(OR(A28="в аренде", A28="в аренде 1", A28="в аренде 2"), DATEDIF(E28, TODAY(), "D")*H28, "") | K28: =8000+8000+8000 -> 24000 | N28: 19950 | O28: =IFERROR(__xludf.DUMMYFUNCTION("IFERROR( VLOOKUP(C28, FILTER( IMPORTRANGE(""https://docs.google.com/spreadsheets/d/1ZBCmVvzoFu7X0td7O5T5xSJplK8m8h9wvdESBc0a1EE/edit#gid=1841437934"", ""Лист1!$C:$I""), IMPORTRANGE(""https://docs.google.com/spreadsheets/d/1ZBCmVvzoFu7X0"&"td7O5T5xSJplK8m8h9wvdESBc0a1EE/edit#gid=1841437934"", ""Лист1!$C:$C"") = C28 ), 7, FALSE ), """" ) "),"") | P28: =IFERROR(__xludf.DUMMYFUNCTION("IF(OR(ISBLANK(Q28), ISBLANK(O28), VALUE(SUBSTITUTE(INDEX(SPLIT(IF(ISBLANK(R28), Q28, R28), "" km""), 0, 1), "" "", """")) - O28 = 0), """", IF(ISBLANK(R28), VALUE(SUBSTITUTE(INDEX(SPLIT(Q28, "" km""), 0, 1), "" "", """")) - O28, VALUE(SUBSTITUTE(INDEX(SPL"&"IT(R28, "" km""), 0, 1), "" "", """")) - O28))"),19950.0) -> 19950 | Q28: =IF(AND(ISBLANK(N28), ISBLANK(E28), ISBLANK(R28)), "", IF(ISBLANK(R28), TEXT(N28, "#,##0") & " Km, " & TEXT(E28, "dd.mm.yyyy"), R28)) -> 19 950 Km, 20.11.2022 | S28: 3000 | T28: 2 | U28: @KabirovAA | V28: ОКР | W28: =IF(F28 = "", "", IF(NOW() > (DATEVALUE(LEFT(F28, SEARCH(",", F28) - 2)) + TIMEVALUE(MID(F28, SEARCH(",", F28) + 2, 5))), "Завершена", "В аренде")) -> Завершена | X28: =IFERROR(__xludf.DUMMYFUNCTION("IF(C28 = """", """", IF(REGEXMATCH(C28, ""PCX|NMAX|ADV|CLICK""), ""скутер"", ""мото""))"),"скутер") -> скутер
A29: Завершена | B29: OFF | C29: NMAX 155CC GREEN MATT-2 PHUKET 7639 | D29: Константин | E29: 44887 | F29: 36892 | G29: =IF((E29="")+(F29=""), "", IF(DATEDIF(E29, F29, "d") > 30, DATEDIF(E29, F29, "m") & " М", DATEDIF(E29, F29, "d") & " Д")) -> #NUM! | H29: =8000/30 -> 266.66667 | I29: =IF(OR(A29="в аренде", A29="в аренде 1", A29="в аренде 2"), J29-K29, "") | J29: =IF(OR(A29="в аренде", A29="в аренде 1", A29="в аренде 2"), DATEDIF(E29, TODAY(), "D")*H29, "") | K29: =8000+8000+8000+8000 -> 32000 | N29: 31600 | O29: =IFERROR(__xludf.DUMMYFUNCTION("IFERROR( VLOOKUP(C29, FILTER( IMPORTRANGE(""https://docs.google.com/spreadsheets/d/1ZBCmVvzoFu7X0td7O5T5xSJplK8m8h9wvdESBc0a1EE/edit#gid=1841437934"", ""Лист1!$C:$I""), IMPORTRANGE(""https://docs.google.com/spreadsheets/d/1ZBCmVvzoFu7X0"&"td7O5T5xSJplK8m8h9wvdESBc0a1EE/edit#gid=1841437934"", ""Лист1!$C:$C"") = C29 ), 7, FALSE ), """" ) "),"") | P29: =IFERROR(__xludf.DUMMYFUNCTION("IF(OR(ISBLANK(Q29), ISBLANK(O29), VALUE(SUBSTITUTE(INDEX(SPLIT(IF(ISBLANK(R29), Q29, R29), "" km""), 0, 1), "" "", """")) - O29 = 0), """", IF(ISBLANK(R29), VALUE(SUBSTITUTE(INDEX(SPLIT(Q29, "" km""), 0, 1), "" "", """")) - O29, VALUE(SUBSTITUTE(INDEX(SPL"&"IT(R29, "" km""), 0, 1), "" "", """")) - O29))"),31600.0) -> 31600 | Q29: =IF(AND(ISBLANK(N29), ISBLANK(E29), ISBLANK(R29)), "", IF(ISBLANK(R29), TEXT(N29, "#,##0") & " Km, " & TEXT(E29, "dd.mm.yyyy"), R29)) -> 31 600 Km, 22.11.2022 | S29: 0 | T29: 2 | U29: @fansyl | V29: толпа из 4 человек намудрили с паспортом не опытные | W29: =IF(F29 = "", "", IF(NOW() > (DATEVALUE(LEFT(F29, SEARCH(",", F29) - 2)) + TIMEVALUE(MID(F29, SEARCH(",", F29) + 2, 5))), "Завершена", "В аренде")) -> #VALUE! | X29: =IFERROR(__xludf.DUMMYFUNCTION("IF(C29 = """", """", IF(REGEXMATCH(C29, ""PCX|NMAX|ADV|CLICK""), ""скутер"", ""мото""))"),"скутер") -> скутер
A30: Завершена | B30: OFF | C30: FORZA 300CC GREY PHUKET 4234 | D30: Владимир | E30: 44887 | F30: 44917 | G30: =IF((E30="")+(F30=""), "", IF(DATEDIF(E30, F30, "d") > 30, DATEDIF(E30, F30, "m") & " М", DATEDIF(E30, F30, "d") & " Д")) -> 30 Д | H30: =13000/30 -> 433.33333 | I30: =IF(OR(A30="в аренде", A30="в аренде 1", A30="в аренде 2"), J30-K30, "") | J30: =IF(OR(A30="в аренде", A30="в аренде 1", A30="в аренде 2"), DATEDIF(E30, TODAY(), "D")*H30, "") | K30: =13000+3467 -> 16467 | N30: 17800 | O30: =IFERROR(__xludf.DUMMYFUNCTION("IFERROR( VLOOKUP(C30, FILTER( IMPORTRANGE(""https://docs.google.com/spreadsheets/d/1ZBCmVvzoFu7X0td7O5T5xSJplK8m8h9wvdESBc0a1EE/edit#gid=1841437934"", ""Лист1!$C:$I""), IMPORTRANGE(""https://docs.google.com/spreadsheets/d/1ZBCmVvzoFu7X0"&"td7O5T5xSJplK8m8h9wvdESBc0a1EE/edit#gid=1841437934"", ""Лист1!$C:$C"") = C30 ), 7, FALSE ), """" ) "),"") | P30: =IFERROR(__xludf.DUMMYFUNCTION("IF(OR(ISBLANK(Q30), ISBLANK(O30), VALUE(SUBSTITUTE(INDEX(SPLIT(IF(ISBLANK(R30), Q30, R30), "" km""), 0, 1), "" "", """")) - O30 = 0), """", IF(ISBLANK(R30), VALUE(SUBSTITUTE(INDEX(SPLIT(Q30, "" km""), 0, 1), "" "", """")) - O30, VALUE(SUBSTITUTE(INDEX(SPL"&"IT(R30, "" km""), 0, 1), "" "", """")) - O30))"),17800.0) -> 17800 | Q30: =IF(AND(ISBLANK(N30), ISBLANK(E30), ISBLANK(R30)), "", IF(ISBLANK(R30), TEXT(N30, "#,##0") & " Km, " & TEXT(E30, "dd.mm.yyyy"), R30)) -> 17 800 Km, 22.11.2022 | S30: 5000 | T30: 3 | U30: @VoV51 | V30: гуд на спорте | W30: =IF(F30 = "", "", IF(NOW() > (DATEVALUE(LEFT(F30, SEARCH(",", F30) - 2)) + TIMEVALUE(MID(F30, SEARCH(",", F30) + 2, 5))), "Завершена", "В аренде")) -> Завершена | X30: =IFERROR(__xludf.DUMMYFUNCTION("IF(C30 = """", """", IF(REGEXMATCH(C30, ""PCX|NMAX|ADV|CLICK""), ""скутер"", ""мото""))"),"мото") -> мото
A31: Завершена | B31: OFF | C31: NMAX 155CC GREY NOSMART PHUKET 5508 | D31: Константин | E31: 44887 | F31: 44917 | G31: =IF((E31="")+(F31=""), "", IF(DATEDIF(E31, F31, "d") > 30, DATEDIF(E31, F31, "m") & " М", DATEDIF(E31, F31, "d") & " Д")) -> 30 Д | H31: =7000/30 -> 233.33333 | I31: =IF(OR(A31="в аренде", A31="в аренде 1", A31="в аренде 2"), J31-K31, "") | J31: =IF(OR(A31="в аренде", A31="в аренде 1", A31="в аренде 2"), DATEDIF(E31, TODAY(), "D")*H31, "") | K31: 7000 | N31: 24800 | O31: =IFERROR(__xludf.DUMMYFUNCTION("IFERROR( VLOOKUP(C31, FILTER( IMPORTRANGE(""https://docs.google.com/spreadsheets/d/1ZBCmVvzoFu7X0td7O5T5xSJplK8m8h9wvdESBc0a1EE/edit#gid=1841437934"", ""Лист1!$C:$I""), IMPORTRANGE(""https://docs.google.com/spreadsheets/d/1ZBCmVvzoFu7X0"&"td7O5T5xSJplK8m8h9wvdESBc0a1EE/edit#gid=1841437934"", ""Лист1!$C:$C"") = C31 ), 7, FALSE ), """" ) "),"") | P31: =IFERROR(__xludf.DUMMYFUNCTION("IF(OR(ISBLANK(Q31), ISBLANK(O31), VALUE(SUBSTITUTE(INDEX(SPLIT(IF(ISBLANK(R31), Q31, R31), "" km""), 0, 1), "" "", """")) - O31 = 0), """", IF(ISBLANK(R31), VALUE(SUBSTITUTE(INDEX(SPLIT(Q31, "" km""), 0, 1), "" "", """")) - O31, VALUE(SUBSTITUTE(INDEX(SPL"&"IT(R31, "" km""), 0, 1), "" "", """")) - O31))"),24800.0) -> 24800 | Q31: =IF(AND(ISBLANK(N31), ISBLANK(E31), ISBLANK(R31)), "", IF(ISBLANK(R31), TEXT(N31, "#,##0") & " Km, " & TEXT(E31, "dd.mm.yyyy"), R31)) -> 24 800 Km, 22.11.2022 | S31: 100 | T31: 2 | U31: @fansyl | V31: толпа из 4 человек намудрили с паспортом не опытные | W31: =IF(F31 = "", "", IF(NOW() > (DATEVALUE(LEFT(F31, SEARCH(",", F31) - 2)) + TIMEVALUE(MID(F31, SEARCH(",", F31) + 2, 5))), "Завершена", "В аренде")) -> Завершена | X31: =IFERROR(__xludf.DUMMYFUNCTION("IF(C31 = """", """", IF(REGEXMATCH(C31, ""PCX|NMAX|ADV|CLICK""), ""скутер"", ""мото""))"),"скутер") -> скутер
A32: Завершена | B32: OFF | C32: CLICK 125CC PHUKET 5580 | D32: Дмитрий | E32: 44888 | F32: 45008 | G32: =IF((E32="")+(F32=""), "", IF(DATEDIF(E32, F32, "d") > 30, DATEDIF(E32, F32, "m") & " М", DATEDIF(E32, F32, "d") & " Д")) -> 4 М | H32: =4000/30 -> 133.33333 | I32: =IF(OR(A32="в аренде", A32="в аренде 1", A32="в аренде 2"), J32-K32, "") | J32: =IF(OR(A32="в аренде", A32="в аренде 1", A32="в аренде 2"), DATEDIF(E32, TODAY(), "D")*H32, "") | K32: =4000+4000+200+4000+4000 -> 16200 | N32: 26800 | O32: =IFERROR(__xludf.DUMMYFUNCTION("IFERROR( VLOOKUP(C32, FILTER( IMPORTRANGE(""https://docs.google.com/spreadsheets/d/1ZBCmVvzoFu7X0td7O5T5xSJplK8m8h9wvdESBc0a1EE/edit#gid=1841437934"", ""Лист1!$C:$I""), IMPORTRANGE(""https://docs.google.com/spreadsheets/d/1ZBCmVvzoFu7X0"&"td7O5T5xSJplK8m8h9wvdESBc0a1EE/edit#gid=1841437934"", ""Лист1!$C:$C"") = C32 ), 7, FALSE ), """" ) "),33515.0) -> 33515 | P32: =IFERROR(__xludf.DUMMYFUNCTION("IF(OR(ISBLANK(Q32), ISBLANK(O32), VALUE(SUBSTITUTE(INDEX(SPLIT(IF(ISBLANK(R32), Q32, R32), "" km""), 0, 1), "" "", """")) - O32 = 0), """", IF(ISBLANK(R32), VALUE(SUBSTITUTE(INDEX(SPLIT(Q32, "" km""), 0, 1), "" "", """")) - O32, VALUE(SUBSTITUTE(INDEX(SPL"&"IT(R32, "" km""), 0, 1), "" "", """")) - O32))"),-6715.0) -> -6715 | Q32: =IF(AND(ISBLANK(N32), ISBLANK(E32), ISBLANK(R32)), "", IF(ISBLANK(R32), TEXT(N32, "#,##0") & " Km, " & TEXT(E32, "dd.mm.yyyy"), R32)) -> 26 800 Km, 23.11.2022 | S32: 3000 | T32: 1 | U32: @Valdman | V32: Дима из компании артема | W32: =IF(F32 = "", "", IF(NOW() > (DATEVALUE(LEFT(F32, SEARCH(",", F32) - 2)) + TIMEVALUE(MID(F32, SEARCH(",", F32) + 2, 5))), "Завершена", "В аренде")) -> Завершена | X32: =IFERROR(__xludf.DUMMYFUNCTION("IF(C32 = """", """", IF(REGEXMATCH(C32, ""PCX|NMAX|ADV|CLICK""), ""скутер"", ""мото""))"),"скутер") -> скутер
A33: Завершена | B33: OFF | C33: CBR 650R PHUKET 4505 | D33: Александр Степанов | E33: 44889 | F33: 44894 | G33: =IF((E33="")+(F33=""), "", IF(DATEDIF(E33, F33, "d") > 30, DATEDIF(E33, F33, "m") & " М", DATEDIF(E33, F33, "d") & " Д")) -> 5 Д | H33: 2200 | I33: =IF(OR(A33="в аренде", A33="в аренде 1", A33="в аренде 2"), J33-K33, "") | J33: =IF(OR(A33="в аренде", A33="в аренде 1", A33="в аренде 2"), DATEDIF(E33, TODAY(), "D")*H33, "") | K33: 11000 | N33: 27573 | O33: =IFERROR(__xludf.DUMMYFUNCTION("IFERROR( VLOOKUP(C33, FILTER( IMPORTRANGE(""https://docs.google.com/spreadsheets/d/1ZBCmVvzoFu7X0td7O5T5xSJplK8m8h9wvdESBc0a1EE/edit#gid=1841437934"", ""Лист1!$C:$I""), IMPORTRANGE(""https://docs.google.com/spreadsheets/d/1ZBCmVvzoFu7X0"&"td7O5T5xSJplK8m8h9wvdESBc0a1EE/edit#gid=1841437934"", ""Лист1!$C:$C"") = C33 ), 7, FALSE ), """" ) "),63700.0) -> 63700 | P33: =IFERROR(__xludf.DUMMYFUNCTION("IF(OR(ISBLANK(Q33), ISBLANK(O33), VALUE(SUBSTITUTE(INDEX(SPLIT(IF(ISBLANK(R33), Q33, R33), "" km""), 0, 1), "" "", """")) - O33 = 0), """", IF(ISBLANK(R33), VALUE(SUBSTITUTE(INDEX(SPLIT(Q33, "" km""), 0, 1), "" "", """")) - O33, VALUE(SUBSTITUTE(INDEX(SPL"&"IT(R33, "" km""), 0, 1), "" "", """")) - O33))"),-36127.0) -> -36127 | Q33: =IF(AND(ISBLANK(N33), ISBLANK(E33), ISBLANK(R33)), "", IF(ISBLANK(R33), TEXT(N33, "#,##0") & " Km, " & TEXT(E33, "dd.mm.yyyy"), R33)) -> 27 573 Km, 24.11.2022 | S33: 17000 | T33: 1 | U33: @fomLeyb | V33: опытный скромный | W33: =IF(F33 = "", "", IF(NOW() > (DATEVALUE(LEFT(F33, SEARCH(",", F33) - 2)) + TIMEVALUE(MID(F33, SEARCH(",", F33) + 2, 5))), "Завершена", "В аренде")) -> Завершена | X33: =IFERROR(__xludf.DUMMYFUNCTION("IF(C33 = """", """", IF(REGEXMATCH(C33, ""PCX|NMAX|ADV|CLICK""), ""скутер"", ""мото""))"),"мото") -> мото
A34: Завершена | B34: OFF | C34: NMAX 155CC GREY MATT PHUKET 7527 | D34: Алина Галеева | E34: 44893 | F34: 44976 | G34: =IF((E34="")+(F34=""), "", IF(DATEDIF(E34, F34, "d") > 30, DATEDIF(E34, F34, "m") & " М", DATEDIF(E34, F34, "d") & " Д")) -> 2 М | H34: =8000/30 -> 266.66667 | I34: =IF(OR(A34="в аренде", A34="в аренде 1", A34="в аренде 2"), J34-K34, "") | J34: =IF(OR(A34="в аренде", A34="в аренде 1", A34="в аренде 2"), DATEDIF(E34, TODAY(), "D")*H34, "") | K34: =12000+8000+2670 -> 22670 | N34: 13300 | O34: =IFERROR(__xludf.DUMMYFUNCTION("IFERROR( VLOOKUP(C34, FILTER( IMPORTRANGE(""https://docs.google.com/spreadsheets/d/1ZBCmVvzoFu7X0td7O5T5xSJplK8m8h9wvdESBc0a1EE/edit#gid=1841437934"", ""Лист1!$C:$I""), IMPORTRANGE(""https://docs.google.com/spreadsheets/d/1ZBCmVvzoFu7X0"&"td7O5T5xSJplK8m8h9wvdESBc0a1EE/edit#gid=1841437934"", ""Лист1!$C:$C"") = C34 ), 7, FALSE ), """" ) "),"") | P34: =IFERROR(__xludf.DUMMYFUNCTION("IF(OR(ISBLANK(Q34), ISBLANK(O34), VALUE(SUBSTITUTE(INDEX(SPLIT(IF(ISBLANK(R34), Q34, R34), "" km""), 0, 1), "" "", """")) - O34 = 0), """", IF(ISBLANK(R34), VALUE(SUBSTITUTE(INDEX(SPLIT(Q34, "" km""), 0, 1), "" "", """")) - O34, VALUE(SUBSTITUTE(INDEX(SPL"&"IT(R34, "" km""), 0, 1), "" "", """")) - O34))"),13300.0) -> 13300 | Q34: =IF(AND(ISBLANK(N34), ISBLANK(E34), ISBLANK(R34)), "", IF(ISBLANK(R34), TEXT(N34, "#,##0") & " Km, " & TEXT(E34, "dd.mm.yyyy"), R34)) -> 13 300 Km, 28.11.2022 | S34: 3000 | T34: 1 | U34: @alinochf | V34: медленная опыта не много | W34: =IF(F34 = "", "", IF(NOW() > (DATEVALUE(LEFT(F34, SEARCH(",", F34) - 2)) + TIMEVALUE(MID(F34, SEARCH(",", F34) + 2, 5))), "Завершена", "В аренде")) -> Завершена | X34: =IFERROR(__xludf.DUMMYFUNCTION("IF(C34 = """", """", IF(REGEXMATCH(C34, ""PCX|NMAX|ADV|CLICK""), ""скутер"", ""мото""))"),"скутер") -> скутер
A35: Завершена | B35: OFF | C35: XMAX 300CC Y-CON | D35: Александр Ильин | E35: 44893 | F35: 45044 | G35: =IF((E35="")+(F35=""), "", IF(DATEDIF(E35, F35, "d") > 30, DATEDIF(E35, F35, "m") & " М", DATEDIF(E35, F35, "d") & " Д")) -> 5 М | H35: =14000/30 -> 466.66667 | I35: =IF(OR(A35="в аренде", A35="в аренде 1", A35="в аренде 2"), J35-K35, "") | J35: =IF(OR(A35="в аренде", A35="в аренде 1", A35="в аренде 2"), DATEDIF(E35, TODAY(), "D")*H35, "") | K35: =15300-3000+1633+14000+14000+14000+14000+14000 -> 83933 | N35: 18800 | O35: =IFERROR(__xludf.DUMMYFUNCTION("IFERROR( VLOOKUP(C35, FILTER( IMPORTRANGE(""https://docs.google.com/spreadsheets/d/1ZBCmVvzoFu7X0td7O5T5xSJplK8m8h9wvdESBc0a1EE/edit#gid=1841437934"", ""Лист1!$C:$I""), IMPORTRANGE(""https://docs.google.com/spreadsheets/d/1ZBCmVvzoFu7X0"&"td7O5T5xSJplK8m8h9wvdESBc0a1EE/edit#gid=1841437934"", ""Лист1!$C:$C"") = C35 ), 7, FALSE ), """" ) "),"") | P35: =IFERROR(__xludf.DUMMYFUNCTION("IF(OR(ISBLANK(Q35), ISBLANK(O35), VALUE(SUBSTITUTE(INDEX(SPLIT(IF(ISBLANK(R35), Q35, R35), "" km""), 0, 1), "" "", """")) - O35 = 0), """", IF(ISBLANK(R35), VALUE(SUBSTITUTE(INDEX(SPLIT(Q35, "" km""), 0, 1), "" "", """")) - O35, VALUE(SUBSTITUTE(INDEX(SPL"&"IT(R35, "" km""), 0, 1), "" "", """")) - O35))"),18800.0) -> 18800 | Q35: =IF(AND(ISBLANK(N35), ISBLANK(E35), ISBLANK(R35)), "", IF(ISBLANK(R35), TEXT(N35, "#,##0") & " Km, " & TEXT(E35, "dd.mm.yyyy"), R35)) -> 18 800 Km, 28.11.2022 | S35: 5000 | T35: 1 | U35: @Alex_hetzer | V35: немного странный но ок опыт не большой | W35: =IF(F35 = "", "", IF(NOW() > (DATEVALUE(LEFT(F35, SEARCH(",", F35) - 2)) + TIMEVALUE(MID(F35, SEARCH(",", F35) + 2, 5))), "Завершена", "В аренде")) -> Завершена | X35: =IFERROR(__xludf.DUMMYFUNCTION("IF(C35 = """", """", IF(REGEXMATCH(C35, ""PCX|NMAX|ADV|CLICK""), ""скутер"", ""мото""))"),"мото") -> мото
A36: Завершена | B36: OFF | C36: XMAX 300CC BLUE PHUKET 5773 | D36: Дмитрий Чепурной | E36: 44895 | F36: 44925 | G36: =IF((E36="")+(F36=""), "", IF(DATEDIF(E36, F36, "d") > 30, DATEDIF(E36, F36, "m") & " М", DATEDIF(E36, F36, "d") & " Д")) -> 30 Д | H36: =14000/30 -> 466.66667 | I36: =IF(OR(A36="в аренде", A36="в аренде 1", A36="в аренде 2"), J36-K36, "") | J36: =IF(OR(A36="в аренде", A36="в аренде 1", A36="в аренде 2"), DATEDIF(E36, TODAY(), "D")*H36, "") | K36: 14000 | N36: 29000 | O36: =IFERROR(__xludf.DUMMYFUNCTION("IFERROR( VLOOKUP(C36, FILTER( IMPORTRANGE(""https://docs.google.com/spreadsheets/d/1ZBCmVvzoFu7X0td7O5T5xSJplK8m8h9wvdESBc0a1EE/edit#gid=1841437934"", ""Лист1!$C:$I""), IMPORTRANGE(""https://docs.google.com/spreadsheets/d/1ZBCmVvzoFu7X0"&"td7O5T5xSJplK8m8h9wvdESBc0a1EE/edit#gid=1841437934"", ""Лист1!$C:$C"") = C36 ), 7, FALSE ), """" ) "),23500.0) -> 23500 | P36: =IFERROR(__xludf.DUMMYFUNCTION("IF(OR(ISBLANK(Q36), ISBLANK(O36), VALUE(SUBSTITUTE(INDEX(SPLIT(IF(ISBLANK(R36), Q36, R36), "" km""), 0, 1), "" "", """")) - O36 = 0), """", IF(ISBLANK(R36), VALUE(SUBSTITUTE(INDEX(SPLIT(Q36, "" km""), 0, 1), "" "", """")) - O36, VALUE(SUBSTITUTE(INDEX(SPL"&"IT(R36, "" km""), 0, 1), "" "", """")) - O36))"),5500.0) -> 5500 | Q36: =IF(AND(ISBLANK(N36), ISBLANK(E36), ISBLANK(R36)), "", IF(ISBLANK(R36), TEXT(N36, "#,##0") & " Km, " & TEXT(E36, "dd.mm.yyyy"), R36)) -> 29 000 Km, 30.11.2022 | S36: 5000 | T36: 2 | V36: здоровый сахалин | W36: =IF(F36 = "", "", IF(NOW() > (DATEVALUE(LEFT(F36, SEARCH(",", F36) - 2)) + TIMEVALUE(MID(F36, SEARCH(",", F36) + 2, 5))), "Завершена", "В аренде")) -> Завершена | X36: =IFERROR(__xludf.DUMMYFUNCTION("IF(C36 = """", """", IF(REGEXMATCH(C36, ""PCX|NMAX|ADV|CLICK""), ""скутер"", ""мото""))"),"мото") -> мото
A37: Завершена | B37: OFF | C37: NMAX 155CC BLACK GOLD-2 PHUKET 4685 | D37: Рашид от адлер лав | E37: 44895 | F37: 44979 | G37: =IF((E37="")+(F37=""), "", IF(DATEDIF(E37, F37, "d") > 30, DATEDIF(E37, F37, "m") & " М", DATEDIF(E37, F37, "d") & " Д")) -> 2 М | H37: 277 | I37: =IF(OR(A37="в аренде", A37="в аренде 1", A37="в аренде 2"), J37-K37, "") | J37: =IF(OR(A37="в аренде", A37="в аренде 1", A37="в аренде 2"), DATEDIF(E37, TODAY(), "D")*H37, "") | K37: =8000+8000+7000 -> 23000 | N37: 20900 | O37: =IFERROR(__xludf.DUMMYFUNCTION("IFERROR( VLOOKUP(C37, FILTER( IMPORTRANGE(""https://docs.google.com/spreadsheets/d/1ZBCmVvzoFu7X0td7O5T5xSJplK8m8h9wvdESBc0a1EE/edit#gid=1841437934"", ""Лист1!$C:$I""), IMPORTRANGE(""https://docs.google.com/spreadsheets/d/1ZBCmVvzoFu7X0"&"td7O5T5xSJplK8m8h9wvdESBc0a1EE/edit#gid=1841437934"", ""Лист1!$C:$C"") = C37 ), 7, FALSE ), """" ) "),36400.0) -> 36400 | P37: =IFERROR(__xludf.DUMMYFUNCTION("IF(OR(ISBLANK(Q37), ISBLANK(O37), VALUE(SUBSTITUTE(INDEX(SPLIT(IF(ISBLANK(R37), Q37, R37), "" km""), 0, 1), "" "", """")) - O37 = 0), """", IF(ISBLANK(R37), VALUE(SUBSTITUTE(INDEX(SPLIT(Q37, "" km""), 0, 1), "" "", """")) - O37, VALUE(SUBSTITUTE(INDEX(SPL"&"IT(R37, "" km""), 0, 1), "" "", """")) - O37))"),-15500.0) -> -15500 | Q37: =IF(AND(ISBLANK(N37), ISBLANK(E37), ISBLANK(R37)), "", IF(ISBLANK(R37), TEXT(N37, "#,##0") & " Km, " & TEXT(E37, "dd.mm.yyyy"), R37)) -> 20 900 Km, 30.11.2022 | S37: 3000 | T37: 2 | U37: 080-354-0112 | V37: хз резкий компания из трех | W37: =IF(F37 = "", "", IF(NOW() > (DATEVALUE(LEFT(F37, SEARCH(",", F37) - 2)) + TIMEVALUE(MID(F37, SEARCH(",", F37) + 2, 5))), "Завершена", "В аренде")) -> Завершена | X37: =IFERROR(__xludf.DUMMYFUNCTION("IF(C37 = """", """", IF(REGEXMATCH(C37, ""PCX|NMAX|ADV|CLICK""), ""скутер"", ""мото""))"),"скутер") -> скутер
A38: Завершена | B38: OFF | C38: CBR 650R PHUKET 4505 | D38: Petr Lerman | E38: 44897 | F38: 44904 | G38: =IF((E38="")+(F38=""), "", IF(DATEDIF(E38, F38, "d") > 30, DATEDIF(E38, F38, "m") & " М", DATEDIF(E38, F38, "d") & " Д")) -> 7 Д | H38: =14500/7 -> 2071.4286 | I38: =IF(OR(A38="в аренде", A38="в аренде 1", A38="в аренде 2"), J38-K38, "") | J38: =IF(OR(A38="в аренде", A38="в аренде 1", A38="в аренде 2"), DATEDIF(E38, TODAY(), "D")*H38, "") | K38: 14500 | N38: 27900 | O38: =IFERROR(__xludf.DUMMYFUNCTION("IFERROR( VLOOKUP(C38, FILTER( IMPORTRANGE(""https://docs.google.com/spreadsheets/d/1ZBCmVvzoFu7X0td7O5T5xSJplK8m8h9wvdESBc0a1EE/edit#gid=1841437934"", ""Лист1!$C:$I""), IMPORTRANGE(""https://docs.google.com/spreadsheets/d/1ZBCmVvzoFu7X0"&"td7O5T5xSJplK8m8h9wvdESBc0a1EE/edit#gid=1841437934"", ""Лист1!$C:$C"") = C38 ), 7, FALSE ), """" ) "),63700.0) -> 63700 | P38: =IFERROR(__xludf.DUMMYFUNCTION("IF(OR(ISBLANK(Q38), ISBLANK(O38), VALUE(SUBSTITUTE(INDEX(SPLIT(IF(ISBLANK(R38), Q38, R38), "" km""), 0, 1), "" "", """")) - O38 = 0), """", IF(ISBLANK(R38), VALUE(SUBSTITUTE(INDEX(SPLIT(Q38, "" km""), 0, 1), "" "", """")) - O38, VALUE(SUBSTITUTE(INDEX(SPL"&"IT(R38, "" km""), 0, 1), "" "", """")) - O38))"),-35800.0) -> -35800 | Q38: =IF(AND(ISBLANK(N38), ISBLANK(E38), ISBLANK(R38)), "", IF(ISBLANK(R38), TEXT(N38, "#,##0") & " Km, " & TEXT(E38, "dd.mm.yyyy"), R38)) -> 27 900 Km, 02.12.2022 | S38: 17500 | T38: 1 | U38: @m1333333333 | V38: интересный чел при деньгах | W38: =IF(F38 = "", "", IF(NOW() > (DATEVALUE(LEFT(F38, SEARCH(",", F38) - 2)) + TIMEVALUE(MID(F38, SEARCH(",", F38) + 2, 5))), "Завершена", "В аренде")) -> Завершена | X38: =IFERROR(__xludf.DUMMYFUNCTION("IF(C38 = """", """", IF(REGEXMATCH(C38, ""PCX|NMAX|ADV|CLICK""), ""скутер"", ""мото""))"),"мото") -> мото
A39: Завершена | B39: OFF | C39: NMAX 155CC BLACK PHUKET 8952 | D39: Timur Agliev | E39: 44897 | F39: 44915 | G39: =IF((E39="")+(F39=""), "", IF(DATEDIF(E39, F39, "d") > 30, DATEDIF(E39, F39, "m") & " М", DATEDIF(E39, F39, "d") & " Д")) -> 18 Д | H39: 400 | I39: =IF(OR(A39="в аренде", A39="в аренде 1", A39="в аренде 2"), J39-K39, "") | J39: =IF(OR(A39="в аренде", A39="в аренде 1", A39="в аренде 2"), DATEDIF(E39, TODAY(), "D")*H39, "") | K39: 7000 | N39: 15600 | O39: =IFERROR(__xludf.DUMMYFUNCTION("IFERROR( VLOOKUP(C39, FILTER( IMPORTRANGE(""https://docs.google.com/spreadsheets/d/1ZBCmVvzoFu7X0td7O5T5xSJplK8m8h9wvdESBc0a1EE/edit#gid=1841437934"", ""Лист1!$C:$I""), IMPORTRANGE(""https://docs.google.com/spreadsheets/d/1ZBCmVvzoFu7X0"&"td7O5T5xSJplK8m8h9wvdESBc0a1EE/edit#gid=1841437934"", ""Лист1!$C:$C"") = C39 ), 7, FALSE ), """" ) "),35800.0) -> 35800 | P39: =IFERROR(__xludf.DUMMYFUNCTION("IF(OR(ISBLANK(Q39), ISBLANK(O39), VALUE(SUBSTITUTE(INDEX(SPLIT(IF(ISBLANK(R39), Q39, R39), "" km""), 0, 1), "" "", """")) - O39 = 0), """", IF(ISBLANK(R39), VALUE(SUBSTITUTE(INDEX(SPLIT(Q39, "" km""), 0, 1), "" "", """")) - O39, VALUE(SUBSTITUTE(INDEX(SPL"&"IT(R39, "" km""), 0, 1), "" "", """")) - O39))"),-20200.0) -> -20200 | Q39: =IF(AND(ISBLANK(N39), ISBLANK(E39), ISBLANK(R39)), "", IF(ISBLANK(R39), TEXT(N39, "#,##0") & " Km, " & TEXT(E39, "dd.mm.yyyy"), R39)) -> 15 600 Km, 02.12.2022 | S39: 0 | T39: 2 | U39: @tech_nar | V39: Пиздательный бабла гоняльщик | W39: =IF(F39 = "", "", IF(NOW() > (DATEVALUE(LEFT(F39, SEARCH(",", F39) - 2)) + TIMEVALUE(MID(F39, SEARCH(",", F39) + 2, 5))), "Завершена", "В аренде")) -> Завершена | X39: =IFERROR(__xludf.DUMMYFUNCTION("IF(C39 = """", """", IF(REGEXMATCH(C39, ""PCX|NMAX|ADV|CLICK""), ""скутер"", ""мото""))"),"скутер") -> скутер
A40: Завершена | B40: OFF | C40: XMAX 300CC RED MATT PHUKET 8943 | D40: Всеволод Головин | E40: 44901 | F40: 45022 | G40: =IF((E40="")+(F40=""), "", IF(DATEDIF(E40, F40, "d") > 30, DATEDIF(E40, F40, "m") & " М", DATEDIF(E40, F40, "d") & " Д")) -> 4 М | H40: =13000/30 -> 433.33333 | I40: =IF(OR(A40="в аренде", A40="в аренде 1", A40="в аренде 2"), J40-K40, "") | J40: =IF(OR(A40="в аренде", A40="в аренде 1", A40="в аренде 2"), DATEDIF(E40, TODAY(), "D")*H40, "") | K40: =14000+14000+13000 -> 41000 | N40: 21168 | O40: =IFERROR(__xludf.DUMMYFUNCTION("IFERROR( VLOOKUP(C40, FILTER( IMPORTRANGE(""https://docs.google.com/spreadsheets/d/1ZBCmVvzoFu7X0td7O5T5xSJplK8m8h9wvdESBc0a1EE/edit#gid=1841437934"", ""Лист1!$C:$I""), IMPORTRANGE(""https://docs.google.com/spreadsheets/d/1ZBCmVvzoFu7X0"&"td7O5T5xSJplK8m8h9wvdESBc0a1EE/edit#gid=1841437934"", ""Лист1!$C:$C"") = C40 ), 7, FALSE ), """" ) "),"") | P40: =IFERROR(__xludf.DUMMYFUNCTION("IF(OR(ISBLANK(Q40), ISBLANK(O40), VALUE(SUBSTITUTE(INDEX(SPLIT(IF(ISBLANK(R40), Q40, R40), "" km""), 0, 1), "" "", """")) - O40 = 0), """", IF(ISBLANK(R40), VALUE(SUBSTITUTE(INDEX(SPLIT(Q40, "" km""), 0, 1), "" "", """")) - O40, VALUE(SUBSTITUTE(INDEX(SPL"&"IT(R40, "" km""), 0, 1), "" "", """")) - O40))"),21168.0) -> 21168 | Q40: =IF(AND(ISBLANK(N40), ISBLANK(E40), ISBLANK(R40)), "", IF(ISBLANK(R40), TEXT(N40, "#,##0") & " Km, " & TEXT(E40, "dd.mm.yyyy"), R40)) -> 21 168 Km, 06.12.2022 | S40: 5000 | T40: 3 | U40: @housezz | V40: втроем с ребенком но хорошие | W40: =IF(F40 = "", "", IF(NOW() > (DATEVALUE(LEFT(F40, SEARCH(",", F40) - 2)) + TIMEVALUE(MID(F40, SEARCH(",", F40) + 2, 5))), "Завершена", "В аренде")) -> Завершена | X40: =IFERROR(__xludf.DUMMYFUNCTION("IF(C40 = """", """", IF(REGEXMATCH(C40, ""PCX|NMAX|ADV|CLICK""), ""скутер"", ""мото""))"),"мото") -> мото
A41: Завершена | B41: OFF | C41: NMAX 155CC BLACK-2 PHUKET 9561 | D41: Илья Стойков | E41: 44903 | F41: 44980 | G41: =IF((E41="")+(F41=""), "", IF(DATEDIF(E41, F41, "d") > 30, DATEDIF(E41, F41, "m") & " М", DATEDIF(E41, F41, "d") & " Д")) -> 2 М | H41: =8000/30 -> 266.66667 | I41: =IF(OR(A41="в аренде", A41="в аренде 1", A41="в аренде 2"), J41-K41, "") | J41: =IF(OR(A41="в аренде", A41="в аренде 1", A41="в аренде 2"), DATEDIF(E41, TODAY(), "D")*H41, "") | K41: =8000+12280 -> 20280 | N41: 11358 | O41: =IFERROR(__xludf.DUMMYFUNCTION("IFERROR( VLOOKUP(C41, FILTER( IMPORTRANGE(""https://docs.google.com/spreadsheets/d/1ZBCmVvzoFu7X0td7O5T5xSJplK8m8h9wvdESBc0a1EE/edit#gid=1841437934"", ""Лист1!$C:$I""), IMPORTRANGE(""https://docs.google.com/spreadsheets/d/1ZBCmVvzoFu7X0"&"td7O5T5xSJplK8m8h9wvdESBc0a1EE/edit#gid=1841437934"", ""Лист1!$C:$C"") = C41 ), 7, FALSE ), """" ) "),"") | P41: =IFERROR(__xludf.DUMMYFUNCTION("IF(OR(ISBLANK(Q41), ISBLANK(O41), VALUE(SUBSTITUTE(INDEX(SPLIT(IF(ISBLANK(R41), Q41, R41), "" km""), 0, 1), "" "", """")) - O41 = 0), """", IF(ISBLANK(R41), VALUE(SUBSTITUTE(INDEX(SPLIT(Q41, "" km""), 0, 1), "" "", """")) - O41, VALUE(SUBSTITUTE(INDEX(SPL"&"IT(R41, "" km""), 0, 1), "" "", """")) - O41))"),11358.0) -> 11358 | Q41: =IF(AND(ISBLANK(N41), ISBLANK(E41), ISBLANK(R41)), "", IF(ISBLANK(R41), TEXT(N41, "#,##0") & " Km, " & TEXT(E41, "dd.mm.yyyy"), R41)) -> 11 358 Km, 08.12.2022 | S41: 3000 | T41: 1 | U41: @stojkovD | V41: беларус машенник с ботом | W41: =IF(F41 = "", "", IF(NOW() > (DATEVALUE(LEFT(F41, SEARCH(",", F41) - 2)) + TIMEVALUE(MID(F41, SEARCH(",", F41) + 2, 5))), "Завершена", "В аренде")) -> Завершена | X41: =IFERROR(__xludf.DUMMYFUNCTION("IF(C41 = """", """", IF(REGEXMATCH(C41, ""PCX|NMAX|ADV|CLICK""), ""скутер"", ""мото""))"),"скутер") -> скутер
A42: Завершена | B42: OFF | C42: NMAX 155CC GREY GOLD PHUKET 6908 | D42: Tigran Bogaov | E42: 44908 | F42: 45004 | G42: =IF((E42="")+(F42=""), "", IF(DATEDIF(E42, F42, "d") > 30, DATEDIF(E42, F42, "m") & " М", DATEDIF(E42, F42, "d") & " Д")) -> 3 М | H42: =8000/30 -> 266.66667 | I42: =IF(OR(A42="в аренде", A42="в аренде 1", A42="в аренде 2"), J42-K42, "") | J42: =IF(OR(A42="в аренде", A42="в аренде 1", A42="в аренде 2"), DATEDIF(E42, TODAY(), "D")*H42, "") | K42: =8000+8000+8000+1600 -> 25600 | N42: 25800 | O42: =IFERROR(__xludf.DUMMYFUNCTION("IFERROR( VLOOKUP(C42, FILTER( IMPORTRANGE(""https://docs.google.com/spreadsheets/d/1ZBCmVvzoFu7X0td7O5T5xSJplK8m8h9wvdESBc0a1EE/edit#gid=1841437934"", ""Лист1!$C:$I""), IMPORTRANGE(""https://docs.google.com/spreadsheets/d/1ZBCmVvzoFu7X0"&"td7O5T5xSJplK8m8h9wvdESBc0a1EE/edit#gid=1841437934"", ""Лист1!$C:$C"") = C42 ), 7, FALSE ), """" ) "),32200.0) -> 32200 | P42: =IFERROR(__xludf.DUMMYFUNCTION("IF(OR(ISBLANK(Q42), ISBLANK(O42), VALUE(SUBSTITUTE(INDEX(SPLIT(IF(ISBLANK(R42), Q42, R42), "" km""), 0, 1), "" "", """")) - O42 = 0), """", IF(ISBLANK(R42), VALUE(SUBSTITUTE(INDEX(SPLIT(Q42, "" km""), 0, 1), "" "", """")) - O42, VALUE(SUBSTITUTE(INDEX(SPL"&"IT(R42, "" km""), 0, 1), "" "", """")) - O42))"),-6400.0) -> -6400 | Q42: =IF(AND(ISBLANK(N42), ISBLANK(E42), ISBLANK(R42)), "", IF(ISBLANK(R42), TEXT(N42, "#,##0") & " Km, " & TEXT(E42, "dd.mm.yyyy"), R42)) -> 25 800 Km, 13.12.2022 | S42: 3000 | T42: 0 | U42: @kseniirose | V42: спокойный норм чел | W42: =IF(F42 = "", "", IF(NOW() > (DATEVALUE(LEFT(F42, SEARCH(",", F42) - 2)) + TIMEVALUE(MID(F42, SEARCH(",", F42) + 2, 5))), "Завершена", "В аренде")) -> Завершена | X42: =IFERROR(__xludf.DUMMYFUNCTION("IF(C42 = """", """", IF(REGEXMATCH(C42, ""PCX|NMAX|ADV|CLICK""), ""скутер"", ""мото""))"),"скутер") -> скутер
A43: Завершена | B43: OFF | C43: NMAX 155CC GREEN BLACK | D43: Олег Николаенко | E43: 44911 | F43: 44942 | G43: =IF((E43="")+(F43=""), "", IF(DATEDIF(E43, F43, "d") > 30, DATEDIF(E43, F43, "m") & " М", DATEDIF(E43, F43, "d") & " Д")) -> 1 М | H43: =9000/30 -> 300 | I43: =IF(OR(A43="в аренде", A43="в аренде 1", A43="в аренде 2"), J43-K43, "") | J43: =IF(OR(A43="в аренде", A43="в аренде 1", A43="в аренде 2"), DATEDIF(E43, TODAY(), "D")*H43, "") | K43: 9000 | N43: 12184 | O43: =IFERROR(__xludf.DUMMYFUNCTION("IFERROR( VLOOKUP(C43, FILTER( IMPORTRANGE(""https://docs.google.com/spreadsheets/d/1ZBCmVvzoFu7X0td7O5T5xSJplK8m8h9wvdESBc0a1EE/edit#gid=1841437934"", ""Лист1!$C:$I""), IMPORTRANGE(""https://docs.google.com/spreadsheets/d/1ZBCmVvzoFu7X0"&"td7O5T5xSJplK8m8h9wvdESBc0a1EE/edit#gid=1841437934"", ""Лист1!$C:$C"") = C43 ), 7, FALSE ), """" ) "),"") | P43: =IFERROR(__xludf.DUMMYFUNCTION("IF(OR(ISBLANK(Q43), ISBLANK(O43), VALUE(SUBSTITUTE(INDEX(SPLIT(IF(ISBLANK(R43), Q43, R43), "" km""), 0, 1), "" "", """")) - O43 = 0), """", IF(ISBLANK(R43), VALUE(SUBSTITUTE(INDEX(SPLIT(Q43, "" km""), 0, 1), "" "", """")) - O43, VALUE(SUBSTITUTE(INDEX(SPL"&"IT(R43, "" km""), 0, 1), "" "", """")) - O43))"),12184.0) -> 12184 | Q43: =IF(AND(ISBLANK(N43), ISBLANK(E43), ISBLANK(R43)), "", IF(ISBLANK(R43), TEXT(N43, "#,##0") & " Km, " & TEXT(E43, "dd.mm.yyyy"), R43)) -> 12 184 Km, 16.12.2022 | S43: 3000 | T43: 2 | U43: @failedtruth +79035654455 | V43: вроде норм чел | W43: =IF(F43 = "", "", IF(NOW() > (DATEVALUE(LEFT(F43, SEARCH(",", F43) - 2)) + TIMEVALUE(MID(F43, SEARCH(",", F43) + 2, 5))), "Завершена", "В аренде")) -> Завершена | X43: =IFERROR(__xludf.DUMMYFUNCTION("IF(C43 = """", """", IF(REGEXMATCH(C43, ""PCX|NMAX|ADV|CLICK""), ""скутер"", ""мото""))"),"скутер") -> скутер
A44: Завершена | B44: OFF | C44: CBR 650R PHUKET 4505 | D44: Stanislav sudakov | E44: 44914 | F44: 44928 | G44: =IF((E44="")+(F44=""), "", IF(DATEDIF(E44, F44, "d") > 30, DATEDIF(E44, F44, "m") & " М", DATEDIF(E44, F44, "d") & " Д")) -> 14 Д | H44: =18000/14 -> 1285.7143 | I44: =IF(OR(A44="в аренде", A44="в аренде 1", A44="в аренде 2"), J44-K44, "") | J44: =IF(OR(A44="в аренде", A44="в аренде 1", A44="в аренде 2"), DATEDIF(E44, TODAY(), "D")*H44, "") | K44: =18000 -> 18000 | N44: 27950 | O44: =IFERROR(__xludf.DUMMYFUNCTION("IFERROR( VLOOKUP(C44, FILTER( IMPORTRANGE(""https://docs.google.com/spreadsheets/d/1ZBCmVvzoFu7X0td7O5T5xSJplK8m8h9wvdESBc0a1EE/edit#gid=1841437934"", ""Лист1!$C:$I""), IMPORTRANGE(""https://docs.google.com/spreadsheets/d/1ZBCmVvzoFu7X0"&"td7O5T5xSJplK8m8h9wvdESBc0a1EE/edit#gid=1841437934"", ""Лист1!$C:$C"") = C44 ), 7, FALSE ), """" ) "),63700.0) -> 63700 | P44: =IFERROR(__xludf.DUMMYFUNCTION("IF(OR(ISBLANK(Q44), ISBLANK(O44), VALUE(SUBSTITUTE(INDEX(SPLIT(IF(ISBLANK(R44), Q44, R44), "" km""), 0, 1), "" "", """")) - O44 = 0), """", IF(ISBLANK(R44), VALUE(SUBSTITUTE(INDEX(SPLIT(Q44, "" km""), 0, 1), "" "", """")) - O44, VALUE(SUBSTITUTE(INDEX(SPL"&"IT(R44, "" km""), 0, 1), "" "", """")) - O44))"),-35750.0) -> -35750 | Q44: =IF(AND(ISBLANK(N44), ISBLANK(E44), ISBLANK(R44)), "", IF(ISBLANK(R44), TEXT(N44, "#,##0") & " Km, " & TEXT(E44, "dd.mm.yyyy"), R44)) -> 27 950 Km, 19.12.2022 | S44: 20000 | T44: 1 | U44: @dndmeplz | V44: адекват | W44: =IF(F44 = "", "", IF(NOW() > (DATEVALUE(LEFT(F44, SEARCH(",", F44) - 2)) + TIMEVALUE(MID(F44, SEARCH(",", F44) + 2, 5))), "Завершена", "В аренде")) -> Завершена | X44: =IFERROR(__xludf.DUMMYFUNCTION("IF(C44 = """", """", IF(REGEXMATCH(C44, ""PCX|NMAX|ADV|CLICK""), ""скутер"", ""мото""))"),"мото") -> мото
A45: Завершена | B45: OFF | C45: XSR 155СС BLACK PHUKET 8949 | D45: Alexandre Valery Etiene | E45: 44916 | F45: 45098 | G45: =IF((E45="")+(F45=""), "", IF(DATEDIF(E45, F45, "d") > 30, DATEDIF(E45, F45, "m") & " М", DATEDIF(E45, F45, "d") & " Д")) -> 6 М | H45: =11000/30 -> 366.66667 | I45: =IF(OR(A45="в аренде", A45="в аренде 1", A45="в аренде 2"), J45-K45, "") | J45: =IF(OR(A45="в аренде", A45="в аренде 1", A45="в аренде 2"), DATEDIF(E45, TODAY(), "D")*H45, "") | K45: =11000+11000+11000+11000+11000 -> 55000 | N45: 4800 | O45: =IFERROR(__xludf.DUMMYFUNCTION("IFERROR( VLOOKUP(C45, FILTER( IMPORTRANGE(""https://docs.google.com/spreadsheets/d/1ZBCmVvzoFu7X0td7O5T5xSJplK8m8h9wvdESBc0a1EE/edit#gid=1841437934"", ""Лист1!$C:$I""), IMPORTRANGE(""https://docs.google.com/spreadsheets/d/1ZBCmVvzoFu7X0"&"td7O5T5xSJplK8m8h9wvdESBc0a1EE/edit#gid=1841437934"", ""Лист1!$C:$C"") = C45 ), 7, FALSE ), """" ) "),27000.0) -> 27000 | P45: =IFERROR(__xludf.DUMMYFUNCTION("IF(OR(ISBLANK(Q45), ISBLANK(O45), VALUE(SUBSTITUTE(INDEX(SPLIT(IF(ISBLANK(R45), Q45, R45), "" km""), 0, 1), "" "", """")) - O45 = 0), """", IF(ISBLANK(R45), VALUE(SUBSTITUTE(INDEX(SPLIT(Q45, "" km""), 0, 1), "" "", """")) - O45, VALUE(SUBSTITUTE(INDEX(SPL"&"IT(R45, "" km""), 0, 1), "" "", """")) - O45))"),-19680.0) -> -19680 | Q45: =IF(AND(ISBLANK(N45), ISBLANK(E45), ISBLANK(R45)), "", IF(ISBLANK(R45), TEXT(N45, "#,##0") & " Km, " & TEXT(E45, "dd.mm.yyyy"), R45)) -> 7320 2 марта | R45: 7320 2 марта | S45: 10000 | T45: 0 | U45: @cannaiseur | V45: очень старный тип хочет в вагнер | W45: =IF(F45 = "", "", IF(NOW() > (DATEVALUE(LEFT(F45, SEARCH(",", F45) - 2)) + TIMEVALUE(MID(F45, SEARCH(",", F45) + 2, 5))), "Завершена", "В аренде")) -> Завершена | X45: =IFERROR(__xludf.DUMMYFUNCTION("IF(C45 = """", """", IF(REGEXMATCH(C45, ""PCX|NMAX|ADV|CLICK""), ""скутер"", ""мото""))"),"мото") -> мото
A46: Завершена | B46: OFF | C46: NMAX 155CC GREY NOSMART PHUKET 5508 | D46: Kirill Fedorenko | E46: 44917 | F46: 44920 | G46: =IF((E46="")+(F46=""), "", IF(DATEDIF(E46, F46, "d") > 30, DATEDIF(E46, F46, "m") & " М", DATEDIF(E46, F46, "d") & " Д")) -> 3 Д | H46: =400 -> 400 | I46: =IF(OR(A46="в аренде", A46="в аренде 1", A46="в аренде 2"), J46-K46, "") | J46: =IF(OR(A46="в аренде", A46="в аренде 1", A46="в аренде 2"), DATEDIF(E46, TODAY(), "D")*H46, "") | K46: 1200 | N46: 25480 | O46: =IFERROR(__xludf.DUMMYFUNCTION("IFERROR( VLOOKUP(C46, FILTER( IMPORTRANGE(""https://docs.google.com/spreadsheets/d/1ZBCmVvzoFu7X0td7O5T5xSJplK8m8h9wvdESBc0a1EE/edit#gid=1841437934"", ""Лист1!$C:$I""), IMPORTRANGE(""https://docs.google.com/spreadsheets/d/1ZBCmVvzoFu7X0"&"td7O5T5xSJplK8m8h9wvdESBc0a1EE/edit#gid=1841437934"", ""Лист1!$C:$C"") = C46 ), 7, FALSE ), """" ) "),"") | P46: =IFERROR(__xludf.DUMMYFUNCTION("IF(OR(ISBLANK(Q46), ISBLANK(O46), VALUE(SUBSTITUTE(INDEX(SPLIT(IF(ISBLANK(R46), Q46, R46), "" km""), 0, 1), "" "", """")) - O46 = 0), """", IF(ISBLANK(R46), VALUE(SUBSTITUTE(INDEX(SPLIT(Q46, "" km""), 0, 1), "" "", """")) - O46, VALUE(SUBSTITUTE(INDEX(SPL"&"IT(R46, "" km""), 0, 1), "" "", """")) - O46))"),25480.0) -> 25480 | Q46: =IF(AND(ISBLANK(N46), ISBLANK(E46), ISBLANK(R46)), "", IF(ISBLANK(R46), TEXT(N46, "#,##0") & " Km, " & TEXT(E46, "dd.mm.yyyy"), R46)) -> 25 480 Km, 22.12.2022 | S46: 3000 | T46: 2 | V46: турист друг соседа | W46: =IF(F46 = "", "", IF(NOW() > (DATEVALUE(LEFT(F46, SEARCH(",", F46) - 2)) + TIMEVALUE(MID(F46, SEARCH(",", F46) + 2, 5))), "Завершена", "В аренде")) -> Завершена | X46: =IFERROR(__xludf.DUMMYFUNCTION("IF(C46 = """", """", IF(REGEXMATCH(C46, ""PCX|NMAX|ADV|CLICK""), ""скутер"", ""мото""))"),"скутер") -> скутер
A47: Завершена | B47: OFF | C47: NMAX 155CC BLACK GOLD PHUKET 4255 | D47: Юлия даширбаданова | E47: 44917 | F47: 45018 | G47: =IF((E47="")+(F47=""), "", IF(DATEDIF(E47, F47, "d") > 30, DATEDIF(E47, F47, "m") & " М", DATEDIF(E47, F47, "d") & " Д")) -> 3 М | H47: =7000/30 -> 233.33333 | I47: =IF(OR(A47="в аренде", A47="в аренде 1", A47="в аренде 2"), J47-K47, "") | J47: =IF(OR(A47="в аренде", A47="в аренде 1", A47="в аренде 2"), DATEDIF(E47, TODAY(), "D")*H47, "") | K47: =7000+7000+7000+2300 -> 23300 | N47: 31318 | O47: =IFERROR(__xludf.DUMMYFUNCTION("IFERROR( VLOOKUP(C47, FILTER( IMPORTRANGE(""https://docs.google.com/spreadsheets/d/1ZBCmVvzoFu7X0td7O5T5xSJplK8m8h9wvdESBc0a1EE/edit#gid=1841437934"", ""Лист1!$C:$I""), IMPORTRANGE(""https://docs.google.com/spreadsheets/d/1ZBCmVvzoFu7X0"&"td7O5T5xSJplK8m8h9wvdESBc0a1EE/edit#gid=1841437934"", ""Лист1!$C:$C"") = C47 ), 7, FALSE ), """" ) "),24094.0) -> 24094 | P47: =IFERROR(__xludf.DUMMYFUNCTION("IF(OR(ISBLANK(Q47), ISBLANK(O47), VALUE(SUBSTITUTE(INDEX(SPLIT(IF(ISBLANK(R47), Q47, R47), "" km""), 0, 1), "" "", """")) - O47 = 0), """", IF(ISBLANK(R47), VALUE(SUBSTITUTE(INDEX(SPLIT(Q47, "" km""), 0, 1), "" "", """")) - O47, VALUE(SUBSTITUTE(INDEX(SPL"&"IT(R47, "" km""), 0, 1), "" "", """")) - O47))"),7224.0) -> 7224 | Q47: =IF(AND(ISBLANK(N47), ISBLANK(E47), ISBLANK(R47)), "", IF(ISBLANK(R47), TEXT(N47, "#,##0") & " Km, " & TEXT(E47, "dd.mm.yyyy"), R47)) -> 31 318 Km, 22.12.2022 | S47: =3000 -> 3000 | T47: 1 | V47: подруга павла | W47: =IF(F47 = "", "", IF(NOW() > (DATEVALUE(LEFT(F47, SEARCH(",", F47) - 2)) + TIMEVALUE(MID(F47, SEARCH(",", F47) + 2, 5))), "Завершена", "В аренде")) -> Завершена | X47: =IFERROR(__xludf.DUMMYFUNCTION("IF(C47 = """", """", IF(REGEXMATCH(C47, ""PCX|NMAX|ADV|CLICK""), ""скутер"", ""мото""))"),"скутер") -> скутер
A48: Завершена | B48: OFF | C48: NMAX 155CC GREY NOSMART PHUKET 5508 | D48: Алексей | E48: 44921 | F48: 44954 | G48: =IF((E48="")+(F48=""), "", IF(DATEDIF(E48, F48, "d") > 30, DATEDIF(E48, F48, "m") & " М", DATEDIF(E48, F48, "d") & " Д")) -> 1 М | H48: 350 | I48: =IF(OR(A48="в аренде", A48="в аренде 1", A48="в аренде 2"), J48-K48, "") | J48: =IF(OR(A48="в аренде", A48="в аренде 1", A48="в аренде 2"), DATEDIF(E48, TODAY(), "D")*H48, "") | K48: 700 | N48: 25600 | O48: =IFERROR(__xludf.DUMMYFUNCTION("IFERROR( VLOOKUP(C48, FILTER( IMPORTRANGE(""https://docs.google.com/spreadsheets/d/1ZBCmVvzoFu7X0td7O5T5xSJplK8m8h9wvdESBc0a1EE/edit#gid=1841437934"", ""Лист1!$C:$I""), IMPORTRANGE(""https://docs.google.com/spreadsheets/d/1ZBCmVvzoFu7X0"&"td7O5T5xSJplK8m8h9wvdESBc0a1EE/edit#gid=1841437934"", ""Лист1!$C:$C"") = C48 ), 7, FALSE ), """" ) "),"") | P48: =IFERROR(__xludf.DUMMYFUNCTION("IF(OR(ISBLANK(Q48), ISBLANK(O48), VALUE(SUBSTITUTE(INDEX(SPLIT(IF(ISBLANK(R48), Q48, R48), "" km""), 0, 1), "" "", """")) - O48 = 0), """", IF(ISBLANK(R48), VALUE(SUBSTITUTE(INDEX(SPLIT(Q48, "" km""), 0, 1), "" "", """")) - O48, VALUE(SUBSTITUTE(INDEX(SPL"&"IT(R48, "" km""), 0, 1), "" "", """")) - O48))"),25600.0) -> 25600 | Q48: =IF(AND(ISBLANK(N48), ISBLANK(E48), ISBLANK(R48)), "", IF(ISBLANK(R48), TEXT(N48, "#,##0") & " Km, " & TEXT(E48, "dd.mm.yyyy"), R48)) -> 25 600 Km, 26.12.2022 | S48: 3000 | T48: 1 | U48: @egorovcrz | V48: опыт есть вроде норм чел с другом @dimanesterov | W48: =IF(F48 = "", "", IF(NOW() > (DATEVALUE(LEFT(F48, SEARCH(",", F48) - 2)) + TIMEVALUE(MID(F48, SEARCH(",", F48) + 2, 5))), "Завершена", "В аренде")) -> Завершена | X48: =IFERROR(__xludf.DUMMYFUNCTION("IF(C48 = """", """", IF(REGEXMATCH(C48, ""PCX|NMAX|ADV|CLICK""), ""скутер"", ""мото""))"),"скутер") -> скутер
A49: Завершена | B49: OFF | C49: XMAX 300CC BLUE PHUKET 5773 | D49: Вячеслав Сербин тг света сербина | E49: 44922 | F49: 44958 | G49: =IF((E49="")+(F49=""), "", IF(DATEDIF(E49, F49, "d") > 30, DATEDIF(E49, F49, "m") & " М", DATEDIF(E49, F49, "d") & " Д")) -> 1 М | H49: =16000/30 -> 533.33333 | I49: =IF(OR(A49="в аренде", A49="в аренде 1", A49="в аренде 2"), J49-K49, "") | J49: =IF(OR(A49="в аренде", A49="в аренде 1", A49="в аренде 2"), DATEDIF(E49, TODAY(), "D")*H49, "") | K49: =16000+1600+400 -> 18000 | N49: 29400 | O49: =IFERROR(__xludf.DUMMYFUNCTION("IFERROR( VLOOKUP(C49, FILTER( IMPORTRANGE(""https://docs.google.com/spreadsheets/d/1ZBCmVvzoFu7X0td7O5T5xSJplK8m8h9wvdESBc0a1EE/edit#gid=1841437934"", ""Лист1!$C:$I""), IMPORTRANGE(""https://docs.google.com/spreadsheets/d/1ZBCmVvzoFu7X0"&"td7O5T5xSJplK8m8h9wvdESBc0a1EE/edit#gid=1841437934"", ""Лист1!$C:$C"") = C49 ), 7, FALSE ), """" ) "),23500.0) -> 23500 | P49: =IFERROR(__xludf.DUMMYFUNCTION("IF(OR(ISBLANK(Q49), ISBLANK(O49), VALUE(SUBSTITUTE(INDEX(SPLIT(IF(ISBLANK(R49), Q49, R49), "" km""), 0, 1), "" "", """")) - O49 = 0), """", IF(ISBLANK(R49), VALUE(SUBSTITUTE(INDEX(SPLIT(Q49, "" km""), 0, 1), "" "", """")) - O49, VALUE(SUBSTITUTE(INDEX(SPL"&"IT(R49, "" km""), 0, 1), "" "", """")) - O49))"),5900.0) -> 5900 | Q49: =IF(AND(ISBLANK(N49), ISBLANK(E49), ISBLANK(R49)), "", IF(ISBLANK(R49), TEXT(N49, "#,##0") & " Km, " & TEXT(E49, "dd.mm.yyyy"), R49)) -> 29 400 Km, 27.12.2022 | S49: 3000 | T49: 4 | U49: 89226553805 0637729363(8) | V49: 4 человека 2 детей | W49: =IF(F49 = "", "", IF(NOW() > (DATEVALUE(LEFT(F49, SEARCH(",", F49) - 2)) + TIMEVALUE(MID(F49, SEARCH(",", F49) + 2, 5))), "Завершена", "В аренде")) -> Завершена | X49: =IFERROR(__xludf.DUMMYFUNCTION("IF(C49 = """", """", IF(REGEXMATCH(C49, ""PCX|NMAX|ADV|CLICK""), ""скутер"", ""мото""))"),"мото") -> мото
A50: Завершена | B50: OFF | C50: ADV 150CC PHUKET 7497 | D50: Вячеслав Сербин тг света сербина | E50: 44922 | F50: 44958 | G50: =IF((E50="")+(F50=""), "", IF(DATEDIF(E50, F50, "d") > 30, DATEDIF(E50, F50, "m") & " М", DATEDIF(E50, F50, "d") & " Д")) -> 1 М | H50: =10000/30 -> 333.33333 | I50: =IF(OR(A50="в аренде", A50="в аренде 1", A50="в аренде 2"), J50-K50, "") | J50: =IF(OR(A50="в аренде", A50="в аренде 1", A50="в аренде 2"), DATEDIF(E50, TODAY(), "D")*H50, "") | K50: 0 | N50: 19950 | O50: =IFERROR(__xludf.DUMMYFUNCTION("IFERROR( VLOOKUP(C50, FILTER( IMPORTRANGE(""https://docs.google.com/spreadsheets/d/1ZBCmVvzoFu7X0td7O5T5xSJplK8m8h9wvdESBc0a1EE/edit#gid=1841437934"", ""Лист1!$C:$I""), IMPORTRANGE(""https://docs.google.com/spreadsheets/d/1ZBCmVvzoFu7X0"&"td7O5T5xSJplK8m8h9wvdESBc0a1EE/edit#gid=1841437934"", ""Лист1!$C:$C"") = C50 ), 7, FALSE ), """" ) "),"") | P50: =IFERROR(__xludf.DUMMYFUNCTION("IF(OR(ISBLANK(Q50), ISBLANK(O50), VALUE(SUBSTITUTE(INDEX(SPLIT(IF(ISBLANK(R50), Q50, R50), "" km""), 0, 1), "" "", """")) - O50 = 0), """", IF(ISBLANK(R50), VALUE(SUBSTITUTE(INDEX(SPLIT(Q50, "" km""), 0, 1), "" "", """")) - O50, VALUE(SUBSTITUTE(INDEX(SPL"&"IT(R50, "" km""), 0, 1), "" "", """")) - O50))"),"#VALUE!") -> #VALUE! | Q50: =IF(AND(ISBLANK(N50), ISBLANK(E50), ISBLANK(R50)), "", IF(ISBLANK(R50), TEXT(N50, "#,##0") & " Km, " & TEXT(E50, "dd.mm.yyyy"), R50)) -> смена на синий иксмакс | R50: смена на синий иксмакс | S50: 3000 | T50: 4 | U50: 89226553805 0637729363(8) | V50: 4 человека 2 детей | W50: =IF(F50 = "", "", IF(NOW() > (DATEVALUE(LEFT(F50, SEARCH(",", F50) - 2)) + TIMEVALUE(MID(F50, SEARCH(",", F50) + 2, 5))), "Завершена", "В аренде")) -> Завершена | X50: =IFERROR(__xludf.DUMMYFUNCTION("IF(C50 = """", """", IF(REGEXMATCH(C50, ""PCX|NMAX|ADV|CLICK""), ""скутер"", ""мото""))"),"скутер") -> скутер
A51: Завершена | B51: OFF | C51: NMAX 155CC GREY NOSMART PHUKET 5508 | D51: Sergey Smirnov | E51: 44924 | F51: 44933 | G51: =IF((E51="")+(F51=""), "", IF(DATEDIF(E51, F51, "d") > 30, DATEDIF(E51, F51, "m") & " М", DATEDIF(E51, F51, "d") & " Д")) -> 9 Д | H51: 350 | I51: =IF(OR(A51="в аренде", A51="в аренде 1", A51="в аренде 2"), J51-K51, "") | J51: =IF(OR(A51="в аренде", A51="в аренде 1", A51="в аренде 2"), DATEDIF(E51, TODAY(), "D")*H51, "") | K51: 3150 | N51: 25567 | O51: =IFERROR(__xludf.DUMMYFUNCTION("IFERROR( VLOOKUP(C51, FILTER( IMPORTRANGE(""https://docs.google.com/spreadsheets/d/1ZBCmVvzoFu7X0td7O5T5xSJplK8m8h9wvdESBc0a1EE/edit#gid=1841437934"", ""Лист1!$C:$I""), IMPORTRANGE(""https://docs.google.com/spreadsheets/d/1ZBCmVvzoFu7X0"&"td7O5T5xSJplK8m8h9wvdESBc0a1EE/edit#gid=1841437934"", ""Лист1!$C:$C"") = C51 ), 7, FALSE ), """" ) "),"") | P51: =IFERROR(__xludf.DUMMYFUNCTION("IF(OR(ISBLANK(Q51), ISBLANK(O51), VALUE(SUBSTITUTE(INDEX(SPLIT(IF(ISBLANK(R51), Q51, R51), "" km""), 0, 1), "" "", """")) - O51 = 0), """", IF(ISBLANK(R51), VALUE(SUBSTITUTE(INDEX(SPLIT(Q51, "" km""), 0, 1), "" "", """")) - O51, VALUE(SUBSTITUTE(INDEX(SPL"&"IT(R51, "" km""), 0, 1), "" "", """")) - O51))"),25567.0) -> 25567 | Q51: =IF(AND(ISBLANK(N51), ISBLANK(E51), ISBLANK(R51)), "", IF(ISBLANK(R51), TEXT(N51, "#,##0") & " Km, " & TEXT(E51, "dd.mm.yyyy"), R51)) -> 25 567 Km, 29.12.2022 | S51: 3000 | T51: 2 | U51: @sergeysmlab | V51: Сергей Смирнов @sergeysmlab | W51: =IF(F51 = "", "", IF(NOW() > (DATEVALUE(LEFT(F51, SEARCH(",", F51) - 2)) + TIMEVALUE(MID(F51, SEARCH(",", F51) + 2, 5))), "Завершена", "В аренде")) -> Завершена | X51: =IFERROR(__xludf.DUMMYFUNCTION("IF(C51 = """", """", IF(REGEXMATCH(C51, ""PCX|NMAX|ADV|CLICK""), ""скутер"", ""мото""))"),"скутер") -> скутер
A52: Завершена | B52: OFF | C52: NMAX 155CC BLACK PHUKET 8952 | D52: Egeniy Shumskikh | E52: 44924 | F52: 45014 | G52: =IF((E52="")+(F52=""), "", IF(DATEDIF(E52, F52, "d") > 30, DATEDIF(E52, F52, "m") & " М", DATEDIF(E52, F52, "d") & " Д")) -> 3 М | H52: =9000/30 -> 300 | I52: =IF(OR(A52="в аренде", A52="в аренде 1", A52="в аренде 2"), J52-K52, "") | J52: =IF(OR(A52="в аренде", A52="в аренде 1", A52="в аренде 2"), DATEDIF(E52, TODAY(), "D")*H52, "") | K52: =9000+9000 -> 18000 | N52: 16335 | O52: =IFERROR(__xludf.DUMMYFUNCTION("IFERROR( VLOOKUP(C52, FILTER( IMPORTRANGE(""https://docs.google.com/spreadsheets/d/1ZBCmVvzoFu7X0td7O5T5xSJplK8m8h9wvdESBc0a1EE/edit#gid=1841437934"", ""Лист1!$C:$I""), IMPORTRANGE(""https://docs.google.com/spreadsheets/d/1ZBCmVvzoFu7X0"&"td7O5T5xSJplK8m8h9wvdESBc0a1EE/edit#gid=1841437934"", ""Лист1!$C:$C"") = C52 ), 7, FALSE ), """" ) "),35800.0) -> 35800 | P52: =IFERROR(__xludf.DUMMYFUNCTION("IF(OR(ISBLANK(Q52), ISBLANK(O52), VALUE(SUBSTITUTE(INDEX(SPLIT(IF(ISBLANK(R52), Q52, R52), "" km""), 0, 1), "" "", """")) - O52 = 0), """", IF(ISBLANK(R52), VALUE(SUBSTITUTE(INDEX(SPLIT(Q52, "" km""), 0, 1), "" "", """")) - O52, VALUE(SUBSTITUTE(INDEX(SPL"&"IT(R52, "" km""), 0, 1), "" "", """")) - O52))"),-19465.0) -> -19465 | Q52: =IF(AND(ISBLANK(N52), ISBLANK(E52), ISBLANK(R52)), "", IF(ISBLANK(R52), TEXT(N52, "#,##0") & " Km, " & TEXT(E52, "dd.mm.yyyy"), R52)) -> 16 335 Km, 29.12.2022 | S52: 3000 | T52: 2 | U52: @purple_noise | V52: нормальная пара | W52: =IF(F52 = "", "", IF(NOW() > (DATEVALUE(LEFT(F52, SEARCH(",", F52) - 2)) + TIMEVALUE(MID(F52, SEARCH(",", F52) + 2, 5))), "Завершена", "В аренде")) -> Завершена | X52: =IFERROR(__xludf.DUMMYFUNCTION("IF(C52 = """", """", IF(REGEXMATCH(C52, ""PCX|NMAX|ADV|CLICK""), ""скутер"", ""мото""))"),"скутер") -> скутер
A53: Завершена | B53: OFF | C53: XSR 155СС GREY PHUKET 6946 | D53: Roman Shevin | E53: 44925 | F53: 44932 | G53: =IF((E53="")+(F53=""), "", IF(DATEDIF(E53, F53, "d") > 30, DATEDIF(E53, F53, "m") & " М", DATEDIF(E53, F53, "d") & " Д")) -> 7 Д | H53: 600 | I53: =IF(OR(A53="в аренде", A53="в аренде 1", A53="в аренде 2"), J53-K53, "") | J53: =IF(OR(A53="в аренде", A53="в аренде 1", A53="в аренде 2"), DATEDIF(E53, TODAY(), "D")*H53, "") | K53: 4200 | N53: 5651 | O53: =IFERROR(__xludf.DUMMYFUNCTION("IFERROR( VLOOKUP(C53, FILTER( IMPORTRANGE(""https://docs.google.com/spreadsheets/d/1ZBCmVvzoFu7X0td7O5T5xSJplK8m8h9wvdESBc0a1EE/edit#gid=1841437934"", ""Лист1!$C:$I""), IMPORTRANGE(""https://docs.google.com/spreadsheets/d/1ZBCmVvzoFu7X0"&"td7O5T5xSJplK8m8h9wvdESBc0a1EE/edit#gid=1841437934"", ""Лист1!$C:$C"") = C53 ), 7, FALSE ), """" ) "),"") | P53: =IFERROR(__xludf.DUMMYFUNCTION("IF(OR(ISBLANK(Q53), ISBLANK(O53), VALUE(SUBSTITUTE(INDEX(SPLIT(IF(ISBLANK(R53), Q53, R53), "" km""), 0, 1), "" "", """")) - O53 = 0), """", IF(ISBLANK(R53), VALUE(SUBSTITUTE(INDEX(SPLIT(Q53, "" km""), 0, 1), "" "", """")) - O53, VALUE(SUBSTITUTE(INDEX(SPL"&"IT(R53, "" km""), 0, 1), "" "", """")) - O53))"),5651.0) -> 5651 | Q53: =IF(AND(ISBLANK(N53), ISBLANK(E53), ISBLANK(R53)), "", IF(ISBLANK(R53), TEXT(N53, "#,##0") & " Km, " & TEXT(E53, "dd.mm.yyyy"), R53)) -> 5 651 Km, 30.12.2022 | S53: 10000 | T53: 1 | U53: @Dobbrii_vechor | V53: опытный нормальный чел | W53: =IF(F53 = "", "", IF(NOW() > (DATEVALUE(LEFT(F53, SEARCH(",", F53) - 2)) + TIMEVALUE(MID(F53, SEARCH(",", F53) + 2, 5))), "Завершена", "В аренде")) -> Завершена | X53: =IFERROR(__xludf.DUMMYFUNCTION("IF(C53 = """", """", IF(REGEXMATCH(C53, ""PCX|NMAX|ADV|CLICK""), ""скутер"", ""мото""))"),"мото") -> мото
A54: Завершена | B54: OFF | C54: ADV 150CC PHUKET 7497 | D54: Олег Николаенко | E54: 44925 | F54: 44954 | G54: =IF((E54="")+(F54=""), "", IF(DATEDIF(E54, F54, "d") > 30, DATEDIF(E54, F54, "m") & " М", DATEDIF(E54, F54, "d") & " Д")) -> 29 Д | H54: 450 | I54: =IF(OR(A54="в аренде", A54="в аренде 1", A54="в аренде 2"), J54-K54, "") | J54: =IF(OR(A54="в аренде", A54="в аренде 1", A54="в аренде 2"), DATEDIF(E54, TODAY(), "D")*H54, "") | K54: =6750+3600+2700 -> 13050 | N54: 19250 | O54: =IFERROR(__xludf.DUMMYFUNCTION("IFERROR( VLOOKUP(C54, FILTER( IMPORTRANGE(""https://docs.google.com/spreadsheets/d/1ZBCmVvzoFu7X0td7O5T5xSJplK8m8h9wvdESBc0a1EE/edit#gid=1841437934"", ""Лист1!$C:$I""), IMPORTRANGE(""https://docs.google.com/spreadsheets/d/1ZBCmVvzoFu7X0"&"td7O5T5xSJplK8m8h9wvdESBc0a1EE/edit#gid=1841437934"", ""Лист1!$C:$C"") = C54 ), 7, FALSE ), """" ) "),"") | P54: =IFERROR(__xludf.DUMMYFUNCTION("IF(OR(ISBLANK(Q54), ISBLANK(O54), VALUE(SUBSTITUTE(INDEX(SPLIT(IF(ISBLANK(R54), Q54, R54), "" km""), 0, 1), "" "", """")) - O54 = 0), """", IF(ISBLANK(R54), VALUE(SUBSTITUTE(INDEX(SPLIT(Q54, "" km""), 0, 1), "" "", """")) - O54, VALUE(SUBSTITUTE(INDEX(SPL"&"IT(R54, "" km""), 0, 1), "" "", """")) - O54))"),19250.0) -> 19250 | Q54: =IF(AND(ISBLANK(N54), ISBLANK(E54), ISBLANK(R54)), "", IF(ISBLANK(R54), TEXT(N54, "#,##0") & " Km, " & TEXT(E54, "dd.mm.yyyy"), R54)) -> 19 250 Km, 30.12.2022 | S54: 3000 | T54: 2 | U54: @failedtruth +79035654455 | V54: вроде норм чел для друга взял не на долго | W54: =IF(F54 = "", "", IF(NOW() > (DATEVALUE(LEFT(F54, SEARCH(",", F54) - 2)) + TIMEVALUE(MID(F54, SEARCH(",", F54) + 2, 5))), "Завершена", "В аренде")) -> Завершена | X54: =IFERROR(__xludf.DUMMYFUNCTION("IF(C54 = """", """", IF(REGEXMATCH(C54, ""PCX|NMAX|ADV|CLICK""), ""скутер"", ""мото""))"),"скутер") -> скутер
A55: Завершена | B55: OFF | C55: XMAX 300CC RED PHUKET 6947 | D55: Fedorov Konstantin | E55: 44925 | F55: 44956 | G55: =IF((E55="")+(F55=""), "", IF(DATEDIF(E55, F55, "d") > 30, DATEDIF(E55, F55, "m") & " М", DATEDIF(E55, F55, "d") & " Д")) -> 1 М | H55: =16000/30 -> 533.33333 | I55: =IF(OR(A55="в аренде", A55="в аренде 1", A55="в аренде 2"), J55-K55, "") | J55: =IF(OR(A55="в аренде", A55="в аренде 1", A55="в аренде 2"), DATEDIF(E55, TODAY(), "D")*H55, "") | K55: =16000+1800 -> 17800 | N55: 10600 | O55: =IFERROR(__xludf.DUMMYFUNCTION("IFERROR( VLOOKUP(C55, FILTER( IMPORTRANGE(""https://docs.google.com/spreadsheets/d/1ZBCmVvzoFu7X0td7O5T5xSJplK8m8h9wvdESBc0a1EE/edit#gid=1841437934"", ""Лист1!$C:$I""), IMPORTRANGE(""https://docs.google.com/spreadsheets/d/1ZBCmVvzoFu7X0"&"td7O5T5xSJplK8m8h9wvdESBc0a1EE/edit#gid=1841437934"", ""Лист1!$C:$C"") = C55 ), 7, FALSE ), """" ) "),"") | P55: =IFERROR(__xludf.DUMMYFUNCTION("IF(OR(ISBLANK(Q55), ISBLANK(O55), VALUE(SUBSTITUTE(INDEX(SPLIT(IF(ISBLANK(R55), Q55, R55), "" km""), 0, 1), "" "", """")) - O55 = 0), """", IF(ISBLANK(R55), VALUE(SUBSTITUTE(INDEX(SPLIT(Q55, "" km""), 0, 1), "" "", """")) - O55, VALUE(SUBSTITUTE(INDEX(SPL"&"IT(R55, "" km""), 0, 1), "" "", """")) - O55))"),10600.0) -> 10600 | Q55: =IF(AND(ISBLANK(N55), ISBLANK(E55), ISBLANK(R55)), "", IF(ISBLANK(R55), TEXT(N55, "#,##0") & " Km, " & TEXT(E55, "dd.mm.yyyy"), R55)) -> 10 600 Km, 30.12.2022 | S55: 5000 | U55: @rjcnzy86 | V55: норм семья 1 ребенок | W55: =IF(F55 = "", "", IF(NOW() > (DATEVALUE(LEFT(F55, SEARCH(",", F55) - 2)) + TIMEVALUE(MID(F55, SEARCH(",", F55) + 2, 5))), "Завершена", "В аренде")) -> Завершена | X55: =IFERROR(__xludf.DUMMYFUNCTION("IF(C55 = """", """", IF(REGEXMATCH(C55, ""PCX|NMAX|ADV|CLICK""), ""скутер"", ""мото""))"),"мото") -> мото
A56: Завершена | B56: OFF | C56: FORZA 300CC GREY PHUKET 4234 | D56: Алексей | E56: 44926 | F56: 44958 | G56: =IF((E56="")+(F56=""), "", IF(DATEDIF(E56, F56, "d") > 30, DATEDIF(E56, F56, "m") & " М", DATEDIF(E56, F56, "d") & " Д")) -> 1 М | H56: 600 | I56: =IF(OR(A56="в аренде", A56="в аренде 1", A56="в аренде 2"), J56-K56, "") | J56: =IF(OR(A56="в аренде", A56="в аренде 1", A56="в аренде 2"), DATEDIF(E56, TODAY(), "D")*H56, "") | K56: 600 | O56: =IFERROR(__xludf.DUMMYFUNCTION("IFERROR( VLOOKUP(C56, FILTER( IMPORTRANGE(""https://docs.google.com/spreadsheets/d/1ZBCmVvzoFu7X0td7O5T5xSJplK8m8h9wvdESBc0a1EE/edit#gid=1841437934"", ""Лист1!$C:$I""), IMPORTRANGE(""https://docs.google.com/spreadsheets/d/1ZBCmVvzoFu7X0"&"td7O5T5xSJplK8m8h9wvdESBc0a1EE/edit#gid=1841437934"", ""Лист1!$C:$C"") = C56 ), 7, FALSE ), """" ) "),"") | P56: =IFERROR(__xludf.DUMMYFUNCTION("IF(OR(ISBLANK(Q56), ISBLANK(O56), VALUE(SUBSTITUTE(INDEX(SPLIT(IF(ISBLANK(R56), Q56, R56), "" km""), 0, 1), "" "", """")) - O56 = 0), """", IF(ISBLANK(R56), VALUE(SUBSTITUTE(INDEX(SPLIT(Q56, "" km""), 0, 1), "" "", """")) - O56, VALUE(SUBSTITUTE(INDEX(SPL"&"IT(R56, "" km""), 0, 1), "" "", """")) - O56))"),"") | Q56: =IF(AND(ISBLANK(N56), ISBLANK(E56), ISBLANK(R56)), "", IF(ISBLANK(R56), TEXT(N56, "#,##0") & " Km, " & TEXT(E56, "dd.mm.yyyy"), R56)) -> 0 Km, 31.12.2022 | S56: 3000 | T56: 1 | U56: @egorovcrz | V56: опыт есть вроде норм чел с другом @dimanesterov | W56: =IF(F56 = "", "", IF(NOW() > (DATEVALUE(LEFT(F56, SEARCH(",", F56) - 2)) + TIMEVALUE(MID(F56, SEARCH(",", F56) + 2, 5))), "Завершена", "В аренде")) -> Завершена | X56: =IFERROR(__xludf.DUMMYFUNCTION("IF(C56 = """", """", IF(REGEXMATCH(C56, ""PCX|NMAX|ADV|CLICK""), ""скутер"", ""мото""))"),"мото") -> мото
A57: Завершена | B57: OFF | C57: CBR 650R PHUKET 4505 | D57: Stanislav sudakov | E57: 44928 | F57: 44942 | G57: =IF((E57="")+(F57=""), "", IF(DATEDIF(E57, F57, "d") > 30, DATEDIF(E57, F57, "m") & " М", DATEDIF(E57, F57, "d") & " Д")) -> 14 Д | H57: =12000/14 -> 857.14286 | I57: =IF(OR(A57="в аренде", A57="в аренде 1", A57="в аренде 2"), J57-K57, "") | J57: =IF(OR(A57="в аренде", A57="в аренде 1", A57="в аренде 2"), DATEDIF(E57, TODAY(), "D")*H57, "") | K57: 12000 | N57: 27950 | O57: =IFERROR(__xludf.DUMMYFUNCTION("IFERROR( VLOOKUP(C57, FILTER( IMPORTRANGE(""https://docs.google.com/spreadsheets/d/1ZBCmVvzoFu7X0td7O5T5xSJplK8m8h9wvdESBc0a1EE/edit#gid=1841437934"", ""Лист1!$C:$I""), IMPORTRANGE(""https://docs.google.com/spreadsheets/d/1ZBCmVvzoFu7X0"&"td7O5T5xSJplK8m8h9wvdESBc0a1EE/edit#gid=1841437934"", ""Лист1!$C:$C"") = C57 ), 7, FALSE ), """" ) "),63700.0) -> 63700 | P57: =IFERROR(__xludf.DUMMYFUNCTION("IF(OR(ISBLANK(Q57), ISBLANK(O57), VALUE(SUBSTITUTE(INDEX(SPLIT(IF(ISBLANK(R57), Q57, R57), "" km""), 0, 1), "" "", """")) - O57 = 0), """", IF(ISBLANK(R57), VALUE(SUBSTITUTE(INDEX(SPLIT(Q57, "" km""), 0, 1), "" "", """")) - O57, VALUE(SUBSTITUTE(INDEX(SPL"&"IT(R57, "" km""), 0, 1), "" "", """")) - O57))"),-35750.0) -> -35750 | Q57: =IF(AND(ISBLANK(N57), ISBLANK(E57), ISBLANK(R57)), "", IF(ISBLANK(R57), TEXT(N57, "#,##0") & " Km, " & TEXT(E57, "dd.mm.yyyy"), R57)) -> 27 950 Km, 02.01.2023 | S57: 20000 | T57: 1 | U57: @dndmeplz | V57: адекват | W57: =IF(F57 = "", "", IF(NOW() > (DATEVALUE(LEFT(F57, SEARCH(",", F57) - 2)) + TIMEVALUE(MID(F57, SEARCH(",", F57) + 2, 5))), "Завершена", "В аренде")) -> Завершена | X57: =IFERROR(__xludf.DUMMYFUNCTION("IF(C57 = """", """", IF(REGEXMATCH(C57, ""PCX|NMAX|ADV|CLICK""), ""скутер"", ""мото""))"),"мото") -> мото
A58: Завершена | B58: OFF | C58: FORZA 300CC WHITE PHUKET 8950 | D58: Nikolay Mareev | E58: 44931 | F58: 44957 | G58: =IF((E58="")+(F58=""), "", IF(DATEDIF(E58, F58, "d") > 30, DATEDIF(E58, F58, "m") & " М", DATEDIF(E58, F58, "d") & " Д")) -> 26 Д | H58: 577 | I58: =IF(OR(A58="в аренде", A58="в аренде 1", A58="в аренде 2"), J58-K58, "") | J58: =IF(OR(A58="в аренде", A58="в аренде 1", A58="в аренде 2"), DATEDIF(E58, TODAY(), "D")*H58, "") | K58: 15000 | N58: 15600 | O58: =IFERROR(__xludf.DUMMYFUNCTION("IFERROR( VLOOKUP(C58, FILTER( IMPORTRANGE(""https://docs.google.com/spreadsheets/d/1ZBCmVvzoFu7X0td7O5T5xSJplK8m8h9wvdESBc0a1EE/edit#gid=1841437934"", ""Лист1!$C:$I""), IMPORTRANGE(""https://docs.google.com/spreadsheets/d/1ZBCmVvzoFu7X0"&"td7O5T5xSJplK8m8h9wvdESBc0a1EE/edit#gid=1841437934"", ""Лист1!$C:$C"") = C58 ), 7, FALSE ), """" ) "),30225.0) -> 30225 | P58: =IFERROR(__xludf.DUMMYFUNCTION("IF(OR(ISBLANK(Q58), ISBLANK(O58), VALUE(SUBSTITUTE(INDEX(SPLIT(IF(ISBLANK(R58), Q58, R58), "" km""), 0, 1), "" "", """")) - O58 = 0), """", IF(ISBLANK(R58), VALUE(SUBSTITUTE(INDEX(SPLIT(Q58, "" km""), 0, 1), "" "", """")) - O58, VALUE(SUBSTITUTE(INDEX(SPL"&"IT(R58, "" km""), 0, 1), "" "", """")) - O58))"),-14625.0) -> -14625 | Q58: =IF(AND(ISBLANK(N58), ISBLANK(E58), ISBLANK(R58)), "", IF(ISBLANK(R58), TEXT(N58, "#,##0") & " Km, " & TEXT(E58, "dd.mm.yyyy"), R58)) -> 15 600 Km, 05.01.2023 | S58: 200 | T58: 2 | U58: +79912430104 | V58: не опытный гуляка | W58: =IF(F58 = "", "", IF(NOW() > (DATEVALUE(LEFT(F58, SEARCH(",", F58) - 2)) + TIMEVALUE(MID(F58, SEARCH(",", F58) + 2, 5))), "Завершена", "В аренде")) -> Завершена | X58: =IFERROR(__xludf.DUMMYFUNCTION("IF(C58 = """", """", IF(REGEXMATCH(C58, ""PCX|NMAX|ADV|CLICK""), ""скутер"", ""мото""))"),"мото") -> мото
A59: Завершена | B59: OFF | C59: NMAX 155CC GREY NOSMART PHUKET 5508 | D59: DMITRII Kuzmenko | E59: 44933 | F59: 44998 | G59: =IF((E59="")+(F59=""), "", IF(DATEDIF(E59, F59, "d") > 30, DATEDIF(E59, F59, "m") & " М", DATEDIF(E59, F59, "d") & " Д")) -> 2 М | H59: =300 -> 300 | I59: =IF(OR(A59="в аренде", A59="в аренде 1", A59="в аренде 2"), J59-K59, "") | J59: =IF(OR(A59="в аренде", A59="в аренде 1", A59="в аренде 2"), DATEDIF(E59, TODAY(), "D")*H59, "") | K59: =8000+7000+4000 -> 19000 | N59: 26300 | O59: =IFERROR(__xludf.DUMMYFUNCTION("IFERROR( VLOOKUP(C59, FILTER( IMPORTRANGE(""https://docs.google.com/spreadsheets/d/1ZBCmVvzoFu7X0td7O5T5xSJplK8m8h9wvdESBc0a1EE/edit#gid=1841437934"", ""Лист1!$C:$I""), IMPORTRANGE(""https://docs.google.com/spreadsheets/d/1ZBCmVvzoFu7X0"&"td7O5T5xSJplK8m8h9wvdESBc0a1EE/edit#gid=1841437934"", ""Лист1!$C:$C"") = C59 ), 7, FALSE ), """" ) "),"") | P59: =IFERROR(__xludf.DUMMYFUNCTION("IF(OR(ISBLANK(Q59), ISBLANK(O59), VALUE(SUBSTITUTE(INDEX(SPLIT(IF(ISBLANK(R59), Q59, R59), "" km""), 0, 1), "" "", """")) - O59 = 0), """", IF(ISBLANK(R59), VALUE(SUBSTITUTE(INDEX(SPLIT(Q59, "" km""), 0, 1), "" "", """")) - O59, VALUE(SUBSTITUTE(INDEX(SPL"&"IT(R59, "" km""), 0, 1), "" "", """")) - O59))"),"#VALUE!") -> #VALUE! | Q59: =IF(AND(ISBLANK(N59), ISBLANK(E59), ISBLANK(R59)), "", IF(ISBLANK(R59), TEXT(N59, "#,##0") & " Km, " & TEXT(E59, "dd.mm.yyyy"), R59)) -> залог остался до приезда | R59: залог остался до приезда | S59: 2732 | T59: 2 | U59: +79944178986 | V59: не понятный чел взял в слепую возможно не опытный | W59: =IF(F59 = "", "", IF(NOW() > (DATEVALUE(LEFT(F59, SEARCH(",", F59) - 2)) + TIMEVALUE(MID(F59, SEARCH(",", F59) + 2, 5))), "Завершена", "В аренде")) -> Завершена | X59: =IFERROR(__xludf.DUMMYFUNCTION("IF(C59 = """", """", IF(REGEXMATCH(C59, ""PCX|NMAX|ADV|CLICK""), ""скутер"", ""мото""))"),"скутер") -> скутер
A60: Завершена | B60: OFF | C60: XSR 155СС GREY PHUKET 6946 | D60: Илья Фролов | E60: 44934 | F60: 44965 | G60: =IF((E60="")+(F60=""), "", IF(DATEDIF(E60, F60, "d") > 30, DATEDIF(E60, F60, "m") & " М", DATEDIF(E60, F60, "d") & " Д")) -> 1 М | H60: 600 | I60: =IF(OR(A60="в аренде", A60="в аренде 1", A60="в аренде 2"), J60-K60, "") | J60: =IF(OR(A60="в аренде", A60="в аренде 1", A60="в аренде 2"), DATEDIF(E60, TODAY(), "D")*H60, "") | K60: 3000 | N60: 5883 | O60: =IFERROR(__xludf.DUMMYFUNCTION("IFERROR( VLOOKUP(C60, FILTER( IMPORTRANGE(""https://docs.google.com/spreadsheets/d/1ZBCmVvzoFu7X0td7O5T5xSJplK8m8h9wvdESBc0a1EE/edit#gid=1841437934"", ""Лист1!$C:$I""), IMPORTRANGE(""https://docs.google.com/spreadsheets/d/1ZBCmVvzoFu7X0"&"td7O5T5xSJplK8m8h9wvdESBc0a1EE/edit#gid=1841437934"", ""Лист1!$C:$C"") = C60 ), 7, FALSE ), """" ) "),"") | P60: =IFERROR(__xludf.DUMMYFUNCTION("IF(OR(ISBLANK(Q60), ISBLANK(O60), VALUE(SUBSTITUTE(INDEX(SPLIT(IF(ISBLANK(R60), Q60, R60), "" km""), 0, 1), "" "", """")) - O60 = 0), """", IF(ISBLANK(R60), VALUE(SUBSTITUTE(INDEX(SPLIT(Q60, "" km""), 0, 1), "" "", """")) - O60, VALUE(SUBSTITUTE(INDEX(SPL"&"IT(R60, "" km""), 0, 1), "" "", """")) - O60))"),5883.0) -> 5883 | Q60: =IF(AND(ISBLANK(N60), ISBLANK(E60), ISBLANK(R60)), "", IF(ISBLANK(R60), TEXT(N60, "#,##0") & " Km, " & TEXT(E60, "dd.mm.yyyy"), R60)) -> 5 883 Km, 08.01.2023 | S60: 8000 | T60: 1 | U60: @foryourcash | V60: вроде норм чел для друга взял не на долго | W60: =IF(F60 = "", "", IF(NOW() > (DATEVALUE(LEFT(F60, SEARCH(",", F60) - 2)) + TIMEVALUE(MID(F60, SEARCH(",", F60) + 2, 5))), "Завершена", "В аренде")) -> Завершена | X60: =IFERROR(__xludf.DUMMYFUNCTION("IF(C60 = """", """", IF(REGEXMATCH(C60, ""PCX|NMAX|ADV|CLICK""), ""скутер"", ""мото""))"),"мото") -> мото
A61: Завершена | B61: OFF | C61: XSR 155СС GREY PHUKET 6946 | D61: Дмитрий | E61: 44939 | F61: 44942 | G61: =IF((E61="")+(F61=""), "", IF(DATEDIF(E61, F61, "d") > 30, DATEDIF(E61, F61, "m") & " М", DATEDIF(E61, F61, "d") & " Д")) -> 3 Д | H61: 600 | I61: =IF(OR(A61="в аренде", A61="в аренде 1", A61="в аренде 2"), J61-K61, "") | J61: =IF(OR(A61="в аренде", A61="в аренде 1", A61="в аренде 2"), DATEDIF(E61, TODAY(), "D")*H61, "") | K61: 1800 | N61: 6000 | O61: =IFERROR(__xludf.DUMMYFUNCTION("IFERROR( VLOOKUP(C61, FILTER( IMPORTRANGE(""https://docs.google.com/spreadsheets/d/1ZBCmVvzoFu7X0td7O5T5xSJplK8m8h9wvdESBc0a1EE/edit#gid=1841437934"", ""Лист1!$C:$I""), IMPORTRANGE(""https://docs.google.com/spreadsheets/d/1ZBCmVvzoFu7X0"&"td7O5T5xSJplK8m8h9wvdESBc0a1EE/edit#gid=1841437934"", ""Лист1!$C:$C"") = C61 ), 7, FALSE ), """" ) "),"") | P61: =IFERROR(__xludf.DUMMYFUNCTION("IF(OR(ISBLANK(Q61), ISBLANK(O61), VALUE(SUBSTITUTE(INDEX(SPLIT(IF(ISBLANK(R61), Q61, R61), "" km""), 0, 1), "" "", """")) - O61 = 0), """", IF(ISBLANK(R61), VALUE(SUBSTITUTE(INDEX(SPLIT(Q61, "" km""), 0, 1), "" "", """")) - O61, VALUE(SUBSTITUTE(INDEX(SPL"&"IT(R61, "" km""), 0, 1), "" "", """")) - O61))"),6000.0) -> 6000 | Q61: =IF(AND(ISBLANK(N61), ISBLANK(E61), ISBLANK(R61)), "", IF(ISBLANK(R61), TEXT(N61, "#,##0") & " Km, " & TEXT(E61, "dd.mm.yyyy"), R61)) -> 6 000 Km, 13.01.2023 | S61: 8000 | T61: 1 | U61: @Valdman | V61: Дима из компании артема | W61: =IF(F61 = "", "", IF(NOW() > (DATEVALUE(LEFT(F61, SEARCH(",", F61) - 2)) + TIMEVALUE(MID(F61, SEARCH(",", F61) + 2, 5))), "Завершена", "В аренде")) -> Завершена | X61: =IFERROR(__xludf.DUMMYFUNCTION("IF(C61 = """", """", IF(REGEXMATCH(C61, ""PCX|NMAX|ADV|CLICK""), ""скутер"", ""мото""))"),"мото") -> мото
A62: Завершена | B62: OFF | C62: NMAX 155CC GREEN BLACK | D62: СОсед константин | E62: 44942 | F62: 44960 | G62: =IF((E62="")+(F62=""), "", IF(DATEDIF(E62, F62, "d") > 30, DATEDIF(E62, F62, "m") & " М", DATEDIF(E62, F62, "d") & " Д")) -> 18 Д | H62: 400 | I62: =IF(OR(A62="в аренде", A62="в аренде 1", A62="в аренде 2"), J62-K62, "") | J62: =IF(OR(A62="в аренде", A62="в аренде 1", A62="в аренде 2"), DATEDIF(E62, TODAY(), "D")*H62, "") | K62: =2000+1200+800+800+800+800+400+400 -> 7200 | N62: 12617 | O62: =IFERROR(__xludf.DUMMYFUNCTION("IFERROR( VLOOKUP(C62, FILTER( IMPORTRANGE(""https://docs.google.com/spreadsheets/d/1ZBCmVvzoFu7X0td7O5T5xSJplK8m8h9wvdESBc0a1EE/edit#gid=1841437934"", ""Лист1!$C:$I""), IMPORTRANGE(""https://docs.google.com/spreadsheets/d/1ZBCmVvzoFu7X0"&"td7O5T5xSJplK8m8h9wvdESBc0a1EE/edit#gid=1841437934"", ""Лист1!$C:$C"") = C62 ), 7, FALSE ), """" ) "),"") | P62: =IFERROR(__xludf.DUMMYFUNCTION("IF(OR(ISBLANK(Q62), ISBLANK(O62), VALUE(SUBSTITUTE(INDEX(SPLIT(IF(ISBLANK(R62), Q62, R62), "" km""), 0, 1), "" "", """")) - O62 = 0), """", IF(ISBLANK(R62), VALUE(SUBSTITUTE(INDEX(SPLIT(Q62, "" km""), 0, 1), "" "", """")) - O62, VALUE(SUBSTITUTE(INDEX(SPL"&"IT(R62, "" km""), 0, 1), "" "", """")) - O62))"),12617.0) -> 12617 | Q62: =IF(AND(ISBLANK(N62), ISBLANK(E62), ISBLANK(R62)), "", IF(ISBLANK(R62), TEXT(N62, "#,##0") & " Km, " & TEXT(E62, "dd.mm.yyyy"), R62)) -> 12 617 Km, 16.01.2023 | S62: 3000 | T62: 3 | V62: кантемир компани | W62: =IF(F62 = "", "", IF(NOW() > (DATEVALUE(LEFT(F62, SEARCH(",", F62) - 2)) + TIMEVALUE(MID(F62, SEARCH(",", F62) + 2, 5))), "Завершена", "В аренде")) -> Завершена | X62: =IFERROR(__xludf.DUMMYFUNCTION("IF(C62 = """", """", IF(REGEXMATCH(C62, ""PCX|NMAX|ADV|CLICK""), ""скутер"", ""мото""))"),"скутер") -> скутер
A63: Завершена | B63: OFF | C63: XSR 155СС GREY PHUKET 6946 | D63: Александр Кашко alexandrk15 | E63: 44943 | F63: 44974 | G63: =IF((E63="")+(F63=""), "", IF(DATEDIF(E63, F63, "d") > 30, DATEDIF(E63, F63, "m") & " М", DATEDIF(E63, F63, "d") & " Д")) -> 1 М | H63: 400 | I63: =IF(OR(A63="в аренде", A63="в аренде 1", A63="в аренде 2"), J63-K63, "") | J63: =IF(OR(A63="в аренде", A63="в аренде 1", A63="в аренде 2"), DATEDIF(E63, TODAY(), "D")*H63, "") | K63: 12000 | N63: 6200 | O63: =IFERROR(__xludf.DUMMYFUNCTION("IFERROR( VLOOKUP(C63, FILTER( IMPORTRANGE(""https://docs.google.com/spreadsheets/d/1ZBCmVvzoFu7X0td7O5T5xSJplK8m8h9wvdESBc0a1EE/edit#gid=1841437934"", ""Лист1!$C:$I""), IMPORTRANGE(""https://docs.google.com/spreadsheets/d/1ZBCmVvzoFu7X0"&"td7O5T5xSJplK8m8h9wvdESBc0a1EE/edit#gid=1841437934"", ""Лист1!$C:$C"") = C63 ), 7, FALSE ), """" ) "),"") | P63: =IFERROR(__xludf.DUMMYFUNCTION("IF(OR(ISBLANK(Q63), ISBLANK(O63), VALUE(SUBSTITUTE(INDEX(SPLIT(IF(ISBLANK(R63), Q63, R63), "" km""), 0, 1), "" "", """")) - O63 = 0), """", IF(ISBLANK(R63), VALUE(SUBSTITUTE(INDEX(SPLIT(Q63, "" km""), 0, 1), "" "", """")) - O63, VALUE(SUBSTITUTE(INDEX(SPL"&"IT(R63, "" km""), 0, 1), "" "", """")) - O63))"),6200.0) -> 6200 | Q63: =IF(AND(ISBLANK(N63), ISBLANK(E63), ISBLANK(R63)), "", IF(ISBLANK(R63), TEXT(N63, "#,##0") & " Km, " & TEXT(E63, "dd.mm.yyyy"), R63)) -> 6 200 Km, 17.01.2023 | S63: 300 | T63: 2 | V63: чел не очень опытный но норм | W63: =IF(F63 = "", "", IF(NOW() > (DATEVALUE(LEFT(F63, SEARCH(",", F63) - 2)) + TIMEVALUE(MID(F63, SEARCH(",", F63) + 2, 5))), "Завершена", "В аренде")) -> Завершена | X63: =IFERROR(__xludf.DUMMYFUNCTION("IF(C63 = """", """", IF(REGEXMATCH(C63, ""PCX|NMAX|ADV|CLICK""), ""скутер"", ""мото""))"),"мото") -> мото
A64: Завершена | B64: OFF | C64: NMAX 155CC BLUE YELLOW 2020 | D64: Sergey Smirnov | E64: 44945 | F64: 44947 | G64: =IF((E64="")+(F64=""), "", IF(DATEDIF(E64, F64, "d") > 30, DATEDIF(E64, F64, "m") & " М", DATEDIF(E64, F64, "d") & " Д")) -> 2 Д | H64: 400 | I64: =IF(OR(A64="в аренде", A64="в аренде 1", A64="в аренде 2"), J64-K64, "") | J64: =IF(OR(A64="в аренде", A64="в аренде 1", A64="в аренде 2"), DATEDIF(E64, TODAY(), "D")*H64, "") | K64: 800 | N64: 18155 | O64: =IFERROR(__xludf.DUMMYFUNCTION("IFERROR( VLOOKUP(C64, FILTER( IMPORTRANGE(""https://docs.google.com/spreadsheets/d/1ZBCmVvzoFu7X0td7O5T5xSJplK8m8h9wvdESBc0a1EE/edit#gid=1841437934"", ""Лист1!$C:$I""), IMPORTRANGE(""https://docs.google.com/spreadsheets/d/1ZBCmVvzoFu7X0"&"td7O5T5xSJplK8m8h9wvdESBc0a1EE/edit#gid=1841437934"", ""Лист1!$C:$C"") = C64 ), 7, FALSE ), """" ) "),"") | P64: =IFERROR(__xludf.DUMMYFUNCTION("IF(OR(ISBLANK(Q64), ISBLANK(O64), VALUE(SUBSTITUTE(INDEX(SPLIT(IF(ISBLANK(R64), Q64, R64), "" km""), 0, 1), "" "", """")) - O64 = 0), """", IF(ISBLANK(R64), VALUE(SUBSTITUTE(INDEX(SPLIT(Q64, "" km""), 0, 1), "" "", """")) - O64, VALUE(SUBSTITUTE(INDEX(SPL"&"IT(R64, "" km""), 0, 1), "" "", """")) - O64))"),18155.0) -> 18155 | Q64: =IF(AND(ISBLANK(N64), ISBLANK(E64), ISBLANK(R64)), "", IF(ISBLANK(R64), TEXT(N64, "#,##0") & " Km, " & TEXT(E64, "dd.mm.yyyy"), R64)) -> 18 155 Km, 19.01.2023 | S64: 3000 | T64: 2 | U64: @sergeysmlab | V64: Сергей Смирнов @sergeysmlab | W64: =IF(F64 = "", "", IF(NOW() > (DATEVALUE(LEFT(F64, SEARCH(",", F64) - 2)) + TIMEVALUE(MID(F64, SEARCH(",", F64) + 2, 5))), "Завершена", "В аренде")) -> Завершена | X64: =IFERROR(__xludf.DUMMYFUNCTION("IF(C64 = """", """", IF(REGEXMATCH(C64, ""PCX|NMAX|ADV|CLICK""), ""скутер"", ""мото""))"),"скутер") -> скутер
A65: Завершена | B65: OFF | C65: NMAX 155CC BLUE YELLOW 2020 | D65: Nikita Kovalevskii | E65: 44949 | F65: 45040 | G65: =IF((E65="")+(F65=""), "", IF(DATEDIF(E65, F65, "d") > 30, DATEDIF(E65, F65, "m") & " М", DATEDIF(E65, F65, "d") & " Д")) -> 3 М | H65: =8000/30 -> 266.66667 | I65: =IF(OR(A65="в аренде", A65="в аренде 1", A65="в аренде 2"), J65-K65, "") | J65: =IF(OR(A65="в аренде", A65="в аренде 1", A65="в аренде 2"), DATEDIF(E65, TODAY(), "D")*H65, "") | K65: =8500+8500+8000 -> 25000 | N65: 18327 | O65: =IFERROR(__xludf.DUMMYFUNCTION("IFERROR( VLOOKUP(C65, FILTER( IMPORTRANGE(""https://docs.google.com/spreadsheets/d/1ZBCmVvzoFu7X0td7O5T5xSJplK8m8h9wvdESBc0a1EE/edit#gid=1841437934"", ""Лист1!$C:$I""), IMPORTRANGE(""https://docs.google.com/spreadsheets/d/1ZBCmVvzoFu7X0"&"td7O5T5xSJplK8m8h9wvdESBc0a1EE/edit#gid=1841437934"", ""Лист1!$C:$C"") = C65 ), 7, FALSE ), """" ) "),"") | P65: =IFERROR(__xludf.DUMMYFUNCTION("IF(OR(ISBLANK(Q65), ISBLANK(O65), VALUE(SUBSTITUTE(INDEX(SPLIT(IF(ISBLANK(R65), Q65, R65), "" km""), 0, 1), "" "", """")) - O65 = 0), """", IF(ISBLANK(R65), VALUE(SUBSTITUTE(INDEX(SPLIT(Q65, "" km""), 0, 1), "" "", """")) - O65, VALUE(SUBSTITUTE(INDEX(SPL"&"IT(R65, "" km""), 0, 1), "" "", """")) - O65))"),18327.0) -> 18327 | Q65: =IF(AND(ISBLANK(N65), ISBLANK(E65), ISBLANK(R65)), "", IF(ISBLANK(R65), TEXT(N65, "#,##0") & " Km, " & TEXT(E65, "dd.mm.yyyy"), R65)) -> 18 327 Km, 23.01.2023 | S65: 3000 | T65: 0 | V65: @Nord_horse | W65: =IF(F65 = "", "", IF(NOW() > (DATEVALUE(LEFT(F65, SEARCH(",", F65) - 2)) + TIMEVALUE(MID(F65, SEARCH(",", F65) + 2, 5))), "Завершена", "В аренде")) -> Завершена | X65: =IFERROR(__xludf.DUMMYFUNCTION("IF(C65 = """", """", IF(REGEXMATCH(C65, ""PCX|NMAX|ADV|CLICK""), ""скутер"", ""мото""))"),"скутер") -> скутер
A66: Завершена | B66: OFF | C66: XMAX 300CC GREEN PHUKET 4248 | D66: Denis Odinokov whats | E66: 44950 | F66: 44958 | G66: =IF((E66="")+(F66=""), "", IF(DATEDIF(E66, F66, "d") > 30, DATEDIF(E66, F66, "m") & " М", DATEDIF(E66, F66, "d") & " Д")) -> 8 Д | H66: 800 | I66: =IF(OR(A66="в аренде", A66="в аренде 1", A66="в аренде 2"), J66-K66, "") | J66: =IF(OR(A66="в аренде", A66="в аренде 1", A66="в аренде 2"), DATEDIF(E66, TODAY(), "D")*H66, "") | K66: 4000 | N66: 12459 | O66: =IFERROR(__xludf.DUMMYFUNCTION("IFERROR( VLOOKUP(C66, FILTER( IMPORTRANGE(""https://docs.google.com/spreadsheets/d/1ZBCmVvzoFu7X0td7O5T5xSJplK8m8h9wvdESBc0a1EE/edit#gid=1841437934"", ""Лист1!$C:$I""), IMPORTRANGE(""https://docs.google.com/spreadsheets/d/1ZBCmVvzoFu7X0"&"td7O5T5xSJplK8m8h9wvdESBc0a1EE/edit#gid=1841437934"", ""Лист1!$C:$C"") = C66 ), 7, FALSE ), """" ) "),32600.0) -> 32600 | P66: =IFERROR(__xludf.DUMMYFUNCTION("IF(OR(ISBLANK(Q66), ISBLANK(O66), VALUE(SUBSTITUTE(INDEX(SPLIT(IF(ISBLANK(R66), Q66, R66), "" km""), 0, 1), "" "", """")) - O66 = 0), """", IF(ISBLANK(R66), VALUE(SUBSTITUTE(INDEX(SPLIT(Q66, "" km""), 0, 1), "" "", """")) - O66, VALUE(SUBSTITUTE(INDEX(SPL"&"IT(R66, "" km""), 0, 1), "" "", """")) - O66))"),-20141.0) -> -20141 | Q66: =IF(AND(ISBLANK(N66), ISBLANK(E66), ISBLANK(R66)), "", IF(ISBLANK(R66), TEXT(N66, "#,##0") & " Km, " & TEXT(E66, "dd.mm.yyyy"), R66)) -> 12 459 Km, 24.01.2023 | S66: 200 | T66: 2 | U66: +79172002515 | V66: норм чел опыт не большой | W66: =IF(F66 = "", "", IF(NOW() > (DATEVALUE(LEFT(F66, SEARCH(",", F66) - 2)) + TIMEVALUE(MID(F66, SEARCH(",", F66) + 2, 5))), "Завершена", "В аренде")) -> Завершена | X66: =IFERROR(__xludf.DUMMYFUNCTION("IF(C66 = """", """", IF(REGEXMATCH(C66, ""PCX|NMAX|ADV|CLICK""), ""скутер"", ""мото""))"),"мото") -> мото
A67: Завершена | B67: OFF | C67: FORZA 300CC RED PHUKET 4244 | D67: Андрей васильков | E67: 44950 | F67: 44964 | G67: =IF((E67="")+(F67=""), "", IF(DATEDIF(E67, F67, "d") > 30, DATEDIF(E67, F67, "m") & " М", DATEDIF(E67, F67, "d") & " Д")) -> 14 Д | H67: 700 | I67: =IF(OR(A67="в аренде", A67="в аренде 1", A67="в аренде 2"), J67-K67, "") | J67: =IF(OR(A67="в аренде", A67="в аренде 1", A67="в аренде 2"), DATEDIF(E67, TODAY(), "D")*H67, "") | K67: =14*700 -> 9800 | N67: 22000 | O67: =IFERROR(__xludf.DUMMYFUNCTION("IFERROR( VLOOKUP(C67, FILTER( IMPORTRANGE(""https://docs.google.com/spreadsheets/d/1ZBCmVvzoFu7X0td7O5T5xSJplK8m8h9wvdESBc0a1EE/edit#gid=1841437934"", ""Лист1!$C:$I""), IMPORTRANGE(""https://docs.google.com/spreadsheets/d/1ZBCmVvzoFu7X0"&"td7O5T5xSJplK8m8h9wvdESBc0a1EE/edit#gid=1841437934"", ""Лист1!$C:$C"") = C67 ), 7, FALSE ), """" ) "),"") | P67: =IFERROR(__xludf.DUMMYFUNCTION("IF(OR(ISBLANK(Q67), ISBLANK(O67), VALUE(SUBSTITUTE(INDEX(SPLIT(IF(ISBLANK(R67), Q67, R67), "" km""), 0, 1), "" "", """")) - O67 = 0), """", IF(ISBLANK(R67), VALUE(SUBSTITUTE(INDEX(SPLIT(Q67, "" km""), 0, 1), "" "", """")) - O67, VALUE(SUBSTITUTE(INDEX(SPL"&"IT(R67, "" km""), 0, 1), "" "", """")) - O67))"),22000.0) -> 22000 | Q67: =IF(AND(ISBLANK(N67), ISBLANK(E67), ISBLANK(R67)), "", IF(ISBLANK(R67), TEXT(N67, "#,##0") & " Km, " & TEXT(E67, "dd.mm.yyyy"), R67)) -> 22 000 Km, 24.01.2023 | S67: 5000 | T67: 2 | U67: @Andy_PCO | V67: друг соседа егора | W67: =IF(F67 = "", "", IF(NOW() > (DATEVALUE(LEFT(F67, SEARCH(",", F67) - 2)) + TIMEVALUE(MID(F67, SEARCH(",", F67) + 2, 5))), "Завершена", "В аренде")) -> Завершена | X67: =IFERROR(__xludf.DUMMYFUNCTION("IF(C67 = """", """", IF(REGEXMATCH(C67, ""PCX|NMAX|ADV|CLICK""), ""скутер"", ""мото""))"),"мото") -> мото
A68: Завершена | B68: OFF | C68: ADV 150CC PHUKET 7497 | D68: Alekxey Rykov | E68: 44954 | F68: 44964 | G68: =IF((E68="")+(F68=""), "", IF(DATEDIF(E68, F68, "d") > 30, DATEDIF(E68, F68, "m") & " М", DATEDIF(E68, F68, "d") & " Д")) -> 10 Д | H68: 450 | I68: =IF(OR(A68="в аренде", A68="в аренде 1", A68="в аренде 2"), J68-K68, "") | J68: =IF(OR(A68="в аренде", A68="в аренде 1", A68="в аренде 2"), DATEDIF(E68, TODAY(), "D")*H68, "") | K68: 4500 | N68: 19950 | O68: =IFERROR(__xludf.DUMMYFUNCTION("IFERROR( VLOOKUP(C68, FILTER( IMPORTRANGE(""https://docs.google.com/spreadsheets/d/1ZBCmVvzoFu7X0td7O5T5xSJplK8m8h9wvdESBc0a1EE/edit#gid=1841437934"", ""Лист1!$C:$I""), IMPORTRANGE(""https://docs.google.com/spreadsheets/d/1ZBCmVvzoFu7X0"&"td7O5T5xSJplK8m8h9wvdESBc0a1EE/edit#gid=1841437934"", ""Лист1!$C:$C"") = C68 ), 7, FALSE ), """" ) "),"") | P68: =IFERROR(__xludf.DUMMYFUNCTION("IF(OR(ISBLANK(Q68), ISBLANK(O68), VALUE(SUBSTITUTE(INDEX(SPLIT(IF(ISBLANK(R68), Q68, R68), "" km""), 0, 1), "" "", """")) - O68 = 0), """", IF(ISBLANK(R68), VALUE(SUBSTITUTE(INDEX(SPLIT(Q68, "" km""), 0, 1), "" "", """")) - O68, VALUE(SUBSTITUTE(INDEX(SPL"&"IT(R68, "" km""), 0, 1), "" "", """")) - O68))"),19950.0) -> 19950 | Q68: =IF(AND(ISBLANK(N68), ISBLANK(E68), ISBLANK(R68)), "", IF(ISBLANK(R68), TEXT(N68, "#,##0") & " Km, " & TEXT(E68, "dd.mm.yyyy"), R68)) -> 19 950 Km, 28.01.2023 | S68: 100 | T68: 2 | U68: +79267191322 | V68: норм пара | W68: =IF(F68 = "", "", IF(NOW() > (DATEVALUE(LEFT(F68, SEARCH(",", F68) - 2)) + TIMEVALUE(MID(F68, SEARCH(",", F68) + 2, 5))), "Завершена", "В аренде")) -> Завершена | X68: =IFERROR(__xludf.DUMMYFUNCTION("IF(C68 = """", """", IF(REGEXMATCH(C68, ""PCX|NMAX|ADV|CLICK""), ""скутер"", ""мото""))"),"скутер") -> скутер
A69: Завершена | B69: OFF | C69: XMAX 300CC GREEN PHUKET 4248 | D69: Nikita Avtaneev | E69: 44958 | F69: 44985 | G69: =IF((E69="")+(F69=""), "", IF(DATEDIF(E69, F69, "d") > 30, DATEDIF(E69, F69, "m") & " М", DATEDIF(E69, F69, "d") & " Д")) -> 27 Д | H69: =16000/28 -> 571.42857 | I69: =IF(OR(A69="в аренде", A69="в аренде 1", A69="в аренде 2"), J69-K69, "") | J69: =IF(OR(A69="в аренде", A69="в аренде 1", A69="в аренде 2"), DATEDIF(E69, TODAY(), "D")*H69, "") | K69: 16000 | N69: 12600 | O69: =IFERROR(__xludf.DUMMYFUNCTION("IFERROR( VLOOKUP(C69, FILTER( IMPORTRANGE(""https://docs.google.com/spreadsheets/d/1ZBCmVvzoFu7X0td7O5T5xSJplK8m8h9wvdESBc0a1EE/edit#gid=1841437934"", ""Лист1!$C:$I""), IMPORTRANGE(""https://docs.google.com/spreadsheets/d/1ZBCmVvzoFu7X0"&"td7O5T5xSJplK8m8h9wvdESBc0a1EE/edit#gid=1841437934"", ""Лист1!$C:$C"") = C69 ), 7, FALSE ), """" ) "),32600.0) -> 32600 | P69: =IFERROR(__xludf.DUMMYFUNCTION("IF(OR(ISBLANK(Q69), ISBLANK(O69), VALUE(SUBSTITUTE(INDEX(SPLIT(IF(ISBLANK(R69), Q69, R69), "" km""), 0, 1), "" "", """")) - O69 = 0), """", IF(ISBLANK(R69), VALUE(SUBSTITUTE(INDEX(SPLIT(Q69, "" km""), 0, 1), "" "", """")) - O69, VALUE(SUBSTITUTE(INDEX(SPL"&"IT(R69, "" km""), 0, 1), "" "", """")) - O69))"),-20000.0) -> -20000 | Q69: =IF(AND(ISBLANK(N69), ISBLANK(E69), ISBLANK(R69)), "", IF(ISBLANK(R69), TEXT(N69, "#,##0") & " Km, " & TEXT(E69, "dd.mm.yyyy"), R69)) -> 12 600 Km, 01.02.2023 | S69: 5000 | T69: 2 | U69: @avtaneev | V69: норм чел есть опыт снимал у ильи | W69: =IF(F69 = "", "", IF(NOW() > (DATEVALUE(LEFT(F69, SEARCH(",", F69) - 2)) + TIMEVALUE(MID(F69, SEARCH(",", F69) + 2, 5))), "Завершена", "В аренде")) -> Завершена | X69: =IFERROR(__xludf.DUMMYFUNCTION("IF(C69 = """", """", IF(REGEXMATCH(C69, ""PCX|NMAX|ADV|CLICK""), ""скутер"", ""мото""))"),"мото") -> мото
A70: Завершена | B70: OFF | C70: CBR 650R PHUKET 4505 | D70: Ivan Rochev | E70: 44960 | F70: 44963 | G70: =IF((E70="")+(F70=""), "", IF(DATEDIF(E70, F70, "d") > 30, DATEDIF(E70, F70, "m") & " М", DATEDIF(E70, F70, "d") & " Д")) -> 3 Д | H70: 2000 | I70: =IF(OR(A70="в аренде", A70="в аренде 1", A70="в аренде 2"), J70-K70, "") | J70: =IF(OR(A70="в аренде", A70="в аренде 1", A70="в аренде 2"), DATEDIF(E70, TODAY(), "D")*H70, "") | K70: 6000 | N70: 29763 | O70: =IFERROR(__xludf.DUMMYFUNCTION("IFERROR( VLOOKUP(C70, FILTER( IMPORTRANGE(""https://docs.google.com/spreadsheets/d/1ZBCmVvzoFu7X0td7O5T5xSJplK8m8h9wvdESBc0a1EE/edit#gid=1841437934"", ""Лист1!$C:$I""), IMPORTRANGE(""https://docs.google.com/spreadsheets/d/1ZBCmVvzoFu7X0"&"td7O5T5xSJplK8m8h9wvdESBc0a1EE/edit#gid=1841437934"", ""Лист1!$C:$C"") = C70 ), 7, FALSE ), """" ) "),63700.0) -> 63700 | P70: =IFERROR(__xludf.DUMMYFUNCTION("IF(OR(ISBLANK(Q70), ISBLANK(O70), VALUE(SUBSTITUTE(INDEX(SPLIT(IF(ISBLANK(R70), Q70, R70), "" km""), 0, 1), "" "", """")) - O70 = 0), """", IF(ISBLANK(R70), VALUE(SUBSTITUTE(INDEX(SPLIT(Q70, "" km""), 0, 1), "" "", """")) - O70, VALUE(SUBSTITUTE(INDEX(SPL"&"IT(R70, "" km""), 0, 1), "" "", """")) - O70))"),-33937.0) -> -33937 | Q70: =IF(AND(ISBLANK(N70), ISBLANK(E70), ISBLANK(R70)), "", IF(ISBLANK(R70), TEXT(N70, "#,##0") & " Km, " & TEXT(E70, "dd.mm.yyyy"), R70)) -> 29 763 Km, 03.02.2023 | S70: 20000 | T70: 2 | U70: @ivanro4ev | V70: милая молодая пара | W70: =IF(F70 = "", "", IF(NOW() > (DATEVALUE(LEFT(F70, SEARCH(",", F70) - 2)) + TIMEVALUE(MID(F70, SEARCH(",", F70) + 2, 5))), "Завершена", "В аренде")) -> Завершена | X70: =IFERROR(__xludf.DUMMYFUNCTION("IF(C70 = """", """", IF(REGEXMATCH(C70, ""PCX|NMAX|ADV|CLICK""), ""скутер"", ""мото""))"),"мото") -> мото
A71: Завершена | B71: OFF | C71: XMAX 300CC RED PHUKET 6947 | D71: Evgenii Prkofev | E71: 44960 | F71: 44972 | G71: =IF((E71="")+(F71=""), "", IF(DATEDIF(E71, F71, "d") > 30, DATEDIF(E71, F71, "m") & " М", DATEDIF(E71, F71, "d") & " Д")) -> 12 Д | H71: 700 | I71: =IF(OR(A71="в аренде", A71="в аренде 1", A71="в аренде 2"), J71-K71, "") | J71: =IF(OR(A71="в аренде", A71="в аренде 1", A71="в аренде 2"), DATEDIF(E71, TODAY(), "D")*H71, "") | K71: =5600+3000 -> 8600 | N71: 12000 | O71: =IFERROR(__xludf.DUMMYFUNCTION("IFERROR( VLOOKUP(C71, FILTER( IMPORTRANGE(""https://docs.google.com/spreadsheets/d/1ZBCmVvzoFu7X0td7O5T5xSJplK8m8h9wvdESBc0a1EE/edit#gid=1841437934"", ""Лист1!$C:$I""), IMPORTRANGE(""https://docs.google.com/spreadsheets/d/1ZBCmVvzoFu7X0"&"td7O5T5xSJplK8m8h9wvdESBc0a1EE/edit#gid=1841437934"", ""Лист1!$C:$C"") = C71 ), 7, FALSE ), """" ) "),"") | P71: =IFERROR(__xludf.DUMMYFUNCTION("IF(OR(ISBLANK(Q71), ISBLANK(O71), VALUE(SUBSTITUTE(INDEX(SPLIT(IF(ISBLANK(R71), Q71, R71), "" km""), 0, 1), "" "", """")) - O71 = 0), """", IF(ISBLANK(R71), VALUE(SUBSTITUTE(INDEX(SPLIT(Q71, "" km""), 0, 1), "" "", """")) - O71, VALUE(SUBSTITUTE(INDEX(SPL"&"IT(R71, "" km""), 0, 1), "" "", """")) - O71))"),12000.0) -> 12000 | Q71: =IF(AND(ISBLANK(N71), ISBLANK(E71), ISBLANK(R71)), "", IF(ISBLANK(R71), TEXT(N71, "#,##0") & " Km, " & TEXT(E71, "dd.mm.yyyy"), R71)) -> 12 000 Km, 03.02.2023 | S71: 5000 | T71: 3 шлема | U71: @Evgeniy_Parfumerov | V71: 2 чела ок не очень пытный с ребенком | W71: =IF(F71 = "", "", IF(NOW() > (DATEVALUE(LEFT(F71, SEARCH(",", F71) - 2)) + TIMEVALUE(MID(F71, SEARCH(",", F71) + 2, 5))), "Завершена", "В аренде")) -> Завершена | X71: =IFERROR(__xludf.DUMMYFUNCTION("IF(C71 = """", """", IF(REGEXMATCH(C71, ""PCX|NMAX|ADV|CLICK""), ""скутер"", ""мото""))"),"мото") -> мото
A72: Завершена | B72: OFF | C72: XMAX 300CC BLUE PHUKET 5773 | D72: Марат Салихов | E72: 44962 | F72: 44969 | G72: =IF((E72="")+(F72=""), "", IF(DATEDIF(E72, F72, "d") > 30, DATEDIF(E72, F72, "m") & " М", DATEDIF(E72, F72, "d") & " Д")) -> 7 Д | H72: 800 | I72: =IF(OR(A72="в аренде", A72="в аренде 1", A72="в аренде 2"), J72-K72, "") | J72: =IF(OR(A72="в аренде", A72="в аренде 1", A72="в аренде 2"), DATEDIF(E72, TODAY(), "D")*H72, "") | K72: 6000 | N72: 30400 | O72: =IFERROR(__xludf.DUMMYFUNCTION("IFERROR( VLOOKUP(C72, FILTER( IMPORTRANGE(""https://docs.google.com/spreadsheets/d/1ZBCmVvzoFu7X0td7O5T5xSJplK8m8h9wvdESBc0a1EE/edit#gid=1841437934"", ""Лист1!$C:$I""), IMPORTRANGE(""https://docs.google.com/spreadsheets/d/1ZBCmVvzoFu7X0"&"td7O5T5xSJplK8m8h9wvdESBc0a1EE/edit#gid=1841437934"", ""Лист1!$C:$C"") = C72 ), 7, FALSE ), """" ) "),23500.0) -> 23500 | P72: =IFERROR(__xludf.DUMMYFUNCTION("IF(OR(ISBLANK(Q72), ISBLANK(O72), VALUE(SUBSTITUTE(INDEX(SPLIT(IF(ISBLANK(R72), Q72, R72), "" km""), 0, 1), "" "", """")) - O72 = 0), """", IF(ISBLANK(R72), VALUE(SUBSTITUTE(INDEX(SPLIT(Q72, "" km""), 0, 1), "" "", """")) - O72, VALUE(SUBSTITUTE(INDEX(SPL"&"IT(R72, "" km""), 0, 1), "" "", """")) - O72))"),6900.0) -> 6900 | Q72: =IF(AND(ISBLANK(N72), ISBLANK(E72), ISBLANK(R72)), "", IF(ISBLANK(R72), TEXT(N72, "#,##0") & " Km, " & TEXT(E72, "dd.mm.yyyy"), R72)) -> 30 400 Km, 05.02.2023 | S72: 5000 | T72: 2 | U72: @vezhevich | V72: перепутал цену взял пока на неделю | W72: =IF(F72 = "", "", IF(NOW() > (DATEVALUE(LEFT(F72, SEARCH(",", F72) - 2)) + TIMEVALUE(MID(F72, SEARCH(",", F72) + 2, 5))), "Завершена", "В аренде")) -> Завершена | X72: =IFERROR(__xludf.DUMMYFUNCTION("IF(C72 = """", """", IF(REGEXMATCH(C72, ""PCX|NMAX|ADV|CLICK""), ""скутер"", ""мото""))"),"мото") -> мото
A73: Завершена | B73: OFF | C73: FORZA 300CC WHITE PHUKET 8950 | D73: Valeriy Russanevich | E73: 44962 | F73: 44978 | G73: =IF((E73="")+(F73=""), "", IF(DATEDIF(E73, F73, "d") > 30, DATEDIF(E73, F73, "m") & " М", DATEDIF(E73, F73, "d") & " Д")) -> 16 Д | H73: 600 | I73: =IF(OR(A73="в аренде", A73="в аренде 1", A73="в аренде 2"), J73-K73, "") | J73: =IF(OR(A73="в аренде", A73="в аренде 1", A73="в аренде 2"), DATEDIF(E73, TODAY(), "D")*H73, "") | K73: 10200 | N73: 16000 | O73: =IFERROR(__xludf.DUMMYFUNCTION("IFERROR( VLOOKUP(C73, FILTER( IMPORTRANGE(""https://docs.google.com/spreadsheets/d/1ZBCmVvzoFu7X0td7O5T5xSJplK8m8h9wvdESBc0a1EE/edit#gid=1841437934"", ""Лист1!$C:$I""), IMPORTRANGE(""https://docs.google.com/spreadsheets/d/1ZBCmVvzoFu7X0"&"td7O5T5xSJplK8m8h9wvdESBc0a1EE/edit#gid=1841437934"", ""Лист1!$C:$C"") = C73 ), 7, FALSE ), """" ) "),30225.0) -> 30225 | P73: =IFERROR(__xludf.DUMMYFUNCTION("IF(OR(ISBLANK(Q73), ISBLANK(O73), VALUE(SUBSTITUTE(INDEX(SPLIT(IF(ISBLANK(R73), Q73, R73), "" km""), 0, 1), "" "", """")) - O73 = 0), """", IF(ISBLANK(R73), VALUE(SUBSTITUTE(INDEX(SPLIT(Q73, "" km""), 0, 1), "" "", """")) - O73, VALUE(SUBSTITUTE(INDEX(SPL"&"IT(R73, "" km""), 0, 1), "" "", """")) - O73))"),-14225.0) -> -14225 | Q73: =IF(AND(ISBLANK(N73), ISBLANK(E73), ISBLANK(R73)), "", IF(ISBLANK(R73), TEXT(N73, "#,##0") & " Km, " & TEXT(E73, "dd.mm.yyyy"), R73)) -> 16 000 Km, 05.02.2023 | S73: 5000 | T73: 2 | V73: взрослый чел интересный поэт | W73: =IF(F73 = "", "", IF(NOW() > (DATEVALUE(LEFT(F73, SEARCH(",", F73) - 2)) + TIMEVALUE(MID(F73, SEARCH(",", F73) + 2, 5))), "Завершена", "В аренде")) -> Завершена | X73: =IFERROR(__xludf.DUMMYFUNCTION("IF(C73 = """", """", IF(REGEXMATCH(C73, ""PCX|NMAX|ADV|CLICK""), ""скутер"", ""мото""))"),"мото") -> мото
A74: Завершена | B74: OFF | C74: NMAX 155CC GREEN BLACK | D74: Ivan Rochev | E74: 44963 | F74: 45022 | G74: =IF((E74="")+(F74=""), "", IF(DATEDIF(E74, F74, "d") > 30, DATEDIF(E74, F74, "m") & " М", DATEDIF(E74, F74, "d") & " Д")) -> 2 М | H74: 271 | I74: =IF(OR(A74="в аренде", A74="в аренде 1", A74="в аренде 2"), J74-K74, "") | J74: =IF(OR(A74="в аренде", A74="в аренде 1", A74="в аренде 2"), DATEDIF(E74, TODAY(), "D")*H74, "") | K74: =8500+7500 -> 16000 | N74: 13361 | O74: =IFERROR(__xludf.DUMMYFUNCTION("IFERROR( VLOOKUP(C74, FILTER( IMPORTRANGE(""https://docs.google.com/spreadsheets/d/1ZBCmVvzoFu7X0td7O5T5xSJplK8m8h9wvdESBc0a1EE/edit#gid=1841437934"", ""Лист1!$C:$I""), IMPORTRANGE(""https://docs.google.com/spreadsheets/d/1ZBCmVvzoFu7X0"&"td7O5T5xSJplK8m8h9wvdESBc0a1EE/edit#gid=1841437934"", ""Лист1!$C:$C"") = C74 ), 7, FALSE ), """" ) "),"") | P74: =IFERROR(__xludf.DUMMYFUNCTION("IF(OR(ISBLANK(Q74), ISBLANK(O74), VALUE(SUBSTITUTE(INDEX(SPLIT(IF(ISBLANK(R74), Q74, R74), "" km""), 0, 1), "" "", """")) - O74 = 0), """", IF(ISBLANK(R74), VALUE(SUBSTITUTE(INDEX(SPLIT(Q74, "" km""), 0, 1), "" "", """")) - O74, VALUE(SUBSTITUTE(INDEX(SPL"&"IT(R74, "" km""), 0, 1), "" "", """")) - O74))"),13361.0) -> 13361 | Q74: =IF(AND(ISBLANK(N74), ISBLANK(E74), ISBLANK(R74)), "", IF(ISBLANK(R74), TEXT(N74, "#,##0") & " Km, " & TEXT(E74, "dd.mm.yyyy"), R74)) -> 13 361 Km, 06.02.2023 | S74: 3000 | T74: 2 | U74: @ivanro4ev | V74: милая молодая пара | W74: =IF(F74 = "", "", IF(NOW() > (DATEVALUE(LEFT(F74, SEARCH(",", F74) - 2)) + TIMEVALUE(MID(F74, SEARCH(",", F74) + 2, 5))), "Завершена", "В аренде")) -> Завершена | X74: =IFERROR(__xludf.DUMMYFUNCTION("IF(C74 = """", """", IF(REGEXMATCH(C74, ""PCX|NMAX|ADV|CLICK""), ""скутер"", ""мото""))"),"скутер") -> скутер
A75: Завершена | B75: OFF | C75: CBR 650R PHUKET 4505 | D75: Bogdan Borvinok | E75: 44965 | F75: 44971 | G75: =IF((E75="")+(F75=""), "", IF(DATEDIF(E75, F75, "d") > 30, DATEDIF(E75, F75, "m") & " М", DATEDIF(E75, F75, "d") & " Д")) -> 6 Д | H75: 2000 | I75: =IF(OR(A75="в аренде", A75="в аренде 1", A75="в аренде 2"), J75-K75, "") | J75: =IF(OR(A75="в аренде", A75="в аренде 1", A75="в аренде 2"), DATEDIF(E75, TODAY(), "D")*H75, "") | K75: 12000 | N75: 30400 | O75: =IFERROR(__xludf.DUMMYFUNCTION("IFERROR( VLOOKUP(C75, FILTER( IMPORTRANGE(""https://docs.google.com/spreadsheets/d/1ZBCmVvzoFu7X0td7O5T5xSJplK8m8h9wvdESBc0a1EE/edit#gid=1841437934"", ""Лист1!$C:$I""), IMPORTRANGE(""https://docs.google.com/spreadsheets/d/1ZBCmVvzoFu7X0"&"td7O5T5xSJplK8m8h9wvdESBc0a1EE/edit#gid=1841437934"", ""Лист1!$C:$C"") = C75 ), 7, FALSE ), """" ) "),63700.0) -> 63700 | P75: =IFERROR(__xludf.DUMMYFUNCTION("IF(OR(ISBLANK(Q75), ISBLANK(O75), VALUE(SUBSTITUTE(INDEX(SPLIT(IF(ISBLANK(R75), Q75, R75), "" km""), 0, 1), "" "", """")) - O75 = 0), """", IF(ISBLANK(R75), VALUE(SUBSTITUTE(INDEX(SPLIT(Q75, "" km""), 0, 1), "" "", """")) - O75, VALUE(SUBSTITUTE(INDEX(SPL"&"IT(R75, "" km""), 0, 1), "" "", """")) - O75))"),-33300.0) -> -33300 | Q75: =IF(AND(ISBLANK(N75), ISBLANK(E75), ISBLANK(R75)), "", IF(ISBLANK(R75), TEXT(N75, "#,##0") & " Km, " & TEXT(E75, "dd.mm.yyyy"), R75)) -> 30 400 Km, 08.02.2023 | S75: 20000 | T75: 1 | U75: @gromovgram | V75: челы с бали на понте :) | W75: =IF(F75 = "", "", IF(NOW() > (DATEVALUE(LEFT(F75, SEARCH(",", F75) - 2)) + TIMEVALUE(MID(F75, SEARCH(",", F75) + 2, 5))), "Завершена", "В аренде")) -> Завершена | X75: =IFERROR(__xludf.DUMMYFUNCTION("IF(C75 = """", """", IF(REGEXMATCH(C75, ""PCX|NMAX|ADV|CLICK""), ""скутер"", ""мото""))"),"мото") -> мото
A76: Завершена | B76: OFF | C76: ADV 150CC PHUKET 7497 | D76: Alekxey Rykov | E76: 44965 | F76: 45002 | G76: =IF((E76="")+(F76=""), "", IF(DATEDIF(E76, F76, "d") > 30, DATEDIF(E76, F76, "m") & " М", DATEDIF(E76, F76, "d") & " Д")) -> 1 М | H76: 333 | I76: =IF(OR(A76="в аренде", A76="в аренде 1", A76="в аренде 2"), J76-K76, "") | J76: =IF(OR(A76="в аренде", A76="в аренде 1", A76="в аренде 2"), DATEDIF(E76, TODAY(), "D")*H76, "") | K76: =9000+3500 -> 12500 | N76: 20500 | O76: =IFERROR(__xludf.DUMMYFUNCTION("IFERROR( VLOOKUP(C76, FILTER( IMPORTRANGE(""https://docs.google.com/spreadsheets/d/1ZBCmVvzoFu7X0td7O5T5xSJplK8m8h9wvdESBc0a1EE/edit#gid=1841437934"", ""Лист1!$C:$I""), IMPORTRANGE(""https://docs.google.com/spreadsheets/d/1ZBCmVvzoFu7X0"&"td7O5T5xSJplK8m8h9wvdESBc0a1EE/edit#gid=1841437934"", ""Лист1!$C:$C"") = C76 ), 7, FALSE ), """" ) "),"") | P76: =IFERROR(__xludf.DUMMYFUNCTION("IF(OR(ISBLANK(Q76), ISBLANK(O76), VALUE(SUBSTITUTE(INDEX(SPLIT(IF(ISBLANK(R76), Q76, R76), "" km""), 0, 1), "" "", """")) - O76 = 0), """", IF(ISBLANK(R76), VALUE(SUBSTITUTE(INDEX(SPLIT(Q76, "" km""), 0, 1), "" "", """")) - O76, VALUE(SUBSTITUTE(INDEX(SPL"&"IT(R76, "" km""), 0, 1), "" "", """")) - O76))"),20500.0) -> 20500 | Q76: =IF(AND(ISBLANK(N76), ISBLANK(E76), ISBLANK(R76)), "", IF(ISBLANK(R76), TEXT(N76, "#,##0") & " Km, " & TEXT(E76, "dd.mm.yyyy"), R76)) -> 20 500 Km, 08.02.2023 | S76: 3000 | T76: 2 | U76: +79267191322 | V76: норм чел не норм друг | W76: =IF(F76 = "", "", IF(NOW() > (DATEVALUE(LEFT(F76, SEARCH(",", F76) - 2)) + TIMEVALUE(MID(F76, SEARCH(",", F76) + 2, 5))), "Завершена", "В аренде")) -> Завершена | X76: =IFERROR(__xludf.DUMMYFUNCTION("IF(C76 = """", """", IF(REGEXMATCH(C76, ""PCX|NMAX|ADV|CLICK""), ""скутер"", ""мото""))"),"скутер") -> скутер
A77: Завершена | B77: OFF | C77: FORZA 300CC GREY PHUKET 4234 | D77: Владимир | E77: 44966 | F77: 44967 | G77: =IF((E77="")+(F77=""), "", IF(DATEDIF(E77, F77, "d") > 30, DATEDIF(E77, F77, "m") & " М", DATEDIF(E77, F77, "d") & " Д")) -> 1 Д | H77: 700 | I77: =IF(OR(A77="в аренде", A77="в аренде 1", A77="в аренде 2"), J77-K77, "") | J77: =IF(OR(A77="в аренде", A77="в аренде 1", A77="в аренде 2"), DATEDIF(E77, TODAY(), "D")*H77, "") | K77: 0 | N77: 20000 | O77: =IFERROR(__xludf.DUMMYFUNCTION("IFERROR( VLOOKUP(C77, FILTER( IMPORTRANGE(""https://docs.google.com/spreadsheets/d/1ZBCmVvzoFu7X0td7O5T5xSJplK8m8h9wvdESBc0a1EE/edit#gid=1841437934"", ""Лист1!$C:$I""), IMPORTRANGE(""https://docs.google.com/spreadsheets/d/1ZBCmVvzoFu7X0"&"td7O5T5xSJplK8m8h9wvdESBc0a1EE/edit#gid=1841437934"", ""Лист1!$C:$C"") = C77 ), 7, FALSE ), """" ) "),"") | P77: =IFERROR(__xludf.DUMMYFUNCTION("IF(OR(ISBLANK(Q77), ISBLANK(O77), VALUE(SUBSTITUTE(INDEX(SPLIT(IF(ISBLANK(R77), Q77, R77), "" km""), 0, 1), "" "", """")) - O77 = 0), """", IF(ISBLANK(R77), VALUE(SUBSTITUTE(INDEX(SPLIT(Q77, "" km""), 0, 1), "" "", """")) - O77, VALUE(SUBSTITUTE(INDEX(SPL"&"IT(R77, "" km""), 0, 1), "" "", """")) - O77))"),20000.0) -> 20000 | Q77: =IF(AND(ISBLANK(N77), ISBLANK(E77), ISBLANK(R77)), "", IF(ISBLANK(R77), TEXT(N77, "#,##0") & " Km, " & TEXT(E77, "dd.mm.yyyy"), R77)) -> 20 000 Km, 09.02.2023 | S77: 0 | T77: 3 | U77: @VoV51 | V77: гуд на спорте | W77: =IF(F77 = "", "", IF(NOW() > (DATEVALUE(LEFT(F77, SEARCH(",", F77) - 2)) + TIMEVALUE(MID(F77, SEARCH(",", F77) + 2, 5))), "Завершена", "В аренде")) -> Завершена | X77: =IFERROR(__xludf.DUMMYFUNCTION("IF(C77 = """", """", IF(REGEXMATCH(C77, ""PCX|NMAX|ADV|CLICK""), ""скутер"", ""мото""))"),"мото") -> мото
A78: Завершена | B78: OFF | C78: NMAX 155CC GREEN-B PHUKET 4957 | D78: Максим | E78: 44973 | F78: 44985 | G78: =IF((E78="")+(F78=""), "", IF(DATEDIF(E78, F78, "d") > 30, DATEDIF(E78, F78, "m") & " М", DATEDIF(E78, F78, "d") & " Д")) -> 12 Д | H78: =7000/30 -> 233.33333 | I78: =IF(OR(A78="в аренде", A78="в аренде 1", A78="в аренде 2"), J78-K78, "") | J78: =IF(OR(A78="в аренде", A78="в аренде 1", A78="в аренде 2"), DATEDIF(E78, TODAY(), "D")*H78, "") | K78: 1200 | N78: 13900 | O78: =IFERROR(__xludf.DUMMYFUNCTION("IFERROR( VLOOKUP(C78, FILTER( IMPORTRANGE(""https://docs.google.com/spreadsheets/d/1ZBCmVvzoFu7X0td7O5T5xSJplK8m8h9wvdESBc0a1EE/edit#gid=1841437934"", ""Лист1!$C:$I""), IMPORTRANGE(""https://docs.google.com/spreadsheets/d/1ZBCmVvzoFu7X0"&"td7O5T5xSJplK8m8h9wvdESBc0a1EE/edit#gid=1841437934"", ""Лист1!$C:$C"") = C78 ), 7, FALSE ), """" ) "),30800.0) -> 30800 | P78: =IFERROR(__xludf.DUMMYFUNCTION("IF(OR(ISBLANK(Q78), ISBLANK(O78), VALUE(SUBSTITUTE(INDEX(SPLIT(IF(ISBLANK(R78), Q78, R78), "" km""), 0, 1), "" "", """")) - O78 = 0), """", IF(ISBLANK(R78), VALUE(SUBSTITUTE(INDEX(SPLIT(Q78, "" km""), 0, 1), "" "", """")) - O78, VALUE(SUBSTITUTE(INDEX(SPL"&"IT(R78, "" km""), 0, 1), "" "", """")) - O78))"),-16900.0) -> -16900 | Q78: =IF(AND(ISBLANK(N78), ISBLANK(E78), ISBLANK(R78)), "", IF(ISBLANK(R78), TEXT(N78, "#,##0") & " Km, " & TEXT(E78, "dd.mm.yyyy"), R78)) -> 13 900 Km, 16.02.2023 | S78: 3000 | T78: 0 | U78: @Maxmironov | V78: приличный небольшой опыт есть | W78: =IF(F78 = "", "", IF(NOW() > (DATEVALUE(LEFT(F78, SEARCH(",", F78) - 2)) + TIMEVALUE(MID(F78, SEARCH(",", F78) + 2, 5))), "Завершена", "В аренде")) -> Завершена | X78: =IFERROR(__xludf.DUMMYFUNCTION("IF(C78 = """", """", IF(REGEXMATCH(C78, ""PCX|NMAX|ADV|CLICK""), ""скутер"", ""мото""))"),"скутер") -> скутер
A79: Завершена | B79: OFF | C79: NMAX 155CC BLACK GREEN PHUKET 4253 | D79: Максим | E79: 44973 | F79: 44985 | G79: =IF((E79="")+(F79=""), "", IF(DATEDIF(E79, F79, "d") > 30, DATEDIF(E79, F79, "m") & " М", DATEDIF(E79, F79, "d") & " Д")) -> 12 Д | H79: 0 | I79: =IF(OR(A79="в аренде", A79="в аренде 1", A79="в аренде 2"), J79-K79, "") | J79: =IF(OR(A79="в аренде", A79="в аренде 1", A79="в аренде 2"), DATEDIF(E79, TODAY(), "D")*H79, "") | K79: 2800 | N79: 17600 | O79: =IFERROR(__xludf.DUMMYFUNCTION("IFERROR( VLOOKUP(C79, FILTER( IMPORTRANGE(""https://docs.google.com/spreadsheets/d/1ZBCmVvzoFu7X0td7O5T5xSJplK8m8h9wvdESBc0a1EE/edit#gid=1841437934"", ""Лист1!$C:$I""), IMPORTRANGE(""https://docs.google.com/spreadsheets/d/1ZBCmVvzoFu7X0"&"td7O5T5xSJplK8m8h9wvdESBc0a1EE/edit#gid=1841437934"", ""Лист1!$C:$C"") = C79 ), 7, FALSE ), """" ) "),35800.0) -> 35800 | P79: =IFERROR(__xludf.DUMMYFUNCTION("IF(OR(ISBLANK(Q79), ISBLANK(O79), VALUE(SUBSTITUTE(INDEX(SPLIT(IF(ISBLANK(R79), Q79, R79), "" km""), 0, 1), "" "", """")) - O79 = 0), """", IF(ISBLANK(R79), VALUE(SUBSTITUTE(INDEX(SPLIT(Q79, "" km""), 0, 1), "" "", """")) - O79, VALUE(SUBSTITUTE(INDEX(SPL"&"IT(R79, "" km""), 0, 1), "" "", """")) - O79))"),-18200.0) -> -18200 | Q79: =IF(AND(ISBLANK(N79), ISBLANK(E79), ISBLANK(R79)), "", IF(ISBLANK(R79), TEXT(N79, "#,##0") & " Km, " & TEXT(E79, "dd.mm.yyyy"), R79)) -> 17 600 Km, 16.02.2023 | S79: 3000 | T79: 0 | U79: @Maxmironov | V79: приличный небольшой опыт есть | W79: =IF(F79 = "", "", IF(NOW() > (DATEVALUE(LEFT(F79, SEARCH(",", F79) - 2)) + TIMEVALUE(MID(F79, SEARCH(",", F79) + 2, 5))), "Завершена", "В аренде")) -> Завершена | X79: =IFERROR(__xludf.DUMMYFUNCTION("IF(C79 = """", """", IF(REGEXMATCH(C79, ""PCX|NMAX|ADV|CLICK""), ""скутер"", ""мото""))"),"скутер") -> скутер
A80: Завершена | B80: OFF | C80: XMAX 300CC BLUE PHUKET 5773 | D80: Dmitrii Boitcov | E80: 44973 | F80: 44985 | G80: =IF((E80="")+(F80=""), "", IF(DATEDIF(E80, F80, "d") > 30, DATEDIF(E80, F80, "m") & " М", DATEDIF(E80, F80, "d") & " Д")) -> 12 Д | H80: 800 | I80: =IF(OR(A80="в аренде", A80="в аренде 1", A80="в аренде 2"), J80-K80, "") | J80: =IF(OR(A80="в аренде", A80="в аренде 1", A80="в аренде 2"), DATEDIF(E80, TODAY(), "D")*H80, "") | K80: =5600+2300+1600 -> 9500 | N80: 30600 | O80: =IFERROR(__xludf.DUMMYFUNCTION("IFERROR( VLOOKUP(C80, FILTER( IMPORTRANGE(""https://docs.google.com/spreadsheets/d/1ZBCmVvzoFu7X0td7O5T5xSJplK8m8h9wvdESBc0a1EE/edit#gid=1841437934"", ""Лист1!$C:$I""), IMPORTRANGE(""https://docs.google.com/spreadsheets/d/1ZBCmVvzoFu7X0"&"td7O5T5xSJplK8m8h9wvdESBc0a1EE/edit#gid=1841437934"", ""Лист1!$C:$C"") = C80 ), 7, FALSE ), """" ) "),23500.0) -> 23500 | P80: =IFERROR(__xludf.DUMMYFUNCTION("IF(OR(ISBLANK(Q80), ISBLANK(O80), VALUE(SUBSTITUTE(INDEX(SPLIT(IF(ISBLANK(R80), Q80, R80), "" km""), 0, 1), "" "", """")) - O80 = 0), """", IF(ISBLANK(R80), VALUE(SUBSTITUTE(INDEX(SPLIT(Q80, "" km""), 0, 1), "" "", """")) - O80, VALUE(SUBSTITUTE(INDEX(SPL"&"IT(R80, "" km""), 0, 1), "" "", """")) - O80))"),7100.0) -> 7100 | Q80: =IF(AND(ISBLANK(N80), ISBLANK(E80), ISBLANK(R80)), "", IF(ISBLANK(R80), TEXT(N80, "#,##0") & " Km, " & TEXT(E80, "dd.mm.yyyy"), R80)) -> 30 600 Km, 16.02.2023 | S80: 200 | T80: 2 | V80: как будто зэки | W80: =IF(F80 = "", "", IF(NOW() > (DATEVALUE(LEFT(F80, SEARCH(",", F80) - 2)) + TIMEVALUE(MID(F80, SEARCH(",", F80) + 2, 5))), "Завершена", "В аренде")) -> Завершена | X80: =IFERROR(__xludf.DUMMYFUNCTION("IF(C80 = """", """", IF(REGEXMATCH(C80, ""PCX|NMAX|ADV|CLICK""), ""скутер"", ""мото""))"),"мото") -> мото
A81: Завершена | B81: OFF | C81: XSR 155СС GREY PHUKET 6946 | D81: Dmitry Trofimov | E81: 44974 | F81: 45024 | G81: =IF((E81="")+(F81=""), "", IF(DATEDIF(E81, F81, "d") > 30, DATEDIF(E81, F81, "m") & " М", DATEDIF(E81, F81, "d") & " Д")) -> 1 М | H81: 400 | I81: =IF(OR(A81="в аренде", A81="в аренде 1", A81="в аренде 2"), J81-K81, "") | J81: =IF(OR(A81="в аренде", A81="в аренде 1", A81="в аренде 2"), DATEDIF(E81, TODAY(), "D")*H81, "") | K81: =2800+12000+12000+5600 -> 32400 | N81: 7110 | O81: =IFERROR(__xludf.DUMMYFUNCTION("IFERROR( VLOOKUP(C81, FILTER( IMPORTRANGE(""https://docs.google.com/spreadsheets/d/1ZBCmVvzoFu7X0td7O5T5xSJplK8m8h9wvdESBc0a1EE/edit#gid=1841437934"", ""Лист1!$C:$I""), IMPORTRANGE(""https://docs.google.com/spreadsheets/d/1ZBCmVvzoFu7X0"&"td7O5T5xSJplK8m8h9wvdESBc0a1EE/edit#gid=1841437934"", ""Лист1!$C:$C"") = C81 ), 7, FALSE ), """" ) "),"") | P81: =IFERROR(__xludf.DUMMYFUNCTION("IF(OR(ISBLANK(Q81), ISBLANK(O81), VALUE(SUBSTITUTE(INDEX(SPLIT(IF(ISBLANK(R81), Q81, R81), "" km""), 0, 1), "" "", """")) - O81 = 0), """", IF(ISBLANK(R81), VALUE(SUBSTITUTE(INDEX(SPLIT(Q81, "" km""), 0, 1), "" "", """")) - O81, VALUE(SUBSTITUTE(INDEX(SPL"&"IT(R81, "" km""), 0, 1), "" "", """")) - O81))"),7110.0) -> 7110 | Q81: =IF(AND(ISBLANK(N81), ISBLANK(E81), ISBLANK(R81)), "", IF(ISBLANK(R81), TEXT(N81, "#,##0") & " Km, " & TEXT(E81, "dd.mm.yyyy"), R81)) -> 7 110 Km, 17.02.2023 | S81: 300 | T81: 2 | U81: @d1mausername | V81: норм чел молодой строитель нет опытана механике | W81: =IF(F81 = "", "", IF(NOW() > (DATEVALUE(LEFT(F81, SEARCH(",", F81) - 2)) + TIMEVALUE(MID(F81, SEARCH(",", F81) + 2, 5))), "Завершена", "В аренде")) -> Завершена | X81: =IFERROR(__xludf.DUMMYFUNCTION("IF(C81 = """", """", IF(REGEXMATCH(C81, ""PCX|NMAX|ADV|CLICK""), ""скутер"", ""мото""))"),"мото") -> мото
A82: Завершена | B82: OFF | C82: CBR 650R PHUKET 4505 | D82: Petr Lerman | E82: 44975 | F82: 44982 | G82: =IF((E82="")+(F82=""), "", IF(DATEDIF(E82, F82, "d") > 30, DATEDIF(E82, F82, "m") & " М", DATEDIF(E82, F82, "d") & " Д")) -> 7 Д | H82: =12000/7 -> 1714.2857 | I82: =IF(OR(A82="в аренде", A82="в аренде 1", A82="в аренде 2"), J82-K82, "") | J82: =IF(OR(A82="в аренде", A82="в аренде 1", A82="в аренде 2"), DATEDIF(E82, TODAY(), "D")*H82, "") | K82: 12000 | N82: 30600 | O82: =IFERROR(__xludf.DUMMYFUNCTION("IFERROR( VLOOKUP(C82, FILTER( IMPORTRANGE(""https://docs.google.com/spreadsheets/d/1ZBCmVvzoFu7X0td7O5T5xSJplK8m8h9wvdESBc0a1EE/edit#gid=1841437934"", ""Лист1!$C:$I""), IMPORTRANGE(""https://docs.google.com/spreadsheets/d/1ZBCmVvzoFu7X0"&"td7O5T5xSJplK8m8h9wvdESBc0a1EE/edit#gid=1841437934"", ""Лист1!$C:$C"") = C82 ), 7, FALSE ), """" ) "),63700.0) -> 63700 | P82: =IFERROR(__xludf.DUMMYFUNCTION("IF(OR(ISBLANK(Q82), ISBLANK(O82), VALUE(SUBSTITUTE(INDEX(SPLIT(IF(ISBLANK(R82), Q82, R82), "" km""), 0, 1), "" "", """")) - O82 = 0), """", IF(ISBLANK(R82), VALUE(SUBSTITUTE(INDEX(SPLIT(Q82, "" km""), 0, 1), "" "", """")) - O82, VALUE(SUBSTITUTE(INDEX(SPL"&"IT(R82, "" km""), 0, 1), "" "", """")) - O82))"),-33100.0) -> -33100 | Q82: =IF(AND(ISBLANK(N82), ISBLANK(E82), ISBLANK(R82)), "", IF(ISBLANK(R82), TEXT(N82, "#,##0") & " Km, " & TEXT(E82, "dd.mm.yyyy"), R82)) -> 30 600 Km, 18.02.2023 | S82: 20000 | T82: 1 | U82: @m1333333333 | V82: интересный чел при деньгах | W82: =IF(F82 = "", "", IF(NOW() > (DATEVALUE(LEFT(F82, SEARCH(",", F82) - 2)) + TIMEVALUE(MID(F82, SEARCH(",", F82) + 2, 5))), "Завершена", "В аренде")) -> Завершена | X82: =IFERROR(__xludf.DUMMYFUNCTION("IF(C82 = """", """", IF(REGEXMATCH(C82, ""PCX|NMAX|ADV|CLICK""), ""скутер"", ""мото""))"),"мото") -> мото
A83: Завершена | B83: OFF | C83: XMAX 300CC RED PHUKET 6947 | D83: Bogdan Gerbzomer | E83: 44976 | F83: 45004 | G83: =IF((E83="")+(F83=""), "", IF(DATEDIF(E83, F83, "d") > 30, DATEDIF(E83, F83, "m") & " М", DATEDIF(E83, F83, "d") & " Д")) -> 28 Д | H83: =14500/30 -> 483.33333 | I83: =IF(OR(A83="в аренде", A83="в аренде 1", A83="в аренде 2"), J83-K83, "") | J83: =IF(OR(A83="в аренде", A83="в аренде 1", A83="в аренде 2"), DATEDIF(E83, TODAY(), "D")*H83, "") | K83: 14500 | N83: 12700 | O83: =IFERROR(__xludf.DUMMYFUNCTION("IFERROR( VLOOKUP(C83, FILTER( IMPORTRANGE(""https://docs.google.com/spreadsheets/d/1ZBCmVvzoFu7X0td7O5T5xSJplK8m8h9wvdESBc0a1EE/edit#gid=1841437934"", ""Лист1!$C:$I""), IMPORTRANGE(""https://docs.google.com/spreadsheets/d/1ZBCmVvzoFu7X0"&"td7O5T5xSJplK8m8h9wvdESBc0a1EE/edit#gid=1841437934"", ""Лист1!$C:$C"") = C83 ), 7, FALSE ), """" ) "),"") | P83: =IFERROR(__xludf.DUMMYFUNCTION("IF(OR(ISBLANK(Q83), ISBLANK(O83), VALUE(SUBSTITUTE(INDEX(SPLIT(IF(ISBLANK(R83), Q83, R83), "" km""), 0, 1), "" "", """")) - O83 = 0), """", IF(ISBLANK(R83), VALUE(SUBSTITUTE(INDEX(SPLIT(Q83, "" km""), 0, 1), "" "", """")) - O83, VALUE(SUBSTITUTE(INDEX(SPL"&"IT(R83, "" km""), 0, 1), "" "", """")) - O83))"),12700.0) -> 12700 | Q83: =IF(AND(ISBLANK(N83), ISBLANK(E83), ISBLANK(R83)), "", IF(ISBLANK(R83), TEXT(N83, "#,##0") & " Km, " & TEXT(E83, "dd.mm.yyyy"), R83)) -> 12 700 Km, 19.02.2023 | S83: 5000 | T83: 2 | U83: +79240030368 | V83: норм | W83: =IF(F83 = "", "", IF(NOW() > (DATEVALUE(LEFT(F83, SEARCH(",", F83) - 2)) + TIMEVALUE(MID(F83, SEARCH(",", F83) + 2, 5))), "Завершена", "В аренде")) -> Завершена | X83: =IFERROR(__xludf.DUMMYFUNCTION("IF(C83 = """", """", IF(REGEXMATCH(C83, ""PCX|NMAX|ADV|CLICK""), ""скутер"", ""мото""))"),"мото") -> мото
A84: Завершена | B84: OFF | C84: FORZA 300CC RED PHUKET 4244 | D84: Альберт | E84: 44976 | F84: 45010 | G84: =IF((E84="")+(F84=""), "", IF(DATEDIF(E84, F84, "d") > 30, DATEDIF(E84, F84, "m") & " М", DATEDIF(E84, F84, "d") & " Д")) -> 1 М | H84: 470 | I84: =IF(OR(A84="в аренде", A84="в аренде 1", A84="в аренде 2"), J84-K84, "") | J84: =IF(OR(A84="в аренде", A84="в аренде 1", A84="в аренде 2"), DATEDIF(E84, TODAY(), "D")*H84, "") | K84: 16000 | N84: 22400 | O84: =IFERROR(__xludf.DUMMYFUNCTION("IFERROR( VLOOKUP(C84, FILTER( IMPORTRANGE(""https://docs.google.com/spreadsheets/d/1ZBCmVvzoFu7X0td7O5T5xSJplK8m8h9wvdESBc0a1EE/edit#gid=1841437934"", ""Лист1!$C:$I""), IMPORTRANGE(""https://docs.google.com/spreadsheets/d/1ZBCmVvzoFu7X0"&"td7O5T5xSJplK8m8h9wvdESBc0a1EE/edit#gid=1841437934"", ""Лист1!$C:$C"") = C84 ), 7, FALSE ), """" ) "),"") | P84: =IFERROR(__xludf.DUMMYFUNCTION("IF(OR(ISBLANK(Q84), ISBLANK(O84), VALUE(SUBSTITUTE(INDEX(SPLIT(IF(ISBLANK(R84), Q84, R84), "" km""), 0, 1), "" "", """")) - O84 = 0), """", IF(ISBLANK(R84), VALUE(SUBSTITUTE(INDEX(SPLIT(Q84, "" km""), 0, 1), "" "", """")) - O84, VALUE(SUBSTITUTE(INDEX(SPL"&"IT(R84, "" km""), 0, 1), "" "", """")) - O84))"),22400.0) -> 22400 | Q84: =IF(AND(ISBLANK(N84), ISBLANK(E84), ISBLANK(R84)), "", IF(ISBLANK(R84), TEXT(N84, "#,##0") & " Km, " & TEXT(E84, "dd.mm.yyyy"), R84)) -> 22 400 Km, 19.02.2023 | S84: 5000 | T84: 2 | U84: @KabirovAA | V84: ОКР | W84: =IF(F84 = "", "", IF(NOW() > (DATEVALUE(LEFT(F84, SEARCH(",", F84) - 2)) + TIMEVALUE(MID(F84, SEARCH(",", F84) + 2, 5))), "Завершена", "В аренде")) -> Завершена | X84: =IFERROR(__xludf.DUMMYFUNCTION("IF(C84 = """", """", IF(REGEXMATCH(C84, ""PCX|NMAX|ADV|CLICK""), ""скутер"", ""мото""))"),"мото") -> мото
A85: Завершена | B85: OFF | C85: NMAX 155CC BLACK GOLD-3 PHUKET 7530 | D85: СОсед константин | E85: 44978 | F85: 44979 | G85: =IF((E85="")+(F85=""), "", IF(DATEDIF(E85, F85, "d") > 30, DATEDIF(E85, F85, "m") & " М", DATEDIF(E85, F85, "d") & " Д")) -> 1 Д | H85: 300 | I85: =IF(OR(A85="в аренде", A85="в аренде 1", A85="в аренде 2"), J85-K85, "") | J85: =IF(OR(A85="в аренде", A85="в аренде 1", A85="в аренде 2"), DATEDIF(E85, TODAY(), "D")*H85, "") | K85: 300 | N85: 36000 | O85: =IFERROR(__xludf.DUMMYFUNCTION("IFERROR( VLOOKUP(C85, FILTER( IMPORTRANGE(""https://docs.google.com/spreadsheets/d/1ZBCmVvzoFu7X0td7O5T5xSJplK8m8h9wvdESBc0a1EE/edit#gid=1841437934"", ""Лист1!$C:$I""), IMPORTRANGE(""https://docs.google.com/spreadsheets/d/1ZBCmVvzoFu7X0"&"td7O5T5xSJplK8m8h9wvdESBc0a1EE/edit#gid=1841437934"", ""Лист1!$C:$C"") = C85 ), 7, FALSE ), """" ) "),31000.0) -> 31000 | P85: =IFERROR(__xludf.DUMMYFUNCTION("IF(OR(ISBLANK(Q85), ISBLANK(O85), VALUE(SUBSTITUTE(INDEX(SPLIT(IF(ISBLANK(R85), Q85, R85), "" km""), 0, 1), "" "", """")) - O85 = 0), """", IF(ISBLANK(R85), VALUE(SUBSTITUTE(INDEX(SPLIT(Q85, "" km""), 0, 1), "" "", """")) - O85, VALUE(SUBSTITUTE(INDEX(SPL"&"IT(R85, "" km""), 0, 1), "" "", """")) - O85))"),5000.0) -> 5000 | Q85: =IF(AND(ISBLANK(N85), ISBLANK(E85), ISBLANK(R85)), "", IF(ISBLANK(R85), TEXT(N85, "#,##0") & " Km, " & TEXT(E85, "dd.mm.yyyy"), R85)) -> 36 000 Km, 21.02.2023 | S85: 3000 | T85: 3 | V85: кантемир компани | W85: =IF(F85 = "", "", IF(NOW() > (DATEVALUE(LEFT(F85, SEARCH(",", F85) - 2)) + TIMEVALUE(MID(F85, SEARCH(",", F85) + 2, 5))), "Завершена", "В аренде")) -> Завершена | X85: =IFERROR(__xludf.DUMMYFUNCTION("IF(C85 = """", """", IF(REGEXMATCH(C85, ""PCX|NMAX|ADV|CLICK""), ""скутер"", ""мото""))"),"скутер") -> скутер
A86: Завершена | B86: OFF | C86: NMAX 155CC BLACK-2 PHUKET 9561 | D86: PAvel Nikulin | E86: 44978 | F86: 45068 | G86: =IF((E86="")+(F86=""), "", IF(DATEDIF(E86, F86, "d") > 30, DATEDIF(E86, F86, "m") & " М", DATEDIF(E86, F86, "d") & " Д")) -> 3 М | H86: =7000/30 -> 233.33333 | I86: =IF(OR(A86="в аренде", A86="в аренде 1", A86="в аренде 2"), J86-K86, "") | J86: =IF(OR(A86="в аренде", A86="в аренде 1", A86="в аренде 2"), DATEDIF(E86, TODAY(), "D")*H86, "") | K86: =7500+7000+7000 -> 21500 | N86: 14100 | O86: =IFERROR(__xludf.DUMMYFUNCTION("IFERROR( VLOOKUP(C86, FILTER( IMPORTRANGE(""https://docs.google.com/spreadsheets/d/1ZBCmVvzoFu7X0td7O5T5xSJplK8m8h9wvdESBc0a1EE/edit#gid=1841437934"", ""Лист1!$C:$I""), IMPORTRANGE(""https://docs.google.com/spreadsheets/d/1ZBCmVvzoFu7X0"&"td7O5T5xSJplK8m8h9wvdESBc0a1EE/edit#gid=1841437934"", ""Лист1!$C:$C"") = C86 ), 7, FALSE ), """" ) "),"") | P86: =IFERROR(__xludf.DUMMYFUNCTION("IF(OR(ISBLANK(Q86), ISBLANK(O86), VALUE(SUBSTITUTE(INDEX(SPLIT(IF(ISBLANK(R86), Q86, R86), "" km""), 0, 1), "" "", """")) - O86 = 0), """", IF(ISBLANK(R86), VALUE(SUBSTITUTE(INDEX(SPLIT(Q86, "" km""), 0, 1), "" "", """")) - O86, VALUE(SUBSTITUTE(INDEX(SPL"&"IT(R86, "" km""), 0, 1), "" "", """")) - O86))"),"#VALUE!") -> #VALUE! | Q86: =IF(AND(ISBLANK(N86), ISBLANK(E86), ISBLANK(R86)), "", IF(ISBLANK(R86), TEXT(N86, "#,##0") & " Km, " & TEXT(E86, "dd.mm.yyyy"), R86)) -> сделал скидку теперь по 7000 с мая | R86: сделал скидку теперь по 7000 с мая | S86: 3000 | T86: 2 | U86: @ipaul3277 | V86: норм чел найхарн | W86: =IF(F86 = "", "", IF(NOW() > (DATEVALUE(LEFT(F86, SEARCH(",", F86) - 2)) + TIMEVALUE(MID(F86, SEARCH(",", F86) + 2, 5))), "Завершена", "В аренде")) -> Завершена | X86: =IFERROR(__xludf.DUMMYFUNCTION("IF(C86 = """", """", IF(REGEXMATCH(C86, ""PCX|NMAX|ADV|CLICK""), ""скутер"", ""мото""))"),"скутер") -> скутер
A87: Завершена | B87: OFF | C87: NMAX 155CC GREEN MATT PHUKET 6901 | D87: СОсед константин | E87: 44979 | F87: 44980 | G87: =IF((E87="")+(F87=""), "", IF(DATEDIF(E87, F87, "d") > 30, DATEDIF(E87, F87, "m") & " М", DATEDIF(E87, F87, "d") & " Д")) -> 1 Д | H87: 400 | I87: =IF(OR(A87="в аренде", A87="в аренде 1", A87="в аренде 2"), J87-K87, "") | J87: =IF(OR(A87="в аренде", A87="в аренде 1", A87="в аренде 2"), DATEDIF(E87, TODAY(), "D")*H87, "") | K87: 400 | N87: 23500 | O87: =IFERROR(__xludf.DUMMYFUNCTION("IFERROR( VLOOKUP(C87, FILTER( IMPORTRANGE(""https://docs.google.com/spreadsheets/d/1ZBCmVvzoFu7X0td7O5T5xSJplK8m8h9wvdESBc0a1EE/edit#gid=1841437934"", ""Лист1!$C:$I""), IMPORTRANGE(""https://docs.google.com/spreadsheets/d/1ZBCmVvzoFu7X0"&"td7O5T5xSJplK8m8h9wvdESBc0a1EE/edit#gid=1841437934"", ""Лист1!$C:$C"") = C87 ), 7, FALSE ), """" ) "),"") | P87: =IFERROR(__xludf.DUMMYFUNCTION("IF(OR(ISBLANK(Q87), ISBLANK(O87), VALUE(SUBSTITUTE(INDEX(SPLIT(IF(ISBLANK(R87), Q87, R87), "" km""), 0, 1), "" "", """")) - O87 = 0), """", IF(ISBLANK(R87), VALUE(SUBSTITUTE(INDEX(SPLIT(Q87, "" km""), 0, 1), "" "", """")) - O87, VALUE(SUBSTITUTE(INDEX(SPL"&"IT(R87, "" km""), 0, 1), "" "", """")) - O87))"),23500.0) -> 23500 | Q87: =IF(AND(ISBLANK(N87), ISBLANK(E87), ISBLANK(R87)), "", IF(ISBLANK(R87), TEXT(N87, "#,##0") & " Km, " & TEXT(E87, "dd.mm.yyyy"), R87)) -> 23 500 Km, 22.02.2023 | S87: 0 | T87: 1 | V87: кантемир компани | W87: =IF(F87 = "", "", IF(NOW() > (DATEVALUE(LEFT(F87, SEARCH(",", F87) - 2)) + TIMEVALUE(MID(F87, SEARCH(",", F87) + 2, 5))), "Завершена", "В аренде")) -> Завершена | X87: =IFERROR(__xludf.DUMMYFUNCTION("IF(C87 = """", """", IF(REGEXMATCH(C87, ""PCX|NMAX|ADV|CLICK""), ""скутер"", ""мото""))"),"скутер") -> скутер
A88: Завершена | B88: OFF | C88: NMAX 155CC GREY MATT PHUKET 7527 | D88: Irina Oksanichenko | E88: 44980 | F88: 44990 | G88: =IF((E88="")+(F88=""), "", IF(DATEDIF(E88, F88, "d") > 30, DATEDIF(E88, F88, "m") & " М", DATEDIF(E88, F88, "d") & " Д")) -> 10 Д | H88: 325 | I88: =IF(OR(A88="в аренде", A88="в аренде 1", A88="в аренде 2"), J88-K88, "") | J88: =IF(OR(A88="в аренде", A88="в аренде 1", A88="в аренде 2"), DATEDIF(E88, TODAY(), "D")*H88, "") | K88: 3250 | N88: 15500 | O88: =IFERROR(__xludf.DUMMYFUNCTION("IFERROR( VLOOKUP(C88, FILTER( IMPORTRANGE(""https://docs.google.com/spreadsheets/d/1ZBCmVvzoFu7X0td7O5T5xSJplK8m8h9wvdESBc0a1EE/edit#gid=1841437934"", ""Лист1!$C:$I""), IMPORTRANGE(""https://docs.google.com/spreadsheets/d/1ZBCmVvzoFu7X0"&"td7O5T5xSJplK8m8h9wvdESBc0a1EE/edit#gid=1841437934"", ""Лист1!$C:$C"") = C88 ), 7, FALSE ), """" ) "),"") | P88: =IFERROR(__xludf.DUMMYFUNCTION("IF(OR(ISBLANK(Q88), ISBLANK(O88), VALUE(SUBSTITUTE(INDEX(SPLIT(IF(ISBLANK(R88), Q88, R88), "" km""), 0, 1), "" "", """")) - O88 = 0), """", IF(ISBLANK(R88), VALUE(SUBSTITUTE(INDEX(SPLIT(Q88, "" km""), 0, 1), "" "", """")) - O88, VALUE(SUBSTITUTE(INDEX(SPL"&"IT(R88, "" km""), 0, 1), "" "", """")) - O88))"),15500.0) -> 15500 | Q88: =IF(AND(ISBLANK(N88), ISBLANK(E88), ISBLANK(R88)), "", IF(ISBLANK(R88), TEXT(N88, "#,##0") & " Km, " & TEXT(E88, "dd.mm.yyyy"), R88)) -> 15 500 Km, 23.02.2023 | S88: сто дол | T88: 2 | V88: 3 девушки патонг | W88: =IF(F88 = "", "", IF(NOW() > (DATEVALUE(LEFT(F88, SEARCH(",", F88) - 2)) + TIMEVALUE(MID(F88, SEARCH(",", F88) + 2, 5))), "Завершена", "В аренде")) -> Завершена | X88: =IFERROR(__xludf.DUMMYFUNCTION("IF(C88 = """", """", IF(REGEXMATCH(C88, ""PCX|NMAX|ADV|CLICK""), ""скутер"", ""мото""))"),"скутер") -> скутер
A89: Завершена | B89: OFF | C89: NMAX 155CC GREEN MATT PHUKET 6901 | D89: Tatiana Kievskaya | E89: 44980 | F89: 44990 | G89: =IF((E89="")+(F89=""), "", IF(DATEDIF(E89, F89, "d") > 30, DATEDIF(E89, F89, "m") & " М", DATEDIF(E89, F89, "d") & " Д")) -> 10 Д | H89: 325 | I89: =IF(OR(A89="в аренде", A89="в аренде 1", A89="в аренде 2"), J89-K89, "") | J89: =IF(OR(A89="в аренде", A89="в аренде 1", A89="в аренде 2"), DATEDIF(E89, TODAY(), "D")*H89, "") | K89: =3250-500 -> 2750 | N89: 23500 | O89: =IFERROR(__xludf.DUMMYFUNCTION("IFERROR( VLOOKUP(C89, FILTER( IMPORTRANGE(""https://docs.google.com/spreadsheets/d/1ZBCmVvzoFu7X0td7O5T5xSJplK8m8h9wvdESBc0a1EE/edit#gid=1841437934"", ""Лист1!$C:$I""), IMPORTRANGE(""https://docs.google.com/spreadsheets/d/1ZBCmVvzoFu7X0"&"td7O5T5xSJplK8m8h9wvdESBc0a1EE/edit#gid=1841437934"", ""Лист1!$C:$C"") = C89 ), 7, FALSE ), """" ) "),"") | P89: =IFERROR(__xludf.DUMMYFUNCTION("IF(OR(ISBLANK(Q89), ISBLANK(O89), VALUE(SUBSTITUTE(INDEX(SPLIT(IF(ISBLANK(R89), Q89, R89), "" km""), 0, 1), "" "", """")) - O89 = 0), """", IF(ISBLANK(R89), VALUE(SUBSTITUTE(INDEX(SPLIT(Q89, "" km""), 0, 1), "" "", """")) - O89, VALUE(SUBSTITUTE(INDEX(SPL"&"IT(R89, "" km""), 0, 1), "" "", """")) - O89))"),23500.0) -> 23500 | Q89: =IF(AND(ISBLANK(N89), ISBLANK(E89), ISBLANK(R89)), "", IF(ISBLANK(R89), TEXT(N89, "#,##0") & " Km, " & TEXT(E89, "dd.mm.yyyy"), R89)) -> 23 500 Km, 23.02.2023 | S89: сто дол | T89: 1 | V89: 3 девушки патонг | W89: =IF(F89 = "", "", IF(NOW() > (DATEVALUE(LEFT(F89, SEARCH(",", F89) - 2)) + TIMEVALUE(MID(F89, SEARCH(",", F89) + 2, 5))), "Завершена", "В аренде")) -> Завершена | X89: =IFERROR(__xludf.DUMMYFUNCTION("IF(C89 = """", """", IF(REGEXMATCH(C89, ""PCX|NMAX|ADV|CLICK""), ""скутер"", ""мото""))"),"скутер") -> скутер
A90: Завершена | B90: OFF | C90: NMAX 155CC GREEN-B PHUKET 4957 | D90: СОсед константин | E90: 44981 | F90: 44983 | G90: =IF((E90="")+(F90=""), "", IF(DATEDIF(E90, F90, "d") > 30, DATEDIF(E90, F90, "m") & " М", DATEDIF(E90, F90, "d") & " Д")) -> 2 Д | H90: 400 | I90: =IF(OR(A90="в аренде", A90="в аренде 1", A90="в аренде 2"), J90-K90, "") | J90: =IF(OR(A90="в аренде", A90="в аренде 1", A90="в аренде 2"), DATEDIF(E90, TODAY(), "D")*H90, "") | K90: 800 | N90: 14300 | O90: =IFERROR(__xludf.DUMMYFUNCTION("IFERROR( VLOOKUP(C90, FILTER( IMPORTRANGE(""https://docs.google.com/spreadsheets/d/1ZBCmVvzoFu7X0td7O5T5xSJplK8m8h9wvdESBc0a1EE/edit#gid=1841437934"", ""Лист1!$C:$I""), IMPORTRANGE(""https://docs.google.com/spreadsheets/d/1ZBCmVvzoFu7X0"&"td7O5T5xSJplK8m8h9wvdESBc0a1EE/edit#gid=1841437934"", ""Лист1!$C:$C"") = C90 ), 7, FALSE ), """" ) "),30800.0) -> 30800 | P90: =IFERROR(__xludf.DUMMYFUNCTION("IF(OR(ISBLANK(Q90), ISBLANK(O90), VALUE(SUBSTITUTE(INDEX(SPLIT(IF(ISBLANK(R90), Q90, R90), "" km""), 0, 1), "" "", """")) - O90 = 0), """", IF(ISBLANK(R90), VALUE(SUBSTITUTE(INDEX(SPLIT(Q90, "" km""), 0, 1), "" "", """")) - O90, VALUE(SUBSTITUTE(INDEX(SPL"&"IT(R90, "" km""), 0, 1), "" "", """")) - O90))"),-16500.0) -> -16500 | Q90: =IF(AND(ISBLANK(N90), ISBLANK(E90), ISBLANK(R90)), "", IF(ISBLANK(R90), TEXT(N90, "#,##0") & " Km, " & TEXT(E90, "dd.mm.yyyy"), R90)) -> 14 300 Km, 24.02.2023 | S90: 0 | T90: 1 | V90: кантемир компани | W90: =IF(F90 = "", "", IF(NOW() > (DATEVALUE(LEFT(F90, SEARCH(",", F90) - 2)) + TIMEVALUE(MID(F90, SEARCH(",", F90) + 2, 5))), "Завершена", "В аренде")) -> Завершена | X90: =IFERROR(__xludf.DUMMYFUNCTION("IF(C90 = """", """", IF(REGEXMATCH(C90, ""PCX|NMAX|ADV|CLICK""), ""скутер"", ""мото""))"),"скутер") -> скутер
A91: Завершена | B91: OFF | C91: FORZA 300CC WHITE PHUKET 8950 | D91: Aleksei Lebed | E91: 44981 | F91: 44988 | G91: =IF((E91="")+(F91=""), "", IF(DATEDIF(E91, F91, "d") > 30, DATEDIF(E91, F91, "m") & " М", DATEDIF(E91, F91, "d") & " Д")) -> 7 Д | H91: 700 | I91: =IF(OR(A91="в аренде", A91="в аренде 1", A91="в аренде 2"), J91-K91, "") | J91: =IF(OR(A91="в аренде", A91="в аренде 1", A91="в аренде 2"), DATEDIF(E91, TODAY(), "D")*H91, "") | K91: 4900 | N91: 16900 | O91: =IFERROR(__xludf.DUMMYFUNCTION("IFERROR( VLOOKUP(C91, FILTER( IMPORTRANGE(""https://docs.google.com/spreadsheets/d/1ZBCmVvzoFu7X0td7O5T5xSJplK8m8h9wvdESBc0a1EE/edit#gid=1841437934"", ""Лист1!$C:$I""), IMPORTRANGE(""https://docs.google.com/spreadsheets/d/1ZBCmVvzoFu7X0"&"td7O5T5xSJplK8m8h9wvdESBc0a1EE/edit#gid=1841437934"", ""Лист1!$C:$C"") = C91 ), 7, FALSE ), """" ) "),30225.0) -> 30225 | P91: =IFERROR(__xludf.DUMMYFUNCTION("IF(OR(ISBLANK(Q91), ISBLANK(O91), VALUE(SUBSTITUTE(INDEX(SPLIT(IF(ISBLANK(R91), Q91, R91), "" km""), 0, 1), "" "", """")) - O91 = 0), """", IF(ISBLANK(R91), VALUE(SUBSTITUTE(INDEX(SPLIT(Q91, "" km""), 0, 1), "" "", """")) - O91, VALUE(SUBSTITUTE(INDEX(SPL"&"IT(R91, "" km""), 0, 1), "" "", """")) - O91))"),-13325.0) -> -13325 | Q91: =IF(AND(ISBLANK(N91), ISBLANK(E91), ISBLANK(R91)), "", IF(ISBLANK(R91), TEXT(N91, "#,##0") & " Km, " & TEXT(E91, "dd.mm.yyyy"), R91)) -> 16 900 Km, 24.02.2023 | S91: 200 | T91: 2 | U91: +79219102662 | V91: нормальная семья | W91: =IF(F91 = "", "", IF(NOW() > (DATEVALUE(LEFT(F91, SEARCH(",", F91) - 2)) + TIMEVALUE(MID(F91, SEARCH(",", F91) + 2, 5))), "Завершена", "В аренде")) -> Завершена | X91: =IFERROR(__xludf.DUMMYFUNCTION("IF(C91 = """", """", IF(REGEXMATCH(C91, ""PCX|NMAX|ADV|CLICK""), ""скутер"", ""мото""))"),"мото") -> мото
A92: Завершена | B92: OFF | C92: XMAX 300CC GREY PHUKET 4246 | D92: Aleksandr Sochkov | E92: 44981 | F92: 44990 | G92: =IF((E92="")+(F92=""), "", IF(DATEDIF(E92, F92, "d") > 30, DATEDIF(E92, F92, "m") & " М", DATEDIF(E92, F92, "d") & " Д")) -> 9 Д | H92: 800 | I92: =IF(OR(A92="в аренде", A92="в аренде 1", A92="в аренде 2"), J92-K92, "") | J92: =IF(OR(A92="в аренде", A92="в аренде 1", A92="в аренде 2"), DATEDIF(E92, TODAY(), "D")*H92, "") | K92: 7200 | N92: 16580 | O92: =IFERROR(__xludf.DUMMYFUNCTION("IFERROR( VLOOKUP(C92, FILTER( IMPORTRANGE(""https://docs.google.com/spreadsheets/d/1ZBCmVvzoFu7X0td7O5T5xSJplK8m8h9wvdESBc0a1EE/edit#gid=1841437934"", ""Лист1!$C:$I""), IMPORTRANGE(""https://docs.google.com/spreadsheets/d/1ZBCmVvzoFu7X0"&"td7O5T5xSJplK8m8h9wvdESBc0a1EE/edit#gid=1841437934"", ""Лист1!$C:$C"") = C92 ), 7, FALSE ), """" ) "),38640.0) -> 38640 | P92: =IFERROR(__xludf.DUMMYFUNCTION("IF(OR(ISBLANK(Q92), ISBLANK(O92), VALUE(SUBSTITUTE(INDEX(SPLIT(IF(ISBLANK(R92), Q92, R92), "" km""), 0, 1), "" "", """")) - O92 = 0), """", IF(ISBLANK(R92), VALUE(SUBSTITUTE(INDEX(SPLIT(Q92, "" km""), 0, 1), "" "", """")) - O92, VALUE(SUBSTITUTE(INDEX(SPL"&"IT(R92, "" km""), 0, 1), "" "", """")) - O92))"),-22060.0) -> -22060 | Q92: =IF(AND(ISBLANK(N92), ISBLANK(E92), ISBLANK(R92)), "", IF(ISBLANK(R92), TEXT(N92, "#,##0") & " Km, " & TEXT(E92, "dd.mm.yyyy"), R92)) -> 16 580 Km, 24.02.2023 | S92: 5000 | T92: 2 | U92: +79266030314 | V92: большой адекватный парень | W92: =IF(F92 = "", "", IF(NOW() > (DATEVALUE(LEFT(F92, SEARCH(",", F92) - 2)) + TIMEVALUE(MID(F92, SEARCH(",", F92) + 2, 5))), "Завершена", "В аренде")) -> Завершена | X92: =IFERROR(__xludf.DUMMYFUNCTION("IF(C92 = """", """", IF(REGEXMATCH(C92, ""PCX|NMAX|ADV|CLICK""), ""скутер"", ""мото""))"),"мото") -> мото
A93: Завершена | B93: OFF | C93: NMAX 155CC BLACK GOLD-3 PHUKET 7530 | D93: Anatolii Goncharuk | E93: 44981 | F93: 45009 | G93: =IF((E93="")+(F93=""), "", IF(DATEDIF(E93, F93, "d") > 30, DATEDIF(E93, F93, "m") & " М", DATEDIF(E93, F93, "d") & " Д")) -> 28 Д | H93: =8000/30 -> 266.66667 | I93: =IF(OR(A93="в аренде", A93="в аренде 1", A93="в аренде 2"), J93-K93, "") | J93: =IF(OR(A93="в аренде", A93="в аренде 1", A93="в аренде 2"), DATEDIF(E93, TODAY(), "D")*H93, "") | K93: 8000 | N93: 36200 | O93: =IFERROR(__xludf.DUMMYFUNCTION("IFERROR( VLOOKUP(C93, FILTER( IMPORTRANGE(""https://docs.google.com/spreadsheets/d/1ZBCmVvzoFu7X0td7O5T5xSJplK8m8h9wvdESBc0a1EE/edit#gid=1841437934"", ""Лист1!$C:$I""), IMPORTRANGE(""https://docs.google.com/spreadsheets/d/1ZBCmVvzoFu7X0"&"td7O5T5xSJplK8m8h9wvdESBc0a1EE/edit#gid=1841437934"", ""Лист1!$C:$C"") = C93 ), 7, FALSE ), """" ) "),31000.0) -> 31000 | P93: =IFERROR(__xludf.DUMMYFUNCTION("IF(OR(ISBLANK(Q93), ISBLANK(O93), VALUE(SUBSTITUTE(INDEX(SPLIT(IF(ISBLANK(R93), Q93, R93), "" km""), 0, 1), "" "", """")) - O93 = 0), """", IF(ISBLANK(R93), VALUE(SUBSTITUTE(INDEX(SPLIT(Q93, "" km""), 0, 1), "" "", """")) - O93, VALUE(SUBSTITUTE(INDEX(SPL"&"IT(R93, "" km""), 0, 1), "" "", """")) - O93))"),5200.0) -> 5200 | Q93: =IF(AND(ISBLANK(N93), ISBLANK(E93), ISBLANK(R93)), "", IF(ISBLANK(R93), TEXT(N93, "#,##0") & " Km, " & TEXT(E93, "dd.mm.yyyy"), R93)) -> 36 200 Km, 24.02.2023 | S93: 3000 | T93: 3 | U93: +79031047916 | V93: семейный эксперт | W93: =IF(F93 = "", "", IF(NOW() > (DATEVALUE(LEFT(F93, SEARCH(",", F93) - 2)) + TIMEVALUE(MID(F93, SEARCH(",", F93) + 2, 5))), "Завершена", "В аренде")) -> Завершена | X93: =IFERROR(__xludf.DUMMYFUNCTION("IF(C93 = """", """", IF(REGEXMATCH(C93, ""PCX|NMAX|ADV|CLICK""), ""скутер"", ""мото""))"),"скутер") -> скутер
A94: Завершена | B94: OFF | C94: CBR 650R PHUKET 4505 | D94: Nikita Avtaneev | E94: 44984 | F94: 44985 | G94: =IF((E94="")+(F94=""), "", IF(DATEDIF(E94, F94, "d") > 30, DATEDIF(E94, F94, "m") & " М", DATEDIF(E94, F94, "d") & " Д")) -> 1 Д | H94: 2000 | I94: =IF(OR(A94="в аренде", A94="в аренде 1", A94="в аренде 2"), J94-K94, "") | J94: =IF(OR(A94="в аренде", A94="в аренде 1", A94="в аренде 2"), DATEDIF(E94, TODAY(), "D")*H94, "") | K94: 2000 | N94: 30900 | O94: =IFERROR(__xludf.DUMMYFUNCTION("IFERROR( VLOOKUP(C94, FILTER( IMPORTRANGE(""https://docs.google.com/spreadsheets/d/1ZBCmVvzoFu7X0td7O5T5xSJplK8m8h9wvdESBc0a1EE/edit#gid=1841437934"", ""Лист1!$C:$I""), IMPORTRANGE(""https://docs.google.com/spreadsheets/d/1ZBCmVvzoFu7X0"&"td7O5T5xSJplK8m8h9wvdESBc0a1EE/edit#gid=1841437934"", ""Лист1!$C:$C"") = C94 ), 7, FALSE ), """" ) "),63700.0) -> 63700 | P94: =IFERROR(__xludf.DUMMYFUNCTION("IF(OR(ISBLANK(Q94), ISBLANK(O94), VALUE(SUBSTITUTE(INDEX(SPLIT(IF(ISBLANK(R94), Q94, R94), "" km""), 0, 1), "" "", """")) - O94 = 0), """", IF(ISBLANK(R94), VALUE(SUBSTITUTE(INDEX(SPLIT(Q94, "" km""), 0, 1), "" "", """")) - O94, VALUE(SUBSTITUTE(INDEX(SPL"&"IT(R94, "" km""), 0, 1), "" "", """")) - O94))"),-32800.0) -> -32800 | Q94: =IF(AND(ISBLANK(N94), ISBLANK(E94), ISBLANK(R94)), "", IF(ISBLANK(R94), TEXT(N94, "#,##0") & " Km, " & TEXT(E94, "dd.mm.yyyy"), R94)) -> 30 900 Km, 27.02.2023 | S94: паспорт | T94: 2 | U94: @avtaneev | V94: норм чел есть опыт снимал у ильи | W94: =IF(F94 = "", "", IF(NOW() > (DATEVALUE(LEFT(F94, SEARCH(",", F94) - 2)) + TIMEVALUE(MID(F94, SEARCH(",", F94) + 2, 5))), "Завершена", "В аренде")) -> Завершена | X94: =IFERROR(__xludf.DUMMYFUNCTION("IF(C94 = """", """", IF(REGEXMATCH(C94, ""PCX|NMAX|ADV|CLICK""), ""скутер"", ""мото""))"),"мото") -> мото
A95: Завершена | B95: OFF | C95: NMAX 155CC BLACK GOLD-2 PHUKET 4685 | D95: Egeniy Shumskikh | E95: 44984 | F95: 45014 | G95: =IF((E95="")+(F95=""), "", IF(DATEDIF(E95, F95, "d") > 30, DATEDIF(E95, F95, "m") & " М", DATEDIF(E95, F95, "d") & " Д")) -> 30 Д | H95: =8500/30 -> 283.33333 | I95: =IF(OR(A95="в аренде", A95="в аренде 1", A95="в аренде 2"), J95-K95, "") | J95: =IF(OR(A95="в аренде", A95="в аренде 1", A95="в аренде 2"), DATEDIF(E95, TODAY(), "D")*H95, "") | K95: 8500 | N95: 25000 | O95: =IFERROR(__xludf.DUMMYFUNCTION("IFERROR( VLOOKUP(C95, FILTER( IMPORTRANGE(""https://docs.google.com/spreadsheets/d/1ZBCmVvzoFu7X0td7O5T5xSJplK8m8h9wvdESBc0a1EE/edit#gid=1841437934"", ""Лист1!$C:$I""), IMPORTRANGE(""https://docs.google.com/spreadsheets/d/1ZBCmVvzoFu7X0"&"td7O5T5xSJplK8m8h9wvdESBc0a1EE/edit#gid=1841437934"", ""Лист1!$C:$C"") = C95 ), 7, FALSE ), """" ) "),36400.0) -> 36400 | P95: =IFERROR(__xludf.DUMMYFUNCTION("IF(OR(ISBLANK(Q95), ISBLANK(O95), VALUE(SUBSTITUTE(INDEX(SPLIT(IF(ISBLANK(R95), Q95, R95), "" km""), 0, 1), "" "", """")) - O95 = 0), """", IF(ISBLANK(R95), VALUE(SUBSTITUTE(INDEX(SPLIT(Q95, "" km""), 0, 1), "" "", """")) - O95, VALUE(SUBSTITUTE(INDEX(SPL"&"IT(R95, "" km""), 0, 1), "" "", """")) - O95))"),-11400.0) -> -11400 | Q95: =IF(AND(ISBLANK(N95), ISBLANK(E95), ISBLANK(R95)), "", IF(ISBLANK(R95), TEXT(N95, "#,##0") & " Km, " & TEXT(E95, "dd.mm.yyyy"), R95)) -> 25 000 Km, 27.02.2023 | S95: 3000 | T95: 2 | U95: @purple_noise | V95: нормальная пара | W95: =IF(F95 = "", "", IF(NOW() > (DATEVALUE(LEFT(F95, SEARCH(",", F95) - 2)) + TIMEVALUE(MID(F95, SEARCH(",", F95) + 2, 5))), "Завершена", "В аренде")) -> Завершена | X95: =IFERROR(__xludf.DUMMYFUNCTION("IF(C95 = """", """", IF(REGEXMATCH(C95, ""PCX|NMAX|ADV|CLICK""), ""скутер"", ""мото""))"),"скутер") -> скутер
A96: Завершена | B96: OFF | C96: NMAX 155CC GREEN-B PHUKET 4957 | D96: Никита Моисеев | E96: 44985 | F96: 45036 | G96: =IF((E96="")+(F96=""), "", IF(DATEDIF(E96, F96, "d") > 30, DATEDIF(E96, F96, "m") & " М", DATEDIF(E96, F96, "d") & " Д")) -> 1 М | H96: 250 | I96: =IF(OR(A96="в аренде", A96="в аренде 1", A96="в аренде 2"), J96-K96, "") | J96: =IF(OR(A96="в аренде", A96="в аренде 1", A96="в аренде 2"), DATEDIF(E96, TODAY(), "D")*H96, "") | K96: =1250+1750+1750+750 -> 5500 | N96: 14400 | O96: =IFERROR(__xludf.DUMMYFUNCTION("IFERROR( VLOOKUP(C96, FILTER( IMPORTRANGE(""https://docs.google.com/spreadsheets/d/1ZBCmVvzoFu7X0td7O5T5xSJplK8m8h9wvdESBc0a1EE/edit#gid=1841437934"", ""Лист1!$C:$I""), IMPORTRANGE(""https://docs.google.com/spreadsheets/d/1ZBCmVvzoFu7X0"&"td7O5T5xSJplK8m8h9wvdESBc0a1EE/edit#gid=1841437934"", ""Лист1!$C:$C"") = C96 ), 7, FALSE ), """" ) "),30800.0) -> 30800 | P96: =IFERROR(__xludf.DUMMYFUNCTION("IF(OR(ISBLANK(Q96), ISBLANK(O96), VALUE(SUBSTITUTE(INDEX(SPLIT(IF(ISBLANK(R96), Q96, R96), "" km""), 0, 1), "" "", """")) - O96 = 0), """", IF(ISBLANK(R96), VALUE(SUBSTITUTE(INDEX(SPLIT(Q96, "" km""), 0, 1), "" "", """")) - O96, VALUE(SUBSTITUTE(INDEX(SPL"&"IT(R96, "" km""), 0, 1), "" "", """")) - O96))"),-16400.0) -> -16400 | Q96: =IF(AND(ISBLANK(N96), ISBLANK(E96), ISBLANK(R96)), "", IF(ISBLANK(R96), TEXT(N96, "#,##0") & " Km, " & TEXT(E96, "dd.mm.yyyy"), R96)) -> 14 400 Km, 28.02.2023 | S96: 3000 | T96: 1 | U96: @spacegilly +79958803611 | V96: Мутный Арбитражник возможно скамер | W96: =IF(F96 = "", "", IF(NOW() > (DATEVALUE(LEFT(F96, SEARCH(",", F96) - 2)) + TIMEVALUE(MID(F96, SEARCH(",", F96) + 2, 5))), "Завершена", "В аренде")) -> Завершена | X96: =IFERROR(__xludf.DUMMYFUNCTION("IF(C96 = """", """", IF(REGEXMATCH(C96, ""PCX|NMAX|ADV|CLICK""), ""скутер"", ""мото""))"),"скутер") -> скутер
A97: Завершена | B97: OFF | C97: NMAX 155CC BLACK GREEN PHUKET 4253 | D97: Nikolay Zhidov | E97: 44987 | F97: 44993 | G97: =IF((E97="")+(F97=""), "", IF(DATEDIF(E97, F97, "d") > 30, DATEDIF(E97, F97, "m") & " М", DATEDIF(E97, F97, "d") & " Д")) -> 6 Д | H97: 400 | I97: =IF(OR(A97="в аренде", A97="в аренде 1", A97="в аренде 2"), J97-K97, "") | J97: =IF(OR(A97="в аренде", A97="в аренде 1", A97="в аренде 2"), DATEDIF(E97, TODAY(), "D")*H97, "") | K97: 2400 | N97: 17750 | O97: =IFERROR(__xludf.DUMMYFUNCTION("IFERROR( VLOOKUP(C97, FILTER( IMPORTRANGE(""https://docs.google.com/spreadsheets/d/1ZBCmVvzoFu7X0td7O5T5xSJplK8m8h9wvdESBc0a1EE/edit#gid=1841437934"", ""Лист1!$C:$I""), IMPORTRANGE(""https://docs.google.com/spreadsheets/d/1ZBCmVvzoFu7X0"&"td7O5T5xSJplK8m8h9wvdESBc0a1EE/edit#gid=1841437934"", ""Лист1!$C:$C"") = C97 ), 7, FALSE ), """" ) "),35800.0) -> 35800 | P97: =IFERROR(__xludf.DUMMYFUNCTION("IF(OR(ISBLANK(Q97), ISBLANK(O97), VALUE(SUBSTITUTE(INDEX(SPLIT(IF(ISBLANK(R97), Q97, R97), "" km""), 0, 1), "" "", """")) - O97 = 0), """", IF(ISBLANK(R97), VALUE(SUBSTITUTE(INDEX(SPLIT(Q97, "" km""), 0, 1), "" "", """")) - O97, VALUE(SUBSTITUTE(INDEX(SPL"&"IT(R97, "" km""), 0, 1), "" "", """")) - O97))"),-18050.0) -> -18050 | Q97: =IF(AND(ISBLANK(N97), ISBLANK(E97), ISBLANK(R97)), "", IF(ISBLANK(R97), TEXT(N97, "#,##0") & " Km, " & TEXT(E97, "dd.mm.yyyy"), R97)) -> 17 750 Km, 02.03.2023 | S97: 3000 | T97: 2 | U97: +79602587889 | V97: через ватсап на 6 дней патонг | W97: =IF(F97 = "", "", IF(NOW() > (DATEVALUE(LEFT(F97, SEARCH(",", F97) - 2)) + TIMEVALUE(MID(F97, SEARCH(",", F97) + 2, 5))), "Завершена", "В аренде")) -> Завершена | X97: =IFERROR(__xludf.DUMMYFUNCTION("IF(C97 = """", """", IF(REGEXMATCH(C97, ""PCX|NMAX|ADV|CLICK""), ""скутер"", ""мото""))"),"скутер") -> скутер
A98: Завершена | B98: OFF | C98: XMAX 300CC GREEN PHUKET 4248 | D98: Svatoslav Sobolev | E98: 44987 | F98: 45018 | G98: =IF((E98="")+(F98=""), "", IF(DATEDIF(E98, F98, "d") > 30, DATEDIF(E98, F98, "m") & " М", DATEDIF(E98, F98, "d") & " Д")) -> 1 М | H98: 500 | I98: =IF(OR(A98="в аренде", A98="в аренде 1", A98="в аренде 2"), J98-K98, "") | J98: =IF(OR(A98="в аренде", A98="в аренде 1", A98="в аренде 2"), DATEDIF(E98, TODAY(), "D")*H98, "") | K98: 15000 | N98: 14000 | O98: =IFERROR(__xludf.DUMMYFUNCTION("IFERROR( VLOOKUP(C98, FILTER( IMPORTRANGE(""https://docs.google.com/spreadsheets/d/1ZBCmVvzoFu7X0td7O5T5xSJplK8m8h9wvdESBc0a1EE/edit#gid=1841437934"", ""Лист1!$C:$I""), IMPORTRANGE(""https://docs.google.com/spreadsheets/d/1ZBCmVvzoFu7X0"&"td7O5T5xSJplK8m8h9wvdESBc0a1EE/edit#gid=1841437934"", ""Лист1!$C:$C"") = C98 ), 7, FALSE ), """" ) "),32600.0) -> 32600 | P98: =IFERROR(__xludf.DUMMYFUNCTION("IF(OR(ISBLANK(Q98), ISBLANK(O98), VALUE(SUBSTITUTE(INDEX(SPLIT(IF(ISBLANK(R98), Q98, R98), "" km""), 0, 1), "" "", """")) - O98 = 0), """", IF(ISBLANK(R98), VALUE(SUBSTITUTE(INDEX(SPLIT(Q98, "" km""), 0, 1), "" "", """")) - O98, VALUE(SUBSTITUTE(INDEX(SPL"&"IT(R98, "" km""), 0, 1), "" "", """")) - O98))"),-18600.0) -> -18600 | Q98: =IF(AND(ISBLANK(N98), ISBLANK(E98), ISBLANK(R98)), "", IF(ISBLANK(R98), TEXT(N98, "#,##0") & " Km, " & TEXT(E98, "dd.mm.yyyy"), R98)) -> 14 000 Km, 02.03.2023 | S98: 200 | T98: 0 | U98: @rislingexplorer | V98: не видел его но опытный с потонга | W98: =IF(F98 = "", "", IF(NOW() > (DATEVALUE(LEFT(F98, SEARCH(",", F98) - 2)) + TIMEVALUE(MID(F98, SEARCH(",", F98) + 2, 5))), "Завершена", "В аренде")) -> Завершена | X98: =IFERROR(__xludf.DUMMYFUNCTION("IF(C98 = """", """", IF(REGEXMATCH(C98, ""PCX|NMAX|ADV|CLICK""), ""скутер"", ""мото""))"),"мото") -> мото
A99: Завершена | B99: OFF | C99: XSR 155СС GREEN | D99: Антон | E99: 44987 | F99: 45048 | G99: =IF((E99="")+(F99=""), "", IF(DATEDIF(E99, F99, "d") > 30, DATEDIF(E99, F99, "m") & " М", DATEDIF(E99, F99, "d") & " Д")) -> 2 М | H99: 400 | I99: =IF(OR(A99="в аренде", A99="в аренде 1", A99="в аренде 2"), J99-K99, "") | J99: =IF(OR(A99="в аренде", A99="в аренде 1", A99="в аренде 2"), DATEDIF(E99, TODAY(), "D")*H99, "") | K99: =12000+12000+12000 -> 36000 | N99: 3500 | O99: =IFERROR(__xludf.DUMMYFUNCTION("IFERROR( VLOOKUP(C99, FILTER( IMPORTRANGE(""https://docs.google.com/spreadsheets/d/1ZBCmVvzoFu7X0td7O5T5xSJplK8m8h9wvdESBc0a1EE/edit#gid=1841437934"", ""Лист1!$C:$I""), IMPORTRANGE(""https://docs.google.com/spreadsheets/d/1ZBCmVvzoFu7X0"&"td7O5T5xSJplK8m8h9wvdESBc0a1EE/edit#gid=1841437934"", ""Лист1!$C:$C"") = C99 ), 7, FALSE ), """" ) "),9000.0) -> 9000 | P99: =IFERROR(__xludf.DUMMYFUNCTION("IF(OR(ISBLANK(Q99), ISBLANK(O99), VALUE(SUBSTITUTE(INDEX(SPLIT(IF(ISBLANK(R99), Q99, R99), "" km""), 0, 1), "" "", """")) - O99 = 0), """", IF(ISBLANK(R99), VALUE(SUBSTITUTE(INDEX(SPLIT(Q99, "" km""), 0, 1), "" "", """")) - O99, VALUE(SUBSTITUTE(INDEX(SPL"&"IT(R99, "" km""), 0, 1), "" "", """")) - O99))"),"#VALUE!") -> #VALUE! | Q99: =IF(AND(ISBLANK(N99), ISBLANK(E99), ISBLANK(R99)), "", IF(ISBLANK(R99), TEXT(N99, "#,##0") & " Km, " & TEXT(E99, "dd.mm.yyyy"), R99)) -> полбака возврат | R99: полбака возврат | S99: 10000 | T99: 2 | U99: @rebmalad | V99: добрый казах | W99: =IF(F99 = "", "", IF(NOW() > (DATEVALUE(LEFT(F99, SEARCH(",", F99) - 2)) + TIMEVALUE(MID(F99, SEARCH(",", F99) + 2, 5))), "Завершена", "В аренде")) -> Завершена | X99: =IFERROR(__xludf.DUMMYFUNCTION("IF(C99 = """", """", IF(REGEXMATCH(C99, ""PCX|NMAX|ADV|CLICK""), ""скутер"", ""мото""))"),"мото") -> мото
A100: Завершена | B100: OFF | C100: NMAX 155CC GREEN MATT PHUKET 6901 | D100: Denis Timofeenko | E100: 44989 | F100: 45020 | G100: =IF((E100="")+(F100=""), "", IF(DATEDIF(E100, F100, "d") > 30, DATEDIF(E100, F100, "m") & " М", DATEDIF(E100, F100, "d") & " Д")) -> 1 М | H100: =8000/30 -> 266.66667 | I100: =IF(OR(A100="в аренде", A100="в аренде 1", A100="в аренде 2"), J100-K100, "") | J100: =IF(OR(A100="в аренде", A100="в аренде 1", A100="в аренде 2"), DATEDIF(E100, TODAY(), "D")*H100, "") | K100: 8000 | N100: 23700 | O100: =IFERROR(__xludf.DUMMYFUNCTION("IFERROR( VLOOKUP(C100, FILTER( IMPORTRANGE(""https://docs.google.com/spreadsheets/d/1ZBCmVvzoFu7X0td7O5T5xSJplK8m8h9wvdESBc0a1EE/edit#gid=1841437934"", ""Лист1!$C:$I""), IMPORTRANGE(""https://docs.google.com/spreadsheets/d/1ZBCmVvzoFu7X"&"0td7O5T5xSJplK8m8h9wvdESBc0a1EE/edit#gid=1841437934"", ""Лист1!$C:$C"") = C100 ), 7, FALSE ), """" ) "),"") | P100: =IFERROR(__xludf.DUMMYFUNCTION("IF(OR(ISBLANK(Q100), ISBLANK(O100), VALUE(SUBSTITUTE(INDEX(SPLIT(IF(ISBLANK(R100), Q100, R100), "" km""), 0, 1), "" "", """")) - O100 = 0), """", IF(ISBLANK(R100), VALUE(SUBSTITUTE(INDEX(SPLIT(Q100, "" km""), 0, 1), "" "", """")) - O100, VALUE(SUBSTITUTE("&"INDEX(SPLIT(R100, "" km""), 0, 1), "" "", """")) - O100))"),23700.0) -> 23700 | Q100: =IF(AND(ISBLANK(N100), ISBLANK(E100), ISBLANK(R100)), "", IF(ISBLANK(R100), TEXT(N100, "#,##0") & " Km, " & TEXT(E100, "dd.mm.yyyy"), R100)) -> 23 700 Km, 04.03.2023 | S100: 6000 | T100: 2 | U100: +79692006918 | V100: 1 ый раз катаются | W100: =IF(F100 = "", "", IF(NOW() > (DATEVALUE(LEFT(F100, SEARCH(",", F100) - 2)) + TIMEVALUE(MID(F100, SEARCH(",", F100) + 2, 5))), "Завершена", "В аренде")) -> Завершена | X100: =IFERROR(__xludf.DUMMYFUNCTION("IF(C100 = """", """", IF(REGEXMATCH(C100, ""PCX|NMAX|ADV|CLICK""), ""скутер"", ""мото""))"),"скутер") -> скутер
...

Sheet Лист28

Sheet Календарь бронирования
F1: Даты и срок | H1: Глобальная скидка
F2: 46208 | G2: Дней | H2: Моты 1 | I2: Моты 2 | J2: Скутеры
F3: 46218 | G3: =ABS(F3 - F2) -> 10 | H3: 0.15 | I3: 0.15 | J3: 0.25
A5: =IFERROR(__xludf.DUMMYFUNCTION("IMPORTRANGE(""1ZBCmVvzoFu7X0td7O5T5xSJplK8m8h9wvdESBc0a1EE"", ""Лист1!C3:C"")"),"ADV 350CC BLACK PHUKET 5849") -> ADV 350CC BLACK PHUKET 5849 | D5: =IFERROR(__xludf.DUMMYFUNCTION("ARRAYFORMULA(IF(REGEXMATCH(LOWER(SUBSTITUTE(TRIM(F5:F1896), ""сс"", ""cc"")), ""xmax 300""), ""TRUE"", ""FALSE"")) "),"FALSE") -> FALSE | E5: =IFERROR(__xludf.DUMMYFUNCTION("ARRAYFORMULA(IF(REGEXMATCH(LOWER(SUBSTITUTE(TRIM(F5:F1896), ""сс"", ""cc"")), ""new""), ""TRUE"", ""FALSE""))"),"FALSE") -> FALSE | F5: =IFERROR(__xludf.DUMMYFUNCTION("FILTER( A5:A1896, ARRAYFORMULA( ISNA( VLOOKUP( A5:A1896, FILTER( 'клиенты'!C$122:C1896, ( (('клиенты'!A$122:A1896 = ""В аренде"") * ('клиенты'!B$122:B1896 <> ""ON"")) + ('клиенты'!A"&"$122:A1896 = ""Бронь"") ) * ('клиенты'!E$122:E1896 <= F3) * ('клиенты'!F$122:F1896 >= F2) ), 1, FALSE ) ) ) )"),"ADV 350CC BLACK PHUKET 5849") -> ADV 350CC BLACK PHUKET 5849 | J5: =IFERROR(__xludf.DUMMYFUNCTION("ARRAYFORMULA( IF( ISNUMBER(SEARCH(""XSR 155"", F5:F1896)), ""XSR 155CC | "" & C5:C1896 & "" дней: "" & G3 & "" стоимость: "" & TEXT('цены альт'!G$3, ""# ##0"") & "", депозит: "" & TEXT('цены альт'!H$3, ""# ##0"") & "" бат"", IF( ISNUMB"&"ER(SEARCH(""CB 300"", F5:F1896)), ""CB 300R | "" & C5:C1896 & "" дней: "" & G3 & "" стоимость: "" & TEXT('цены альт'!G$4, ""# ##0"") & "", депозит: "" & TEXT('цены альт'!H$4, ""# ##0"") & "" бат"", IF( ISNUMBER(SEARCH(""REBEL 300"", F5"&":F1896)), ""REBEL 300CC | "" & C5:C1896 & "" дней: "" & G3 & "" стоимость: "" & TEXT('цены альт'!G$5, ""# ##0"") & "", депозит: "" & TEXT('цены альт'!H$5, ""# ##0"") & "" бат"", IF( ISNUMBER(SEARCH(""MT-03 300"", F5:F1896)), "&" ""MT-03 300CC | "" & C5:C1896 & "" дней: "" & G3 & "" стоимость: "" & TEXT('цены альт'!G$6, ""# ##0"") & "", депозит: "" & TEXT('цены альт'!H$6, ""# ##0"") & "" бат"", IF( ISNUMBER(SEARCH(""NINJA 400"", F5:F1896)), "&"""NINJA 400CC | "" & C5:C1896 & "" дней: "" & G3 & "" стоимость: "" & TEXT('цены альт'!G$7, ""# ##0"") & "", депозит: "" & TEXT('цены альт'!H$7, ""# ##0"") & "" бат"", IF( ISNUMBER(SEARCH(""VULCAN 650"", F5:F1896)), "&" ""VULCAN 650CC | "" & C5:C1896 & "" дней: "" & G3 & "" стоимость: "" & TEXT('цены альт'!G$10, ""# ##0"") & "", депозит: "" & TEXT('цены альт'!H$10, ""# ##0"") & "" бат"", IF( ISNUMBER(SEARCH(""CBR 650R"", F5:F1896)), "&" ""CBR 650R | "" & C5:C1896 & "" дней: "" & G3 & "" стоимость: "" & TEXT('цены альт'!G$11, ""# ##0"") & "", депозит: "" & TEXT('цены альт'!H$11, ""# ##0"") & "" бат"", IF( ISNUMBER(SEARCH(""CB 650R"", F5:F1896)), "&" ""CB 650R | "" & C5:C1896 & "" дней: "" & G3 & "" стоимость: "" & TEXT('цены альт'!G$12, ""# ##0"") & "", депозит: "" & TEXT('цены альт'!H$12, ""# ##0"") & "" бат"", IF( ISNUMBER(SEARCH(""XSR 900"", "&"F5:F1896)), ""XSR 900CC | "" & C5:C1896 & "" дней: "" & G3 & "" стоимость: "" & TEXT('цены альт'!G$13, ""# ##0"") & "", депозит: "" & TEXT('цены альт'!H$13, ""# ##0"") & "" бат"", IF( ISNUMBER("&"SEARCH(""R7"", F5:F1896)), ""R7 | "" & C5:C1896 & "" дней: "" & G3 & "" стоимость: "" & TEXT('цены альт'!G$14, ""# ##0"") & "", депозит: "" & TEXT('цены альт'!H$14, ""# ##0"") & "" бат"", IF( "&" ISNUMBER(SEARCH(""CLICK 125"", F5:F1896)), ""CLICK 125CC | "" & C5:C1896 & "" дней: "" & G3 & "" стоимость: "" & TEXT('цены альт'!G$20, ""# ##0"") & "", депозит: "" & TEXT('цены альт'!H$20, ""# ##0"") & "" бат"", "&" IF( ISNUMBER(SEARCH(""PCX 150"", F5:F1896)), ""PCX 150CC | "" & C5:C1896 & "" дней: "" & G3 & "" стоимость: "" & TEXT('цены альт'!G$21, ""# ##0"") & "", депозит: "" & TEXT('цены альт'!H$21, """&"# ##0"") & "" бат"", IF( ISNUMBER(SEARCH(""ADV 150"", F5:F1896)), ""ADV 150CC | "" & C5:C1896 & "" дней: "" & G3 & "" стоимость: "" & TEXT('цены альт'!G$22, ""# ##0"") & "","&" депозит: "" & TEXT('цены альт'!H$22, ""# ##0"") & "" бат"", IF( ISNUMBER(SEARCH(""NMAX 155"", F5:F1896)), ""NMAX 155CC | "" & C5:C1896 & "" дней: "" & G3 & "" стоимос"&"ть: "" & TEXT('цены альт'!G$23, ""# ##0"") & "", депозит: "" & TEXT('цены альт'!H$23, ""# ##0"") & "" бат"", IF( ISNUMBER(SEARCH(""PCX 160"", F5:F1896)), ""PCX 1"&"60CC | "" & C5:C1896 & "" дней: "" & G3 & "" стоимость: "" & TEXT('цены альт'!G$24, ""# ##0"") & "", депозит: "" & TEXT('цены альт'!H$24, ""# ##0"") & "" бат"", IF( ISNUMBER(SEARCH(""ADV 16"&"0"", F5:F1896)), ""ADV 160CC | "" & C5:C1896 & "" дней: "" & G3 & "" стоимость: "" & TEXT('цены альт'!G$25, ""# ##0"") & "", депозит: "" & TEXT('цены альт'!H$25, ""# ##0"") & "" бат"", IF"&"( ISNUMBER(SEARCH(""FORZA 300"", F5:F1896)), ""FORZA 300CC | "" & C5:C1896 & "" дней: "" & G3 & "" стоимость: "" & TEXT('цены альт'!G$26, ""# ##0"") & "", депозит: "" & TEXT('цены аль"&"т'!H$26, ""# ##0"") & "" бат"", IF( (REGEXMATCH(LOWER(SUBSTITUTE(TRIM(F5:F1896), ""сс"", ""cc"")), ""xmax 300"") * NOT(REGEXMATCH(LOWER(SUBSTITUTE(TRIM(F5:F1896), ""сс"", ""cc"")), "&"""new""))), ""XMAX 300CC | "" & C5:C1896 & "" дней: "" & G3 & "" стоимость: "" & TEXT('цены альт'!G$27, ""# ##0"") & "", депозит: "" & TEXT('цены альт'!H$27, ""# ##0"") & "" бат"", "&" IF( ISNUMBER(SEARCH(""XMAX 300CC NEW"", F5:F1896)), ""XMAX 300CC НОВОЕ ПОКОЛЕНИЕ | "" & C5:C1896 & "" дней: "" & G3 & "" стоимость: "" & TEXT('цены альт'!G$28, ""# ##0"") & "&""", депозит: "" & TEXT('цены альт'!H$28, ""# ##0"") & "" бат"", IF( ISNUMBER(SEARCH(""ADV 350"", F5:F1896)), ""ADV 350CC | "" & C5:"&"C1896 & "" дней: "" & G3 & "" стоимость: "" & TEXT('цены альт'!G$29, ""# ##0"") & "", депозит: "" & TEXT('цены альт'!H$29, ""# ##0"") & "" бат"", IF( ISNUMBER(SEARCH(""X"&"ADV 750"", F5:F1896)), ""XADV 750CC | "" & C5:C1896 & "" дней: "" & G3 & "" стоимость: "" & TEXT('цены альт'!G$30, ""# ##0"") & "", депозит: "" & TEXT('цены альт'!H$30, ""# ##0"") & "" бат"", "&" """" ) ) ) ) ) "&" ) ) ) ) ) ) ) ) ) ) ) ) "&" ) ) ) ) ) "),"ADV 350CC | дней: 10 стоимость: 6816 (Скидка за срок 9%, 682 в день), депозит: 7 000 бат") -> ADV 350CC | дней: 10 стоимость: 6816 (Скидка за срок 9%, 682 в день), депозит: 7 000 бат
A6: =IFERROR(__xludf.DUMMYFUNCTION("""COMPUTED_VALUE"""),"ADV 350CC GREY BKK 798") -> ADV 350CC GREY BKK 798 | D6: =IFERROR(__xludf.DUMMYFUNCTION("""COMPUTED_VALUE"""),"FALSE") -> FALSE | E6: =IFERROR(__xludf.DUMMYFUNCTION("""COMPUTED_VALUE"""),"FALSE") -> FALSE | F6: =IFERROR(__xludf.DUMMYFUNCTION("""COMPUTED_VALUE"""),"ADV 350CC GREY BKK 798") -> ADV 350CC GREY BKK 798 | J6: =IFERROR(__xludf.DUMMYFUNCTION("""COMPUTED_VALUE"""),"ADV 350CC | дней: 10 стоимость: 6816 (Скидка за срок 9%, 682 в день), депозит: 7 000 бат") -> ADV 350CC | дней: 10 стоимость: 6816 (Скидка за срок 9%, 682 в день), депозит: 7 000 бат
A7: =IFERROR(__xludf.DUMMYFUNCTION("""COMPUTED_VALUE"""),"CB 300CC R 9011") -> CB 300CC R 9011 | D7: =IFERROR(__xludf.DUMMYFUNCTION("""COMPUTED_VALUE"""),"FALSE") -> FALSE | E7: =IFERROR(__xludf.DUMMYFUNCTION("""COMPUTED_VALUE"""),"FALSE") -> FALSE | F7: =IFERROR(__xludf.DUMMYFUNCTION("""COMPUTED_VALUE"""),"CBR 650R PHUKET 4505") -> CBR 650R PHUKET 4505 | J7: =IFERROR(__xludf.DUMMYFUNCTION("""COMPUTED_VALUE"""),"CBR 650R | дней: 10 стоимость: 13141 (Скидка за срок 14%, 1314 в день), депозит: 20 000 бат") -> CBR 650R | дней: 10 стоимость: 13141 (Скидка за срок 14%, 1314 в день), депозит: 20 000 бат
A8: =IFERROR(__xludf.DUMMYFUNCTION("""COMPUTED_VALUE"""),"CBR 650R PHUKET 4505") -> CBR 650R PHUKET 4505 | D8: =IFERROR(__xludf.DUMMYFUNCTION("""COMPUTED_VALUE"""),"FALSE") -> FALSE | E8: =IFERROR(__xludf.DUMMYFUNCTION("""COMPUTED_VALUE"""),"FALSE") -> FALSE | F8: =IFERROR(__xludf.DUMMYFUNCTION("""COMPUTED_VALUE"""),"NINJA 400СС PHUKET 6334") -> NINJA 400СС PHUKET 6334 | J8: =IFERROR(__xludf.DUMMYFUNCTION("""COMPUTED_VALUE"""),"NINJA 400CC | дней: 10 стоимость: 8660 (Скидка за срок 14%, 866 в день), депозит: 20 000 бат") -> NINJA 400CC | дней: 10 стоимость: 8660 (Скидка за срок 14%, 866 в день), депозит: 20 000 бат
A9: =IFERROR(__xludf.DUMMYFUNCTION("""COMPUTED_VALUE"""),"CLICK 125CC PHUKET 5580") -> CLICK 125CC PHUKET 5580 | D9: =IFERROR(__xludf.DUMMYFUNCTION("""COMPUTED_VALUE"""),"FALSE") -> FALSE | E9: =IFERROR(__xludf.DUMMYFUNCTION("""COMPUTED_VALUE"""),"FALSE") -> FALSE | F9: =IFERROR(__xludf.DUMMYFUNCTION("""COMPUTED_VALUE"""),"NMAX 155CC BLACK GOLD PHUKET 4255") -> NMAX 155CC BLACK GOLD PHUKET 4255 | J9: =IFERROR(__xludf.DUMMYFUNCTION("""COMPUTED_VALUE"""),"NMAX 155CC | дней: 10 стоимость: 3067 (Скидка за срок 9%, 307 в день), депозит: 3 000 бат") -> NMAX 155CC | дней: 10 стоимость: 3067 (Скидка за срок 9%, 307 в день), депозит: 3 000 бат
A10: =IFERROR(__xludf.DUMMYFUNCTION("""COMPUTED_VALUE"""),"FORZA 300CC WHITE PHUKET 8950") -> FORZA 300CC WHITE PHUKET 8950 | D10: =IFERROR(__xludf.DUMMYFUNCTION("""COMPUTED_VALUE"""),"FALSE") -> FALSE | E10: =IFERROR(__xludf.DUMMYFUNCTION("""COMPUTED_VALUE"""),"FALSE") -> FALSE | F10: =IFERROR(__xludf.DUMMYFUNCTION("""COMPUTED_VALUE"""),"NMAX 155CC BLACK GOLD-2 PHUKET 4685") -> NMAX 155CC BLACK GOLD-2 PHUKET 4685 | J10: =IFERROR(__xludf.DUMMYFUNCTION("""COMPUTED_VALUE"""),"NMAX 155CC | дней: 10 стоимость: 3067 (Скидка за срок 9%, 307 в день), депозит: 3 000 бат") -> NMAX 155CC | дней: 10 стоимость: 3067 (Скидка за срок 9%, 307 в день), депозит: 3 000 бат
A11: =IFERROR(__xludf.DUMMYFUNCTION("""COMPUTED_VALUE"""),"MT-03 300СС BLUE PHUKET 5068") -> MT-03 300СС BLUE PHUKET 5068 | D11: =IFERROR(__xludf.DUMMYFUNCTION("""COMPUTED_VALUE"""),"FALSE") -> FALSE | E11: =IFERROR(__xludf.DUMMYFUNCTION("""COMPUTED_VALUE"""),"FALSE") -> FALSE | F11: =IFERROR(__xludf.DUMMYFUNCTION("""COMPUTED_VALUE"""),"NMAX 155CC BLACK GOLD-3 PHUKET 7530") -> NMAX 155CC BLACK GOLD-3 PHUKET 7530 | J11: =IFERROR(__xludf.DUMMYFUNCTION("""COMPUTED_VALUE"""),"NMAX 155CC | дней: 10 стоимость: 3067 (Скидка за срок 9%, 307 в день), депозит: 3 000 бат") -> NMAX 155CC | дней: 10 стоимость: 3067 (Скидка за срок 9%, 307 в день), депозит: 3 000 бат
A12: =IFERROR(__xludf.DUMMYFUNCTION("""COMPUTED_VALUE"""),"NINJA 400СС PHUKET 6334") -> NINJA 400СС PHUKET 6334 | D12: =IFERROR(__xludf.DUMMYFUNCTION("""COMPUTED_VALUE"""),"FALSE") -> FALSE | E12: =IFERROR(__xludf.DUMMYFUNCTION("""COMPUTED_VALUE"""),"FALSE") -> FALSE | F12: =IFERROR(__xludf.DUMMYFUNCTION("""COMPUTED_VALUE"""),"NMAX 155CC BLACK PHUKET 8952") -> NMAX 155CC BLACK PHUKET 8952 | J12: =IFERROR(__xludf.DUMMYFUNCTION("""COMPUTED_VALUE"""),"NMAX 155CC | дней: 10 стоимость: 3067 (Скидка за срок 9%, 307 в день), депозит: 3 000 бат") -> NMAX 155CC | дней: 10 стоимость: 3067 (Скидка за срок 9%, 307 в день), депозит: 3 000 бат
A13: =IFERROR(__xludf.DUMMYFUNCTION("""COMPUTED_VALUE"""),"NMAX 155CC BLACK GOLD PHUKET 4255") -> NMAX 155CC BLACK GOLD PHUKET 4255 | D13: =IFERROR(__xludf.DUMMYFUNCTION("""COMPUTED_VALUE"""),"FALSE") -> FALSE | E13: =IFERROR(__xludf.DUMMYFUNCTION("""COMPUTED_VALUE"""),"FALSE") -> FALSE | F13: =IFERROR(__xludf.DUMMYFUNCTION("""COMPUTED_VALUE"""),"NMAX 155CC GREEN-B PHUKET 4957") -> NMAX 155CC GREEN-B PHUKET 4957 | J13: =IFERROR(__xludf.DUMMYFUNCTION("""COMPUTED_VALUE"""),"NMAX 155CC | дней: 10 стоимость: 3067 (Скидка за срок 9%, 307 в день), депозит: 3 000 бат") -> NMAX 155CC | дней: 10 стоимость: 3067 (Скидка за срок 9%, 307 в день), депозит: 3 000 бат
A14: =IFERROR(__xludf.DUMMYFUNCTION("""COMPUTED_VALUE"""),"NMAX 155CC BLACK GOLD-2 PHUKET 4685") -> NMAX 155CC BLACK GOLD-2 PHUKET 4685 | D14: =IFERROR(__xludf.DUMMYFUNCTION("""COMPUTED_VALUE"""),"FALSE") -> FALSE | E14: =IFERROR(__xludf.DUMMYFUNCTION("""COMPUTED_VALUE"""),"FALSE") -> FALSE | F14: =IFERROR(__xludf.DUMMYFUNCTION("""COMPUTED_VALUE"""),"NMAX 155CC GREY GOLD PHUKET 6908") -> NMAX 155CC GREY GOLD PHUKET 6908 | J14: =IFERROR(__xludf.DUMMYFUNCTION("""COMPUTED_VALUE"""),"NMAX 155CC | дней: 10 стоимость: 3067 (Скидка за срок 9%, 307 в день), депозит: 3 000 бат") -> NMAX 155CC | дней: 10 стоимость: 3067 (Скидка за срок 9%, 307 в день), депозит: 3 000 бат
A15: =IFERROR(__xludf.DUMMYFUNCTION("""COMPUTED_VALUE"""),"NMAX 155CC BLACK GOLD-3 PHUKET 7530") -> NMAX 155CC BLACK GOLD-3 PHUKET 7530 | D15: =IFERROR(__xludf.DUMMYFUNCTION("""COMPUTED_VALUE"""),"FALSE") -> FALSE | E15: =IFERROR(__xludf.DUMMYFUNCTION("""COMPUTED_VALUE"""),"FALSE") -> FALSE | F15: =IFERROR(__xludf.DUMMYFUNCTION("""COMPUTED_VALUE"""),"NMAX 155CC RACE PHUKET 7532") -> NMAX 155CC RACE PHUKET 7532 | J15: =IFERROR(__xludf.DUMMYFUNCTION("""COMPUTED_VALUE"""),"NMAX 155CC | дней: 10 стоимость: 3067 (Скидка за срок 9%, 307 в день), депозит: 3 000 бат") -> NMAX 155CC | дней: 10 стоимость: 3067 (Скидка за срок 9%, 307 в день), депозит: 3 000 бат
A16: =IFERROR(__xludf.DUMMYFUNCTION("""COMPUTED_VALUE"""),"NMAX 155CC BLACK GREEN PHUKET 4253") -> NMAX 155CC BLACK GREEN PHUKET 4253 | D16: =IFERROR(__xludf.DUMMYFUNCTION("""COMPUTED_VALUE"""),"FALSE") -> FALSE | E16: =IFERROR(__xludf.DUMMYFUNCTION("""COMPUTED_VALUE"""),"FALSE") -> FALSE | F16: =IFERROR(__xludf.DUMMYFUNCTION("""COMPUTED_VALUE"""),"NMAX 155CC RED WHITE PHUKET 9548") -> NMAX 155CC RED WHITE PHUKET 9548 | J16: =IFERROR(__xludf.DUMMYFUNCTION("""COMPUTED_VALUE"""),"NMAX 155CC | дней: 10 стоимость: 3067 (Скидка за срок 9%, 307 в день), депозит: 3 000 бат") -> NMAX 155CC | дней: 10 стоимость: 3067 (Скидка за срок 9%, 307 в день), депозит: 3 000 бат
A17: =IFERROR(__xludf.DUMMYFUNCTION("""COMPUTED_VALUE"""),"NMAX 155CC BLACK PHUKET 8952") -> NMAX 155CC BLACK PHUKET 8952 | D17: =IFERROR(__xludf.DUMMYFUNCTION("""COMPUTED_VALUE"""),"FALSE") -> FALSE | E17: =IFERROR(__xludf.DUMMYFUNCTION("""COMPUTED_VALUE"""),"FALSE") -> FALSE | F17: =IFERROR(__xludf.DUMMYFUNCTION("""COMPUTED_VALUE"""),"VULCAN 650CC S PHUKET 5065") -> VULCAN 650CC S PHUKET 5065 | J17: =IFERROR(__xludf.DUMMYFUNCTION("""COMPUTED_VALUE"""),"VULCAN 650CC | дней: 10 стоимость: 13141 (Скидка за срок 14%, 1314 в день), депозит: 20 000 бат") -> VULCAN 650CC | дней: 10 стоимость: 13141 (Скидка за срок 14%, 1314 в день), депозит: 20 000 бат
A18: =IFERROR(__xludf.DUMMYFUNCTION("""COMPUTED_VALUE"""),"NMAX 155CC GREEN-B PHUKET 4957") -> NMAX 155CC GREEN-B PHUKET 4957 | D18: =IFERROR(__xludf.DUMMYFUNCTION("""COMPUTED_VALUE"""),"TRUE") -> TRUE | E18: =IFERROR(__xludf.DUMMYFUNCTION("""COMPUTED_VALUE"""),"TRUE") -> TRUE | F18: =IFERROR(__xludf.DUMMYFUNCTION("""COMPUTED_VALUE"""),"XMAX 300CC NEW RED GLOSS BKK 5709") -> XMAX 300CC NEW RED GLOSS BKK 5709 | J18: =IFERROR(__xludf.DUMMYFUNCTION("""COMPUTED_VALUE"""),"XMAX 300CC НОВОЕ ПОКОЛЕНИЕ | дней: 10 стоимость: 6406 (Скидка за срок 9%, 641 в день), депозит: 7 000 бат") -> XMAX 300CC НОВОЕ ПОКОЛЕНИЕ | дней: 10 стоимость: 6406 (Скидка за срок 9%, 641 в день), депозит: 7 000 бат
A19: =IFERROR(__xludf.DUMMYFUNCTION("""COMPUTED_VALUE"""),"NMAX 155CC GREY GOLD PHUKET 6908") -> NMAX 155CC GREY GOLD PHUKET 6908 | D19: =IFERROR(__xludf.DUMMYFUNCTION("""COMPUTED_VALUE"""),"TRUE") -> TRUE | E19: =IFERROR(__xludf.DUMMYFUNCTION("""COMPUTED_VALUE"""),"FALSE") -> FALSE | F19: =IFERROR(__xludf.DUMMYFUNCTION("""COMPUTED_VALUE"""),"XMAX 300CC BLUE PHUKET 5773") -> XMAX 300CC BLUE PHUKET 5773 | J19: =IFERROR(__xludf.DUMMYFUNCTION("""COMPUTED_VALUE"""),"XMAX 300CC | дней: 10 стоимость: 5396 (Скидка за срок 9%, 540 в день), депозит: 5 000 бат") -> XMAX 300CC | дней: 10 стоимость: 5396 (Скидка за срок 9%, 540 в день), депозит: 5 000 бат
A20: =IFERROR(__xludf.DUMMYFUNCTION("""COMPUTED_VALUE"""),"NMAX 155CC GREY PHUKET 5960") -> NMAX 155CC GREY PHUKET 5960 | D20: =IFERROR(__xludf.DUMMYFUNCTION("""COMPUTED_VALUE"""),"TRUE") -> TRUE | E20: =IFERROR(__xludf.DUMMYFUNCTION("""COMPUTED_VALUE"""),"FALSE") -> FALSE | F20: =IFERROR(__xludf.DUMMYFUNCTION("""COMPUTED_VALUE"""),"XMAX 300CC GREEN PHUKET 4248") -> XMAX 300CC GREEN PHUKET 4248 | J20: =IFERROR(__xludf.DUMMYFUNCTION("""COMPUTED_VALUE"""),"XMAX 300CC | дней: 10 стоимость: 5396 (Скидка за срок 9%, 540 в день), депозит: 5 000 бат") -> XMAX 300CC | дней: 10 стоимость: 5396 (Скидка за срок 9%, 540 в день), депозит: 5 000 бат
A21: =IFERROR(__xludf.DUMMYFUNCTION("""COMPUTED_VALUE"""),"NMAX 155CC RACE PHUKET 7532") -> NMAX 155CC RACE PHUKET 7532 | D21: =IFERROR(__xludf.DUMMYFUNCTION("""COMPUTED_VALUE"""),"TRUE") -> TRUE | E21: =IFERROR(__xludf.DUMMYFUNCTION("""COMPUTED_VALUE"""),"FALSE") -> FALSE | F21: =IFERROR(__xludf.DUMMYFUNCTION("""COMPUTED_VALUE"""),"XMAX 300CC GREY PHUKET 4246") -> XMAX 300CC GREY PHUKET 4246 | J21: =IFERROR(__xludf.DUMMYFUNCTION("""COMPUTED_VALUE"""),"XMAX 300CC | дней: 10 стоимость: 5396 (Скидка за срок 9%, 540 в день), депозит: 5 000 бат") -> XMAX 300CC | дней: 10 стоимость: 5396 (Скидка за срок 9%, 540 в день), депозит: 5 000 бат
A22: =IFERROR(__xludf.DUMMYFUNCTION("""COMPUTED_VALUE"""),"NMAX 155CC RED WHITE PHUKET 9548") -> NMAX 155CC RED WHITE PHUKET 9548 | D22: =IFERROR(__xludf.DUMMYFUNCTION("""COMPUTED_VALUE"""),"FALSE") -> FALSE | E22: =IFERROR(__xludf.DUMMYFUNCTION("""COMPUTED_VALUE"""),"FALSE") -> FALSE | F22: =IFERROR(__xludf.DUMMYFUNCTION("""COMPUTED_VALUE"""),"XSR 155СС BLACK PHUKET 8949") -> XSR 155СС BLACK PHUKET 8949 | J22: =IFERROR(__xludf.DUMMYFUNCTION("""COMPUTED_VALUE"""),"XSR 155CC | дней: 10 стоимость: 4568 (Скидка за срок 9%, 457 в день), депозит: 7 000 бат") -> XSR 155CC | дней: 10 стоимость: 4568 (Скидка за срок 9%, 457 в день), депозит: 7 000 бат
A23: =IFERROR(__xludf.DUMMYFUNCTION("""COMPUTED_VALUE"""),"VULCAN 650CC S PHUKET 5065") -> VULCAN 650CC S PHUKET 5065 | D23: =IFERROR(__xludf.DUMMYFUNCTION("""COMPUTED_VALUE"""),"FALSE") -> FALSE | E23: =IFERROR(__xludf.DUMMYFUNCTION("""COMPUTED_VALUE"""),"FALSE") -> FALSE | F23: =IFERROR(__xludf.DUMMYFUNCTION("""COMPUTED_VALUE"""),"XSR 155СС GREEN") -> XSR 155СС GREEN | J23: =IFERROR(__xludf.DUMMYFUNCTION("""COMPUTED_VALUE"""),"XSR 155CC | дней: 10 стоимость: 4568 (Скидка за срок 9%, 457 в день), депозит: 7 000 бат") -> XSR 155CC | дней: 10 стоимость: 4568 (Скидка за срок 9%, 457 в день), депозит: 7 000 бат
A24: =IFERROR(__xludf.DUMMYFUNCTION("""COMPUTED_VALUE"""),"XMAX 300CC NEW RED GLOSS BKK 5709") -> XMAX 300CC NEW RED GLOSS BKK 5709 | D24: =IFERROR(__xludf.DUMMYFUNCTION("""COMPUTED_VALUE"""),"TRUE") -> TRUE | E24: =IFERROR(__xludf.DUMMYFUNCTION("""COMPUTED_VALUE"""),"TRUE") -> TRUE | F24: =IFERROR(__xludf.DUMMYFUNCTION("""COMPUTED_VALUE"""),"XMAX 300CC NEW BLACK PHUKET 8969") -> XMAX 300CC NEW BLACK PHUKET 8969 | J24: =IFERROR(__xludf.DUMMYFUNCTION("""COMPUTED_VALUE"""),"XMAX 300CC НОВОЕ ПОКОЛЕНИЕ | дней: 10 стоимость: 6406 (Скидка за срок 9%, 641 в день), депозит: 7 000 бат") -> XMAX 300CC НОВОЕ ПОКОЛЕНИЕ | дней: 10 стоимость: 6406 (Скидка за срок 9%, 641 в день), депозит: 7 000 бат
A25: =IFERROR(__xludf.DUMMYFUNCTION("""COMPUTED_VALUE"""),"XMAX 300CC BLUE PHUKET 5773") -> XMAX 300CC BLUE PHUKET 5773 | D25: =IFERROR(__xludf.DUMMYFUNCTION("""COMPUTED_VALUE"""),"TRUE") -> TRUE | E25: =IFERROR(__xludf.DUMMYFUNCTION("""COMPUTED_VALUE"""),"TRUE") -> TRUE | F25: =IFERROR(__xludf.DUMMYFUNCTION("""COMPUTED_VALUE"""),"XMAX 300CC NEW BLUE PHUKET 1813") -> XMAX 300CC NEW BLUE PHUKET 1813 | J25: =IFERROR(__xludf.DUMMYFUNCTION("""COMPUTED_VALUE"""),"XMAX 300CC НОВОЕ ПОКОЛЕНИЕ | дней: 10 стоимость: 6406 (Скидка за срок 9%, 641 в день), депозит: 7 000 бат") -> XMAX 300CC НОВОЕ ПОКОЛЕНИЕ | дней: 10 стоимость: 6406 (Скидка за срок 9%, 641 в день), депозит: 7 000 бат
A26: =IFERROR(__xludf.DUMMYFUNCTION("""COMPUTED_VALUE"""),"XMAX 300CC GREEN PHUKET 4248") -> XMAX 300CC GREEN PHUKET 4248 | D26: =IFERROR(__xludf.DUMMYFUNCTION("""COMPUTED_VALUE"""),"FALSE") -> FALSE | E26: =IFERROR(__xludf.DUMMYFUNCTION("""COMPUTED_VALUE"""),"FALSE") -> FALSE | F26: =IFERROR(__xludf.DUMMYFUNCTION("""COMPUTED_VALUE"""),"ADV 350CC DARK GREY BANGKOK 6895") -> ADV 350CC DARK GREY BANGKOK 6895 | J26: =IFERROR(__xludf.DUMMYFUNCTION("""COMPUTED_VALUE"""),"ADV 350CC | дней: 10 стоимость: 6816 (Скидка за срок 9%, 682 в день), депозит: 7 000 бат") -> ADV 350CC | дней: 10 стоимость: 6816 (Скидка за срок 9%, 682 в день), депозит: 7 000 бат
A27: =IFERROR(__xludf.DUMMYFUNCTION("""COMPUTED_VALUE"""),"XMAX 300CC GREY PHUKET 4246") -> XMAX 300CC GREY PHUKET 4246 | D27: =IFERROR(__xludf.DUMMYFUNCTION("""COMPUTED_VALUE"""),"TRUE") -> TRUE | E27: =IFERROR(__xludf.DUMMYFUNCTION("""COMPUTED_VALUE"""),"TRUE") -> TRUE | F27: =IFERROR(__xludf.DUMMYFUNCTION("""COMPUTED_VALUE"""),"XMAX 300CC NEW RED GLOSS 2 PHUKET 4729") -> XMAX 300CC NEW RED GLOSS 2 PHUKET 4729 | J27: =IFERROR(__xludf.DUMMYFUNCTION("""COMPUTED_VALUE"""),"XMAX 300CC НОВОЕ ПОКОЛЕНИЕ | дней: 10 стоимость: 6406 (Скидка за срок 9%, 641 в день), депозит: 7 000 бат") -> XMAX 300CC НОВОЕ ПОКОЛЕНИЕ | дней: 10 стоимость: 6406 (Скидка за срок 9%, 641 в день), депозит: 7 000 бат
A28: =IFERROR(__xludf.DUMMYFUNCTION("""COMPUTED_VALUE"""),"XSR 155СС BLACK PHUKET 8949") -> XSR 155СС BLACK PHUKET 8949 | D28: =IFERROR(__xludf.DUMMYFUNCTION("""COMPUTED_VALUE"""),"TRUE") -> TRUE | E28: =IFERROR(__xludf.DUMMYFUNCTION("""COMPUTED_VALUE"""),"TRUE") -> TRUE | F28: =IFERROR(__xludf.DUMMYFUNCTION("""COMPUTED_VALUE"""),"XMAX 300CC NEW BROWN BANGKOK 9315") -> XMAX 300CC NEW BROWN BANGKOK 9315 | J28: =IFERROR(__xludf.DUMMYFUNCTION("""COMPUTED_VALUE"""),"XMAX 300CC НОВОЕ ПОКОЛЕНИЕ | дней: 10 стоимость: 6406 (Скидка за срок 9%, 641 в день), депозит: 7 000 бат") -> XMAX 300CC НОВОЕ ПОКОЛЕНИЕ | дней: 10 стоимость: 6406 (Скидка за срок 9%, 641 в день), депозит: 7 000 бат
A29: =IFERROR(__xludf.DUMMYFUNCTION("""COMPUTED_VALUE"""),"XSR 155СС GREEN") -> XSR 155СС GREEN | D29: =IFERROR(__xludf.DUMMYFUNCTION("""COMPUTED_VALUE"""),"FALSE") -> FALSE | E29: =IFERROR(__xludf.DUMMYFUNCTION("""COMPUTED_VALUE"""),"FALSE") -> FALSE | F29: =IFERROR(__xludf.DUMMYFUNCTION("""COMPUTED_VALUE"""),"ADV 350CC RED BKK 9890") -> ADV 350CC RED BKK 9890 | J29: =IFERROR(__xludf.DUMMYFUNCTION("""COMPUTED_VALUE"""),"ADV 350CC | дней: 10 стоимость: 6816 (Скидка за срок 9%, 682 в день), депозит: 7 000 бат") -> ADV 350CC | дней: 10 стоимость: 6816 (Скидка за срок 9%, 682 в день), депозит: 7 000 бат
